Workbook

Sheet LotV62
A2: THE PIT — lot V62
A3: Fichier V54 conservé. Un dessin ou une case jouable ne certifie pas un kit complet ni une fidélité 1:1.
B4: Nouveaux PNG intégrés | D4: Dessins natifs intégrés | G4: Publication
B5: =SUM(E9:E26) -> 31 | D5: =SUM(F9:F26) -> 86 | G5: Non vérifiée dans ce suivi
A6: Les icônes dérivées et les poses tenues réutilisées ne sont pas de nouveaux dessins.
A8: Chantier | B8: Élément | C8: Nature | D8: État | E8: PNG | F8: Dessins | G8: Vérification | H8: Limites | J8: Sources
A9: Combattant | B9: Emissary PHG — portrait | C9: Portrait | D9: Intégré | E9: 1 | F9: 1 | G9: Parcours Chrome V62, deux côtés, mobile et pixels natifs vérifiés. | H9: Une case distincte des deux Emissary du film. Tenue partiellement reconstruite. | J9: Emissary PHG — portrait 02_PERSONNAGES!A207:V207 / 03_MANQUANTS!A12:L12 IllFonic, mise à jour 2.39 https://forum.predator.illfonic.com/t/patch-notes-2-39/27316
A10: Combattant | B10: Emissary PHG — garde vers la droite | C10: Animation idle | D10: Intégré | E10: 1 | F10: 6 | G10: Parcours Chrome V62, deux côtés, mobile et pixels natifs vérifiés. | H10: Six dessins natifs. Déplacements et attaques non dessinés : pose tenue, pas de nouveau clip. | J10: Emissary PHG — garde vers la droite 02_PERSONNAGES!A207:V207 / 03_MANQUANTS!A12:L12 IllFonic, mise à jour 2.39 https://forum.predator.illfonic.com/t/patch-notes-2-39/27316
A11: Combattant | B11: Emissary PHG — garde vers la gauche | C11: Animation idle | D11: Intégré | E11: 1 | F11: 6 | G11: Parcours Chrome V62, deux côtés, mobile et pixels natifs vérifiés. | H11: Six dessins natifs. Déplacements et attaques non dessinés : pose tenue, pas de nouveau clip. | J11: Emissary PHG — garde vers la gauche 02_PERSONNAGES!A207:V207 / 03_MANQUANTS!A12:L12 IllFonic, mise à jour 2.39 https://forum.predator.illfonic.com/t/patch-notes-2-39/27316
A12: Identités | B12: Samurai, Emissary, Golden Angel, Classic et Captive | C12: Clarification | D12: Intégré | E12: 0 | F12: 0 | G12: Variantes, IDs, ordre et bitmaps historiques conservés. | H12: Samurai était déjà présent. Les dix dossiers nouveaux/candidats ne sont pas dix absences de case. | J12: Samurai, Emissary, Golden Angel, Classic et Captive v62-workbook-roster-audit.json / sources primaires citées
A13: Masques | B13: 14 biomasks référencés | C13: Remplacement | D13: Intégré | E13: 14 | F13: 14 | G13: 53 tests passent. Chrome :26 sélections,14 toggles,2 rechargements, aucune erreur. 28 anciens fichiers inchangés. | H13: Recréations guidées par références licenciées. Détails cachés, usure et microgravures interprétés. Pas de certification 1:1. | J13: 14 biomasks référencés BIOMASQUES-V62.md / biomask-generation-receipts.json
A14: Masques | B14: Anciens dessins préservés et renommés | C14: Conservation | D14: Intégré | E14: 0 | F14: 0 | G14: 28 fichiers historiques inchangés, empreintes vérifiées. | H14: 11 anciens V3 équipables sous IDs clan-*. Elder devient Couronne des Ancêtres. Quatre études V14 restent en galerie. Noms originaux du projet. | J14: Anciens dessins préservés et renommés BIOMASQUES-V62.md
A15: Personnage modulaire | B15: Têtes Classic, Elder, Super et Feral | C15: Remplacement | D15: Intégré | E15: 4 | F15: 4 | G15: 68 compositions DOM/Canvas contrôlées, revue visuelle représentative. Placement et teintes du rig corrigés. | H15: Quatre dessins pour six morphologies. Classic réutilisé pour Young et Huntress. Pas de nouveaux cycles faciaux. Orientation 3/4 adaptée au rig. | J15: Têtes Classic, Elder, Super et Feral modular-head-classic.json / modular-head-families.json / v62-head-composition-qa.json
A16: Arène 126 | B16: Evacuants adultes anonymes — passage lointain | C16: Animation de fond | D16: Intégré | E16: 1 | F16: 6 | G16: Chrome :3 arènes,54 cellules natives, mobile et panne503/reprise. Composition :44 caméras. Tests ciblés passés. | H16: Toit intact, ambiance d'exposition avant destruction. Evacuants adultes et appareil anonymes originaux ; aucune identité de survivant, route narrative ou continuité d'équipement de Wolf certifiée. | J16: Evacuants adultes anonymes — passage lointain 10_VIE_DES_STAGES!E62 / 10_VIE_DES_STAGES!E63 / 10_VIE_DES_STAGES!E64 arena-126-avpr-2007-hospital-roof
A17: Arène 126 | B17: Hélicoptère anonyme — rotor d'évacuation | C17: Animation de fond | D17: Intégré | E17: 1 | F17: 6 | G17: Chrome :3 arènes,54 cellules natives, mobile et panne503/reprise. Composition :44 caméras. Tests ciblés passés. | H17: Toit intact, ambiance d'exposition avant destruction. Evacuants adultes et appareil anonymes originaux ; aucune identité de survivant, route narrative ou continuité d'équipement de Wolf certifiée. | J17: Hélicoptère anonyme — rotor d'évacuation 10_VIE_DES_STAGES!E62 / 10_VIE_DES_STAGES!E63 / 10_VIE_DES_STAGES!E64 arena-126-avpr-2007-hospital-roof
A18: Arène 126 | B18: Évent de toiture — vapeur dans le vent | C18: Animation de fond | D18: Intégré | E18: 1 | F18: 6 | G18: Chrome :3 arènes,54 cellules natives, mobile et panne503/reprise. Composition :44 caméras. Tests ciblés passés. | H18: Toit intact, ambiance d'exposition avant destruction. Evacuants adultes et appareil anonymes originaux ; aucune identité de survivant, route narrative ou continuité d'équipement de Wolf certifiée. | J18: Évent de toiture — vapeur dans le vent 10_VIE_DES_STAGES!E62 / 10_VIE_DES_STAGES!E63 / 10_VIE_DES_STAGES!E64 arena-126-avpr-2007-hospital-roof
A19: Arène 130 | B19: Marine anonyme — traversée de passerelle | C19: Animation de fond | D19: Intégré | E19: 1 | F19: 6 | G19: Chrome :3 arènes,54 cellules natives, mobile et panne503/reprise. Composition :44 caméras. Tests ciblés passés. | H19: Adaptation d'exposition de station industrielle. Marine adulte anonyme et mécanismes originaux ; ni héros Classic 2000 ni route scénarisée ou niveau exact certifié. | J19: Marine anonyme — traversée de passerelle 10_VIE_DES_STAGES!E143 / 10_VIE_DES_STAGES!E144 / 10_VIE_DES_STAGES!E145 arena-130-avp-classic-2000-space-station
A20: Arène 130 | B20: Ascenseur de service — cycle de porte | C20: Animation de fond | D20: Intégré | E20: 1 | F20: 6 | G20: Chrome :3 arènes,54 cellules natives, mobile et panne503/reprise. Composition :44 caméras. Tests ciblés passés. | H20: Adaptation d'exposition de station industrielle. Marine adulte anonyme et mécanismes originaux ; ni héros Classic 2000 ni route scénarisée ou niveau exact certifié. | J20: Ascenseur de service — cycle de porte 10_VIE_DES_STAGES!E143 / 10_VIE_DES_STAGES!E144 / 10_VIE_DES_STAGES!E145 arena-130-avp-classic-2000-space-station
... A26: Arène 051 | B26: Cataractes des Anciens | C26: Conservation | D26: Intégré | E26: 0 | F26: 0 | G26: Ancien ID jouable et images conservés, sans migration forcée des sauvegardes. | H26: Ancienne ruine à cascades renommée création originale. Elle ne représente plus Camp Golgotha. | J26: Cataractes des Anciens v62-golgotha-reconciliation.json

Sheet CombattantsV54
A2: Combattants — 205 dossiers V54
A3: Correspondances du classeur. Les trois créations utilisateur V56 hors V54 restent également jouables.
B4: Dossiers reliés au roster | D4: Identité ou apparence ouverte | F4: Cases runtime
B5: =COUNTIF(C9:C213,"Oui") -> 199 | D5: =COUNTIF(C9:C213,"Non") -> 6 | F5: 199
A6: 199 dossiers reliés, 199 cases runtime : populations distinctes. Six dossiers restent ouverts.
A8: ID V54 | B8: Nom du dossier | C8: Jouable | D8: ID en jeu | E8: Variantes | F8: État | G8: Kit natif complet | H8: Constat | I8: Cellules V54
A9: jungle-hunter | B9: Jungle Hunter | C9: Oui | D9: jungle-hunter | E9: 14 | F9: Déjà au roster | G9: Non certifié | H9: Présence dans le roster seulement ; ni kit complet ni fidélité 1:1 ne sont déduits de cette correspondance. | I9: 02_PERSONNAGES!A5:V5
A10: city-hunter | B10: City Hunter | C10: Oui | D10: city-hunter | E10: 13 | F10: Déjà au roster | G10: Non certifié | H10: Présence dans le roster seulement ; ni kit complet ni fidélité 1:1 ne sont déduits de cette correspondance. | I10: 02_PERSONNAGES!A6:V6
A11: scar | B11: Scar | C11: Oui | D11: scar | E11: 5 | F11: Déjà au roster | G11: Non certifié | H11: Présence dans le roster seulement ; ni kit complet ni fidélité 1:1 ne sont déduits de cette correspondance. | I11: 02_PERSONNAGES!A7:V7
A12: celtic | B12: Celtic | C12: Oui | D12: celtic | E12: 4 | F12: Déjà au roster | G12: Non certifié | H12: Présence dans le roster seulement ; ni kit complet ni fidélité 1:1 ne sont déduits de cette correspondance. | I12: 02_PERSONNAGES!A8:V8
A13: wolf | B13: Wolf | C13: Oui | D13: wolf | E13: 5 | F13: Déjà au roster | G13: Non certifié | H13: Présence dans le roster seulement ; ni kit complet ni fidélité 1:1 ne sont déduits de cette correspondance. | I13: 02_PERSONNAGES!A9:V9
A14: feral-hunter | B14: Feral | C14: Oui | D14: feral-hunter | E14: 7 | F14: Déjà au roster | G14: Non certifié | H14: Présence dans le roster seulement ; ni kit complet ni fidélité 1:1 ne sont déduits de cette correspondance. | I14: 02_PERSONNAGES!A10:V10
A15: berserker | B15: Berserker / Mr. Black | C15: Oui | D15: berserker | E15: 4 | F15: Déjà au roster | G15: Non certifié | H15: Présence dans le roster seulement ; ni kit complet ni fidélité 1:1 ne sont déduits de cette correspondance. | I15: 02_PERSONNAGES!A11:V11
A16: falconer | B16: Falconer | C16: Oui | D16: falconer | E16: 4 | F16: Déjà au roster | G16: Non certifié | H16: Présence dans le roster seulement ; ni kit complet ni fidélité 1:1 ne sont déduits de cette correspondance. | I16: 02_PERSONNAGES!A12:V12
A17: scarface | B17: Scarface | C17: Oui | D17: scarface | E17: 2 | F17: Déjà au roster | G17: Non certifié | H17: Présence dans le roster seulement ; ni kit complet ni fidélité 1:1 ne sont déduits de cette correspondance. | I17: 02_PERSONNAGES!A13:V13
A18: valkyrie | B18: Valkyrie | C18: Oui | D18: valkyrie | E18: 4 | F18: Déjà au roster | G18: Non certifié | H18: Présence dans le roster seulement ; ni kit complet ni fidélité 1:1 ne sont déduits de cette correspondance. | I18: 02_PERSONNAGES!A14:V14
A19: witch | B19: Witch | C19: Oui | D19: witch | E19: 2 | F19: Déjà au roster | G19: Non certifié | H19: Présence dans le roster seulement ; ni kit complet ni fidélité 1:1 ne sont déduits de cette correspondance. | I19: 02_PERSONNAGES!A15:V15
A20: enforcer | B20: Enforcer | C20: Oui | D20: enforcer | E20: 2 | F20: Déjà au roster | G20: Non certifié | H20: Présence dans le roster seulement ; ni kit complet ni fidélité 1:1 ne sont déduits de cette correspondance. | I20: 02_PERSONNAGES!A16:V16
... A213: variant-samurai-phg | B213: Samurai — Hunting Grounds | C213: Oui | D213: user-samurai | E213: 2 | F213: Déjà présent, clarifié | G213: Non certifié | H213: Deux apparences NECA Hunting Grounds déjà présentes ; identité précisée en V62 sans nouvelle case. Kit natif complet toujours non livré. | I213: 02_PERSONNAGES!A209:V209

Sheet Resteclasseur
A2: Demandes encore ouvertes — suivi V63
A3: Distinguer absence, apparence intégrée, kit partiel et conditions narratives encore non vérifiées.
A5: Les 522 demandes restent suivies ; six adaptations V63 ne certifient pas tous les événements.
A8: Chantier | B8: Dossier ou demande | C8: État | D8: Suite nécessaire | E8: Source
A9: Combattant | B9: Predator du tournoi — Bloodshed | C9: Identité ou apparence ouverte | D9: Identité du tournoi attestée par Marvel ; apparence native et kit jouable manquants. Les dessins anonymes fournis ne permettent pas une attribution certaine. | E9: 02_PERSONNAGES!A200:V200 / 03_MANQUANTS!A5:L5
A10: Combattant | B10: Super Predator — The Last Hunt | C10: Identité ou apparence ouverte | D10: Dossier distinct de Mr. Black. Référence de tenue et arsenal à verrouiller ; aucun ajout par simple renommage. | E10: 02_PERSONNAGES!A201:V201 / 03_MANQUANTS!A6:L6
A11: Combattant | B11: Predator jouable — AVP Jaguar | C11: Identité ou apparence ouverte | D11: Incarnation AVP Jaguar absente ; ne pas substituer Dark, Prince ou Jungle Hunter. | E11: 02_PERSONNAGES!A202:V202 / 03_MANQUANTS!A7:L7
A12: Combattant | B12: Predator jouable — AVP Classic 2000 | C12: Identité ou apparence ouverte | D12: Incarnation AVP Classic 2000 absente ; user-classic-2010 appartient au film Predators. | E12: 02_PERSONNAGES!A203:V203 / 03_MANQUANTS!A8:L8
A13: Combattant | B13: Predator père — Blood Ties | C13: Identité ou apparence ouverte | D13: Père de Blood Ties : attribution visuelle à établir avant création ou réaffectation. | E13: 02_PERSONNAGES!A204:V204 / 03_MANQUANTS!A9:L9
A14: Combattant | B14: Predator fils — Blood Ties | C14: Identité ou apparence ouverte | D14: Fils de Blood Ties : identité distincte à établir, sans fusion avec les cycles I et II. | E14: 02_PERSONNAGES!A205:V205 / 03_MANQUANTS!A10:L10
A15: Animations combattants | B15: Emissary, Elder, Captured PHG et bibliothèques incomplètes | C15: Kit partiel | D15: Les trois apparences ont des gardes natives, mais les mouvements, attaques, réactions, intros et résultats de manche restent à dessiner. Aucun kit complet ni dix plaquettes par personnage certifié. | E15: 02_PERSONNAGES / exigences animation V54
A16: Arène 126 | B16: Toit de l’hôpital · variante narrative | C16: Ambiance ajoutée, chapitre ouvert | D16: E62 : évacuation conservée mais inactive sur le toit sans civils. Produire une continuité hors toit cohérente ; route, chronologie et équipement de Wolf restent ouverts. | E16: 09_STAGES!A24:N24
A17: Arène 51 | B17: Camp Golgotha — nouvelle arène 187 | C17: Ambiance ajoutée, chapitre ouvert | D17: V62 fournit un triplet d’ambiance d’exposition. Le chapitre, sa route, ses personnages et ses conditions exactes restent à intégrer. Marines derrière un sas Capteur d’alarme lent Xénomorphe derrière un vitrage distant | E17: 09_STAGES!A50:N50
A18: Arène 130 | B18: Station orbitale Classic | C18: Ambiance ajoutée, chapitre ouvert | D18: V62 fournit un triplet d’ambiance d’exposition. Le chapitre, sa route, ses personnages et ses conditions exactes restent à intégrer. Marine en fuite par une passerelle Porte d’ascenseur hors zone jouable Lumière de quarantaine à intensité bornée | E18: 09_STAGES!A51:N51
A19: Arène 119 | B19: Gorge de la planète hostile | C19: À réaliser | D19: Variante de cadrage/scénario de Dek autour d’un monde existant. Thia observant depuis un abri seulement dans les chapitres alliés Faune extraterrestre dont l’espèce et l’échelle seront référencées Végétation hostile en arrière-plan sans collision compétitive | E19: 09_STAGES!A54:N54
... A36: Homeworld | B36: Refonte de la ville en 2.5D | C36: Nouvelle demande, non livrée V63 | D36: Unifier caméra, maisons, portes, intérieurs, spatioport, proportions et codex des dimensions. V63 ne certifie pas cette future refonte. | E36: Demande utilisateur reçue après le lot V63

Sheet LotV63
A2: THE PIT — changements du lot V63
A3: Copie du suivi V62 ; onglet LotV62 conservé comme historique. Source V54 inchangée.
B4: Nouveaux PNG intégrés | D4: Dessins natifs intégrés | G4: Publication V63
B5: =SUM(E9:E26) -> 13 | D5: =SUM(F9:F26) -> 63 | G5: Non vérifiée dans ce suivi
A6: Deux apparences, zéro nouvelle case ; quatre gardes ne constituent pas deux kits complets.
A8: Chantier | B8: Élément | C8: Nature | D8: État | E8: PNG | F8: Dessins | G8: Vérification | H8: Limites | J8: Sources
A9: Combattant | B9: Hunting Grounds · Elder sans masque · garde native · portrait | C9: Portrait | D9: Intégré, kit partiel | E9: 1 | F9: 1 | G9: Chrome : deux sens, six poses natives par garde ; mobile paysage, pause et sélection vérifiés. | H9: Variante sur une case existante. Marche, attaque, intro et résultats restent à produire. Détails cachés reconstruits, sans certification 1:1. | J9: 02_PERSONNAGES!A206:V206 / 03_MANQUANTS!A11:L11 https://blog.playstation.com/2020/06/12/june-free-update-now-live-in-predator-hunting-grounds/ https://live.staticflickr.com/65535/49996764556_c03bc385e7_h.jpg
A10: Combattant | B10: Hunting Grounds · Elder sans masque · garde native · idle-right | C10: Garde animée | D10: Intégré, kit partiel | E10: 1 | F10: 6 | G10: Chrome : deux sens, six poses natives par garde ; mobile paysage, pause et sélection vérifiés. | H10: Variante sur une case existante. Marche, attaque, intro et résultats restent à produire. Détails cachés reconstruits, sans certification 1:1. | J10: 02_PERSONNAGES!A206:V206 / 03_MANQUANTS!A11:L11 https://blog.playstation.com/2020/06/12/june-free-update-now-live-in-predator-hunting-grounds/ https://live.staticflickr.com/65535/49996764556_c03bc385e7_h.jpg
A11: Combattant | B11: Hunting Grounds · Elder sans masque · garde native · idle-left | C11: Garde animée | D11: Intégré, kit partiel | E11: 1 | F11: 6 | G11: Chrome : deux sens, six poses natives par garde ; mobile paysage, pause et sélection vérifiés. | H11: Variante sur une case existante. Marche, attaque, intro et résultats restent à produire. Détails cachés reconstruits, sans certification 1:1. | J11: 02_PERSONNAGES!A206:V206 / 03_MANQUANTS!A11:L11 https://blog.playstation.com/2020/06/12/june-free-update-now-live-in-predator-hunting-grounds/ https://live.staticflickr.com/65535/49996764556_c03bc385e7_h.jpg
A12: Combattant | B12: Hunting Grounds · Captured masqué · garde native · portrait | C12: Portrait | D12: Intégré, kit partiel | E12: 1 | F12: 1 | G12: Chrome : deux sens, six poses natives par garde ; mobile paysage, pause et sélection vérifiés. | H12: Variante sur une case existante. Marche, attaque, intro et résultats restent à produire. Détails cachés reconstruits, sans certification 1:1. | J12: 02_PERSONNAGES!A208:V208 / 03_MANQUANTS!A13:L13 https://blog.playstation.com/2021/12/15/predator-hunting-grounds-introduces-the-hunting-party/ https://store.steampowered.com/app/1847080/Predator_Hunting_Grounds__Hunting_Party_Bundle/ https://shared.akamai.steamstatic.com/store_item_assets/steam/apps/1847080/ss_4ebbc1badb9563972092231cb1e41b357a7de04e.1920x1080.jpg?t=1764097265
A13: Combattant | B13: Hunting Grounds · Captured masqué · garde native · idle-right | C13: Garde animée | D13: Intégré, kit partiel | E13: 1 | F13: 6 | G13: Chrome : deux sens, six poses natives par garde ; mobile paysage, pause et sélection vérifiés. | H13: Variante sur une case existante. Marche, attaque, intro et résultats restent à produire. Détails cachés reconstruits, sans certification 1:1. | J13: 02_PERSONNAGES!A208:V208 / 03_MANQUANTS!A13:L13 https://blog.playstation.com/2021/12/15/predator-hunting-grounds-introduces-the-hunting-party/ https://store.steampowered.com/app/1847080/Predator_Hunting_Grounds__Hunting_Party_Bundle/ https://shared.akamai.steamstatic.com/store_item_assets/steam/apps/1847080/ss_4ebbc1badb9563972092231cb1e41b357a7de04e.1920x1080.jpg?t=1764097265
A14: Combattant | B14: Hunting Grounds · Captured masqué · garde native · idle-left | C14: Garde animée | D14: Intégré, kit partiel | E14: 1 | F14: 6 | G14: Chrome : deux sens, six poses natives par garde ; mobile paysage, pause et sélection vérifiés. | H14: Variante sur une case existante. Marche, attaque, intro et résultats restent à produire. Détails cachés reconstruits, sans certification 1:1. | J14: 02_PERSONNAGES!A208:V208 / 03_MANQUANTS!A13:L13 https://blog.playstation.com/2021/12/15/predator-hunting-grounds-introduces-the-hunting-party/ https://store.steampowered.com/app/1847080/Predator_Hunting_Grounds__Hunting_Party_Bundle/ https://shared.akamai.steamstatic.com/store_item_assets/steam/apps/1847080/ss_4ebbc1badb9563972092231cb1e41b357a7de04e.1920x1080.jpg?t=1764097265
A15: Arène 126 | B15: Gaine vibrante — raccord fixé au bloc HVAC | C15: Animation de fond | D15: Adaptation intégrée | E15: 1 | F15: 6 | G15: Rendu et application vérifiés ; voir preuve finale liée. | H15: Six poses ; ambiance adaptée. Aucun chapitre ni fidélité littérale 1:1 certifiés. | J15: 10_VIE_DES_STAGES!E503 arena-126-avpr-2007-hospital-roof
A16: Arène 126 | B16: Lumières urbaines — variation lente distante | C16: Animation de fond | D16: Adaptation intégrée | E16: 1 | F16: 6 | G16: Rendu et application vérifiés ; voir preuve finale liée. | H16: Six poses ; ambiance adaptée. Aucun chapitre ni fidélité littérale 1:1 certifiés. | J16: 10_VIE_DES_STAGES!E504 arena-126-avpr-2007-hospital-roof
A17: Arène 126 | B17: Panache avant destruction — cheminée de fond | C17: Animation de fond | D17: Adaptation intégrée | E17: 1 | F17: 6 | G17: Rendu et application vérifiés ; voir preuve finale liée. | H17: Six poses ; ambiance adaptée. Aucun chapitre ni fidélité littérale 1:1 certifiés. | J17: 10_VIE_DES_STAGES!E505 arena-126-avpr-2007-hospital-roof
A18: Arène 130 | B18: Piston de maintenance — derrière barrière | C18: Animation de fond | D18: Adaptation intégrée | E18: 1 | F18: 6 | G18: Rendu et application vérifiés ; voir preuve finale liée. | H18: Six poses ; ambiance adaptée. Aucun chapitre ni fidélité littérale 1:1 certifiés. | J18: 10_VIE_DES_STAGES!E512 arena-130-avp-classic-2000-space-station
A19: Arène 130 | B19: Purge intermittente — conduite du fond | C19: Animation de fond | D19: Adaptation intégrée | E19: 1 | F19: 6 | G19: Rendu et application vérifiés ; voir preuve finale liée. | H19: Six poses ; ambiance adaptée. Aucun chapitre ni fidélité littérale 1:1 certifiés. | J19: 10_VIE_DES_STAGES!E513 arena-130-avp-classic-2000-space-station
A20: Arène 130 | B20: Trappe de contrôle — voyant ambre stable | C20: Animation de fond | D20: Adaptation intégrée | E20: 1 | F20: 6 | G20: Rendu et application vérifiés ; voir preuve finale liée. | H20: Six poses ; ambiance adaptée. Aucun chapitre ni fidélité littérale 1:1 certifiés. | J20: 10_VIE_DES_STAGES!E514 arena-130-avp-classic-2000-space-station
... A26: Menu et sauvegardes | B26: Nouvelle partie, remplacement et récupération | C26: Parcours corrigé | D26: Intégré | E26: 0 | F26: 0 | G26: 91 tests ciblés ; 12 scénarios Chrome isolés. | H26: Aucune sauvegarde personnelle utilisée. Publication distincte du contrôle local. | J26: docs/V63-MENU-SAUVEGARDES.md / docs/v63-menu-after-qa.json

Sheet StagesV54
A2: 174 dossiers de stages — correspondances et demandes V54
A3: 170 cibles de décor ; 522 descriptions conservées. Présence runtime et fidélité littérale sont deux contrôles distincts.
B4: Dossiers sans registre natif V60–V63 | D4: Sans décor runtime | F4: Cibles distinctes avec registre | H4: Événements actifs sur les 35 cibles distinctes
B5: =COUNTIF(E9:E182,0) -> 136 | D5: =COUNTIF(D9:D182,"Non") -> 0 | F5: 35 | H5: 110
A6: Un registre absent ne prouve pas l’absence de tout effet hérité. Les doublons ne doivent pas être additionnés comme nouveaux dessins.
A8: ID V54 | B8: Stage demandé | C8: ID runtime | D8: Décor résolu | E8: Événements natifs | F8: Registre | G8: Dossier complet | H8: Trois demandes et statut | J8: Cellules source
A9: ST001 | B9: Clairière des pièges | C9: arena-103-predator-1987-final-trap-clearing | D9: Oui | E9: 0 | F9: Registre V60–V63 absent | G9: Non certifié | H9: 10_VIE_DES_STAGES!E5 Feuilles secouées par une fuite d’oiseaux Non recertifié par V63 10_VIE_DES_STAGES!E6 Insectes en lisière, jamais devant les silhouettes Non recertifié par V63 10_VIE_DES_STAGES!E7 Lointaine patrouille armée avant le duel, absente du face-à-face final Non recertifié par V63 | J9: 09_STAGES!A5:N5
A10: ST002 | B10: Vaisseau des trophées | C10: arena-106-predator-2-1990-trophy-ship | D10: Oui | E10: 0 | F10: Registre V60–V63 absent | G10: Non certifié | H10: 10_VIE_DES_STAGES!E8 Membres anonymes du clan observant sans intervenir Non recertifié par V63 10_VIE_DES_STAGES!E9 Éclairage de niches passant doucement d’un trophée à l’autre Non recertifié par V63 10_VIE_DES_STAGES!E10 Ouverture furtive de la rampe et vapeur basse Non recertifié par V63 | J10: 09_STAGES!A6:N6
A11: ST003 | B11: Chambre sacrificielle | C11: arena-122-avp-2004-sacrificial-chamber | D11: Oui | E11: 0 | F11: Registre V60–V63 absent | G11: Non certifié | H11: 10_VIE_DES_STAGES!E11 Ombre de xénomorphe derrière une grille Non recertifié par V63 10_VIE_DES_STAGES!E12 Hologramme du labyrinthe sur un socle Non recertifié par V63 10_VIE_DES_STAGES!E13 Vapeur froide et poussière aux joints des murs Non recertifié par V63 | J11: 09_STAGES!A7:N7
A12: ST004 | B12: Épave de Gunnison | C12: arena-127-avpr-2007-forest-crash | D12: Oui | E12: 0 | F12: Registre V60–V63 absent | G12: Non certifié | H12: 10_VIE_DES_STAGES!E14 Balise endommagée clignotant lentement Non recertifié par V63 10_VIE_DES_STAGES!E15 Silhouette xénomorphe traversant une brèche éloignée Non recertifié par V63 10_VIE_DES_STAGES!E16 Braises et fumée verticale non opaque Non recertifié par V63 | J12: 09_STAGES!A8:N8
A13: ST005 | B13: Camp de la réserve | C13: arena-107-predators-2010-hunting-camp | D13: Oui | E13: 0 | F13: Registre V60–V63 absent | G13: Non certifié | H13: 10_VIE_DES_STAGES!E17 Predator Hound reniflant derrière une barrière hors combat Non recertifié par V63 10_VIE_DES_STAGES!E18 Drone de reconnaissance lointain sans cible HUD Non recertifié par V63 10_VIE_DES_STAGES!E19 Végétation qui bouge à l’approche d’une proie cachée Non recertifié par V63 | J13: 09_STAGES!A9:N9
A14: ST006 | B14: Bourbier | C14: arena-115-prey-2022-mud-pit | D14: Oui | E14: 0 | F14: Registre V60–V63 absent | G14: Non certifié | H14: 10_VIE_DES_STAGES!E20 Oiseaux quittant les roseaux Non recertifié par V63 10_VIE_DES_STAGES!E21 Bison lointain en variante de plaine seulement, pas dans chaque forêt Non recertifié par V63 10_VIE_DES_STAGES!E22 Trappeur adulte repliant un piège avant de fuir, non complice de Feral Non recertifié par V63 | J14: 09_STAGES!A10:N10
A15: ST007 | B15: Crash de la forêt | C15: arena-112-the-predator-2018-forest-crash | D15: Oui | E15: 0 | F15: Registre V60–V63 absent | G15: Non certifié | H15: 10_VIE_DES_STAGES!E23 Chien extraterrestre derrière la coque, sans dégâts Non recertifié par V63 10_VIE_DES_STAGES!E24 Agent Stargazer inspectant un écran puis se mettant à couvert Non recertifié par V63 10_VIE_DES_STAGES!E25 Ventilation d’une capsule endommagée Non recertifié par V63 | J15: 09_STAGES!A11:N11
A16: ST008 | B16: Cour du clan | C16: arena-121-badlands-2025-clan-prologue | D16: Oui | E16: 0 | F16: Registre V60–V63 absent | G16: Non certifié | H16: 10_VIE_DES_STAGES!E26 Gardes adultes immobiles puis échange de regard Non recertifié par V63 10_VIE_DES_STAGES!E27 Portes monumentales se fermant avant le round Non recertifié par V63 10_VIE_DES_STAGES!E28 Feux rituels et bannières limitées aux références visuelles Non recertifié par V63 | J16: 09_STAGES!A12:N12
A17: ST009 | B17: Arène du Warlord | C17: arena-118-killer-of-killers-2025-yautja-arena | D17: Oui | E17: 0 | F17: Registre V60–V63 absent | G17: Non certifié | H17: 10_VIE_DES_STAGES!E29 Spectateurs yautja se penchant au bord des gradins Non recertifié par V63 10_VIE_DES_STAGES!E30 Garde refermant une cellule de combattant Non recertifié par V63 10_VIE_DES_STAGES!E31 Signal mécanique du début de duel Non recertifié par V63 | J17: 09_STAGES!A13:N13
A18: ST010 | B18: Glace du récit The Shield | C18: arena-116-killer-of-killers-2025-viking-ice | D18: Oui | E18: 0 | F18: Registre V60–V63 absent | G18: Non certifié | H18: 10_VIE_DES_STAGES!E32 Survivants adultes cherchant un abri au loin Non recertifié par V63 10_VIE_DES_STAGES!E33 Neige tombant d’une branche après un coup lourd Non recertifié par V63 10_VIE_DES_STAGES!E34 Glaçons détachés derrière le plan de jeu Non recertifié par V63 | J18: 09_STAGES!A14:N14
A19: ST011 | B19: Toits du récit The Sword | C19: arena-117-killer-of-killers-2025-japan-rooftops | D19: Oui | E19: 0 | F19: Registre V60–V63 absent | G19: Non certifié | H19: 10_VIE_DES_STAGES!E35 Garde regardant depuis une galerie éloignée Non recertifié par V63 10_VIE_DES_STAGES!E36 Lanternes à faible amplitude Non recertifié par V63 10_VIE_DES_STAGES!E37 Tuiles et poussière uniquement derrière les pieds Non recertifié par V63 | J19: 09_STAGES!A15:N15
A20: ST012 | B20: Freya’s Prospect | C20: arena-131-avp-2010-freyas-prospect | D20: Oui | E20: 0 | F20: Registre V60–V63 absent | G20: Non certifié | H20: 10_VIE_DES_STAGES!E38 Marines en repli derrière une porte blindée Non recertifié par V63 10_VIE_DES_STAGES!E39 Xénomorphe parcourant une canalisation extérieure Non recertifié par V63 10_VIE_DES_STAGES!E40 Écran de quarantaine et gyrophares lents Non recertifié par V63 | J20: 09_STAGES!A16:N16
... A182: ST174 | B182: Predator hunting grounds airstrip | C182: arena-136-predator-hunting-grounds-airstrip | D182: Oui | E182: 0 | F182: Registre V60–V63 absent | G182: Non certifié | H182: 10_VIE_DES_STAGES!E524 Atmosphère locale derrière la zone de combat Non recertifié par V63 10_VIE_DES_STAGES!E525 Mouvement d'un élément mécanique ou végétal attesté par le décor Non recertifié par V63 10_VIE_DES_STAGES!E526 Silhouette de fond uniquement après validation de sa présence dans la scène Non recertifié par V63 | J182: 09_STAGES!A178:N178

Sheet SyntheseV99
A1: YAUTJA · suivi consolidé V99
A2: Arrêté au 2026-10-20 · données runtime actuelles, preuves et travaux ouverts distingués
A3: Synthèse : SyntheseV99 · filtres ligne 4 · en-têtes figés
A4: Indicateur | B4: Valeur | C4: Portée / limite
A5: Chantiers suivis | B5: =COUNTA('ChantiersV99'!A5:A24) -> 20 | C5: Des livraisons partielles et des travaux ouverts, pas un pourcentage de jeu terminé.
A6: EN_COURS | B6: =COUNTIF('ChantiersV99'!F5:F24,"EN_COURS") -> 0 | C6: Statut explicite du registre ; modifier le statut du chantier actualise le compteur Excel.
A7: A_VALIDER | B7: =COUNTIF('ChantiersV99'!F5:F24,"A_VALIDER") -> 0 | C7: Statut explicite du registre ; modifier le statut du chantier actualise le compteur Excel.
A8: OUVERT | B8: =COUNTIF('ChantiersV99'!F5:F24,"OUVERT") -> 9 | C8: Statut explicite du registre ; modifier le statut du chantier actualise le compteur Excel.
A9: LIVRE_PARTIEL | B9: =COUNTIF('ChantiersV99'!F5:F24,"LIVRE_PARTIEL") -> 6 | C9: Statut explicite du registre ; modifier le statut du chantier actualise le compteur Excel.
A10: VALIDE_CIBLE | B10: =COUNTIF('ChantiersV99'!F5:F24,"VALIDE_CIBLE") -> 5 | C10: Statut explicite du registre ; modifier le statut du chantier actualise le compteur Excel.
A11: Planètes dans le runtime | B11: =COUNTA('PlanetesV99'!A5:A34) -> 30 | C11: Cartes du projet ; Korthas reprend ses noms et règles V3.
A12: Biomes classiques | B12: =COUNTIF('PlanetesV99'!C5:C34,"classic") -> 16 | C12: Direction artistique classique ; pas une certification canonique 1:1.
A13: Biomes exotiques | B13: =COUNTIF('PlanetesV99'!C5:C34,"exotic") -> 14 | C13: Surfaces originales du projet, non jouables entre les terres.
A14: Ouvrages source V6 | B14: =COUNTA('OuvragesV6'!A5:A22) -> 18 | C14: Une ligne par W3-S01 à W3-S18.
A15: Ouvrages acceptés en contexte libre | B15: =COUNTIF('OuvragesV6'!F5:F22,"INTEGRE_LIBRE") -> 12 | C15: Exports actuels ; campagne et tests restent des dimensions séparées.
A16: Ouvrages restant ouverts | B16: =COUNTIF('OuvragesV6'!F5:F22,"OUVERT") -> 6 | C16: Transport, montures, énergie, duel, sons situés et route orbitale.
A17: Fiches V3 embarquées | B17: 679 | C17: 32 feuilles contenant des fiches dans l'export runtime ; original annoncé à 39 feuilles par l'import V85, pas autant de fonctionnalités jouées.
A18: Fiches guerre V6 embarquées | B18: 975 | C18: 33 feuilles extraites ; la source privée comprend davantage de domaines.
A19: Scènes documentaires | B19: 730 | C19: 6059 répliques, 1494 choix, 150 variantes, 400 réactions ; pas autant de missions incarnées.
A20: Directions de voix textuelles | B20: 210 | C20: 202 noms distincts / 8 noms ambigus ; aucun nouvel enregistrement audio dans ce lot.
A21: Feuilles du corpus navire | B21: 19 | C21: Corpus consultable ; inspection, acquisition et voyage ne sont pas le même état.
A22: Identifiants combattants runtime actuels | B22: 201 | C22: Population distincte des 205 dossiers historiques du classeur V54.
A23: Arènes runtime actuelles | B23: 187 | C23: Un décor disponible ne certifie pas les événements littéraux du dossier source.
A24: Dossiers personnages V54 ouverts en V63 | B24: 6 | C24: État historique repris explicitement ; pas recertifié V99.
A25: Descriptions de vie des stages conservées | B25: 522 | C25: 174 dossiers historiques ; leurs cellules et statuts V63 restent visibles.
A26: Dossiers stages littéralement certifiés par V99 | B26: 0 | C26: Aucune certification intégrale nouvelle de ces dossiers.
A27: Originaux privés présents | B27: 0 | C27: Les extractions et leurs empreintes sont conservées ; aucun original privé n’a été recréé.
A28: Application Excel native vérifiée | B28: NON | C28: Vérification ZIP/XML et lecture indépendante ; Excel/LibreOffice natif non lancé.

Sheet ChantiersV99
A1: Sources → implémentation → preuve → reste
A2: Une livraison partielle, un test ciblé et une validation navigateur ont leur propre portée.
A3: Synthèse : SyntheseV99 · filtres ligne 4 · en-têtes figés
A4: ID | B4: Domaine | C4: Chantier | D4: Source / cellules | E4: Implémentation | F4: Statut chantier | G4: Comportement / portée | H4: Tests | I4: Navigateur | J4: Preuves / commandes | K4: Reste à faire | L4: Responsable
A5: CLANS-V99-GARRISONS | B5: Guerre de clans | C5: Affecter et libérer une garnison existante | D5: V3 : Règles de conquête, CON-R08 ligne 13 ; CON-R12 ligne 17 ; CON-R15 ligne 20 | E5: app/game/systems/clanWarV85.ts app/game/ClanWarGarrisonV99.tsx | F5: VALIDE_CIBLE | G5: Affectation locale de personnes existantes ; refus réservé / blessé / mort / formation ; confirmation du dernier garde. | H5: PASS 101/101 ciblés ; dont 11 V99 + 4 revue | I5: PASS_PRODUCTION 26/26 ; pilote renforcé | J5: tests/clan-war-garrison-v99.test.mjs docs/clan-war-garrison-v99.md tests/clan-war-garrison-review-v99.test.mjs outputs/qa-three-modes-v99/production/result.json | K5: Modèle, SSR, régressions et Chromium production (26/26 avec pilote renforcé) validés. Portée limitée aux garnisons existantes ; les règles V3 globales et la campagne restent ouvertes. Publication suivie séparément. | L5: clans_v99
A6: PRESERVE-V99-DEPOTS | B6: Preserve Hunt | C6: Neutraliser un lot dans un dépôt physique | D6: Prolongement original V66/V98 ; demande Répartition des joueurs Predator 6aa9eb58-e760-83eb-8098-e735f1d01161 | E6: app/game/systems/gameReserveV66.ts app/game/GameReserveTacticalV98.tsx | F6: VALIDE_CIBLE | G6: Interaction sur place pendant 2 s ; le lot identifié du dépôt est concerné. | H6: PASS 40/40 ciblés ; 26 régressions + 9 V99 + 5 revue | I6: PASS_PRODUCTION 26/26 ; pilote renforcé | J6: tests/game-reserve-supply-denial-v99.test.mjs docs/v99-preserve-hunt-supply-denial.md tests/game-reserve-logistics-review-v99.test.mjs outputs/qa-three-modes-v99/production/result.json | K6: Modèle, interface, persistance et Chromium production (26/26 avec pilote renforcé) validés. Le terrain reste 3/80 secteurs et 8/100 combattants ; aucun nouvel asset, animation ou lore canonique. Publication suivie séparément. | L6: preserve_v99
A7: PRESERVE-V99-RECUPERATION | B7: Preserve Hunt | C7: Récupérer à pied un porteur abattu | D7: Prolongement original de docs/v66-game-reserve-delivery.md et docs/v98-preserve-hunt-interceptions.md | E7: app/game/systems/gameReserveV66.ts app/game/GameReserveTacticalV98.tsx | F7: VALIDE_CIBLE | G7: Un survivant proche se déplace réellement vers les composants du porteur abattu. | H7: PASS 40/40 ciblés ; 26 régressions + 9 V99 + 5 revue | I7: PASS_PRODUCTION 26/26 ; pilote renforcé | J7: tests/game-reserve-supply-denial-v99.test.mjs docs/v99-preserve-hunt-supply-denial.md tests/game-reserve-logistics-review-v99.test.mjs outputs/qa-three-modes-v99/production/result.json | K7: Modèle, interface, persistance et Chromium production (26/26 avec pilote renforcé) validés. Le terrain reste 3/80 secteurs et 8/100 combattants ; aucun nouvel asset, animation ou lore canonique. Publication suivie séparément. | L7: preserve_v99
A8: HW-NAV-PERF | B8: Homeworld | C8: Réduire le calcul froid et les points du guidage | D8: Prolongement de docs/homeworld-wayfinding-v98.md ; navigation du projet, pas nouvelle source canonique | E8: app/game/systems/homeworldNavigationV99.ts app/game/systems/homeworldWayfindingV98.ts | F8: VALIDE_CIBLE | G8: Hiérarchie A* et repli V77 implémentés ; froid 11 297 → 3 190 ms (×3,54), premier palier 183 → 18 points ; longueur totale +7,6 %. | H8: PASS 18/18 ; 4 V99 + 7 oracle + 4 SSR + 3 revue | I8: PASS_PRODUCTION 23/23 ; fixture préparée et contrôles natifs | J8: tests/homeworld-navigation-v99.test.mjs docs/homeworld-navigation-v99.md tests/homeworld-navigation-review-v99.test.mjs outputs/qa-three-modes-v99/production/result.json | K8: 18 tests modèle/SSR et 23 contrôles Chromium Homeworld validés : marche clavier réelle, Escalier du Conseil vers +1, pause/reprise, sauvegarde et Continuer. Froid 2 988 ms, chaud 210 ms, même worker, 18 points. Portée : fixture Homeworld préparée et horloge navigateur contrôlée, pas une campagne jouée ; publication suivie séparément. | L8: homeworld_v99
A9: EXCEL-V99-TRACE | B9: Classeurs | C9: Relier sources, code, preuve et reste à faire | D9: 5 classeurs locaux conservés ; suivi V63 comme base ; extraits source et exports runtime actuels | E9: scripts/build-excel-followup-v99.mjs scripts/build-excel-followup-v99.py docs/v99-workstreams-source.json | F9: VALIDE_CIBLE | G9: Nouveau classeur V99 et registre JSON ; générateur reproductible sans nouvelle dépendance. | H9: PASS 6/6 ; revue OOXML indépendante PASS | I9: SANS_OBJET | J9: tests/excel-followup-v99.test.mjs docs/v99-excel-followup-qa.json | K9: 15 onglets dont 5 feuilles V63 conservées, 12 compteurs recomptés, textes source littéraux et génération déterministe vérifiés. Lecture indépendante openpyxl ; aucune application Excel/LibreOffice native disponible. | L9: excel_v99
A10: CLANS-PLANETES-30 | B10: Guerre de clans | C10: 30 théâtres et surfaces non jouables | D10: Créations originales du projet V96/V97 ; Korthas reprend ses noms et règles V3 | E10: app/game/systems/clanWarPlanetsV96.ts app/game/systems/clanWarCoastlinesV97.ts | F10: LIVRE_PARTIEL | G10: 30 mondes, dont classiques et exotiques ; contours continentaux, routes et couleurs de contrôle dans l'atlas. | H10: HISTORIQUE_V98 | I10: HISTORIQUE_V98 | J10: docs/integration-v98.md outputs/qa-three-modes-v98/verification.json | K10: Préserver l'accès par routes courtes ; aucun statut de planète canonique 1:1 attribué aux créations originales. Validation V99 séparée. | L10: clans_v99
A11: CLANS-COMMANDEMENT-V98 | B11: Guerre de clans | C11: Front, ordres et inspection sans fuite adverse | D11: Adaptation du projet de l'atlas V95–V98 | E11: app/game/systems/clanWarCommandV98.ts app/game/ClanWarCommandV98.tsx | F11: LIVRE_PARTIEL | G11: État d'un front connu et aperçu d'un ordre valide ; ressources localisées selon le mode. | H11: HISTORIQUE_V98 | I11: HISTORIQUE_V98 | J11: docs/integration-v98.md | K11: La preuve V98 reste historique ; ne pas déclarer terminés les trois modes et toutes les règles du classeur. | L11: clans_v99
A12: V6-OUVRAGES-18 | B12: Guerre de clans | C12: Ouvrages V6 : vérifier chaque ligne source | D12: V6, Structures de guerre, W3-S01 à W3-S18, lignes 6 à 23 | E12: app/game/systems/clanWarWorksV6.ts app/game/systems/clanWarMedicalV92.ts | F12: LIVRE_PARTIEL | G12: 12 définitions acceptées par l'export actuel ; standalone. Les six autres restent explicitement ouvertes dans OuvragesV6. | H12: HISTORIQUE_V92 | I12: A_VALIDER | J12: docs/clan-war-medical-v92.md docs/clan-war-structures-v89.md | K12: S09, S10, S13, S14, S15, S18 : transport, montures, énergie, duel, sons et route orbitale à raccorder. Le suivi V88 à 8/18 reste historique. | L12: clans_v99
A13: V6-LOGISTIQUE-CAMPAGNE | B13: Guerre de clans | C13: Raccorder les exercices à la campagne persistante | D13: docs/yautja-v88-import-and-excel-status.md ; séparation V3/V6 documentée en V85 | E13: app/game/systems/clanWarBibleV6.ts app/game/systems/clanWarWorksV6.ts | F13: OUVERT | G13: Les démonstrations identifiées fonctionnent dans leur contexte libre. | H13: NON_EXECUTE | I13: NON_EXECUTE | J13: docs/release-v85-imports-and-excel.md docs/yautja-v88-import-and-excel-status.md | K13: Arrivée effective, mandat, ravitaillement et sauvegarde persistante de campagne ; pas de conversion automatique des monnaies et identifiants V3/V6. | L13: integration
A14: PRESERVE-EXPANSION-80 | B14: Preserve Hunt | C14: Étendre les secteurs et les combattants | D14: docs/v66-game-reserve-delivery.md et docs/v98-preserve-hunt-interceptions.md | E14: app/game/systems/gameReserveV66.ts | F14: OUVERT | G14: Premier terrain Vharuun : 3 secteurs / 80 visés, 8 combattants / 100 visés. | H14: HISTORIQUE_V98 | I14: HISTORIQUE_V98 | J14: docs/integration-v98.md | K14: Créer, intégrer et jouer chaque secteur et combattant supplémentaire ; un plan, une liste ou une image n'est pas un terrain jouable. | L14: preserve_v99
A15: HOMEWORLD-GUIDAGE-V98 | B15: Homeworld | C15: Parcourir les six étages et reprendre le guidage | D15: docs/homeworld-wayfinding-v98.md | E15: app/game/systems/homeworldWayfindingV98.ts | F15: LIVRE_PARTIEL | G15: Parcours V98 joué du port aux escaliers du Conseil, guide annulable, reprise après rechargement. | H15: HISTORIQUE_V98 | I15: HISTORIQUE_V98 | J15: docs/integration-v98.md docs/homeworld-wayfinding-v98.md | K15: Mesurer et rejouer V99 ; ne pas transformer une route calculée en preuve de toutes les interactions du Homeworld. | L15: homeworld_v99
... A18: V6-NAVIRE-VOYAGE | B18: Navire | C18: Passer de l'inspection au voyage réel | D18: V6 navire : R2-M021 acquisition, R2-M022 préparation, R2-M023 voyage ; corpus de 19 feuilles | E18: public/game/dialogues/v85/bible-ships.json | F18: OUVERT | G18: Huit postes d'inspection documentaire décrits en V88 ; aucun navire acquis par leur consultation. | H18: HISTORIQUE_V88 | I18: A_VALIDER | J18: docs/yautja-v88-import-and-excel-status.md | K18: Jouer acquisition, préparation, manifestes et route orbitale avant toute arrivée ; l'interface ne constitue pas un voyage. | L18: integration
A19: V84-VARIANTES-640 | B19: Graphismes | C19: Raccorder les variantes de PNJ et leurs images | D19: Suivi des imports V84/V85/V88 | F19: OUVERT | G19: 640 variantes V84 documentées comme métadonnées ; pas de PNG fourni par ce registre. | H19: NON_EXECUTE | I19: NON_EXECUTE | J19: docs/yautja-v88-import-and-excel-status.md | K19: Produire et vérifier les images natives puis leurs animations et intégrations ; une référence artistique reste une référence. | L19: art
A20: V86-GARNISONS-72-PNG | B20: Graphismes | C20: Distinguer corps statiques et kits animés | D20: docs/release-v86-excel-and-garrisons.md : 18 groupes / 72 PNG natifs | F20: LIVRE_PARTIEL | G20: Corps statiques documentés ; ce nombre ne valide ni toutes les animations ni une fidélité canonique 1:1. | H20: HISTORIQUE_V86 | I20: A_VALIDER | J20: docs/release-v86-excel-and-garrisons.md | K20: Auditer et intégrer les gestes requis dans leur contexte ; aucune clôture générale des kits à partir d'un idle. | L20: art
A21: PIT-V54-6-IDENTITES | B21: The Pit | C21: Conserver les six identités ou incarnations ouvertes | D21: Classeur V54 : 02_PERSONNAGES lignes 200 à 205 ; réconciliation V63 | E21: docs/v63-workbook-roster-audit.json | F21: OUVERT | G21: Six dossiers historiques ouverts, détaillés dans PitOuvertV99 ; le nombre de combattants runtime est compté séparément. | H21: HISTORIQUE_V63 | I21: NON_EXECUTE | J21: docs/v63-workbook-roster-audit.md docs/v63-workbook-roster-audit.json | K21: Identifier et sourcer chaque apparence, produire son kit puis la jouer ; ne pas certifier un kit complet depuis des variantes idle. | L21: pit
A22: PIT-V54-522-EVENEMENTS | B22: The Pit | C22: Rouvrir les événements avec leurs cellules exactes | D22: 174 dossiers / 522 descriptions de 10_VIE_DES_STAGES, réconciliation historique V63 | E22: docs/v63-stage-open-work.json | F22: OUVERT | G22: Les 522 descriptions et leur statut V63 sont reprises sans certifier tous les décors actuels. | H22: HISTORIQUE_V63 | I22: NON_EXECUTE | J22: docs/v63-stage-open-work.json docs/v63-followup-workbook-qa.json | K22: Recertifier sources, déclencheurs et conditions ; l'absence d'un registre V60–V63 ne prouve pas l'absence d'une animation legacy. | L22: pit
A23: PIT-ST103-GOLGOTHA | B23: The Pit | C23: Trio distinct de Golgotha encore ouvert | D23: 10_VIE_DES_STAGES!E311:E313 ; ST103, arena-187-golgotha-uscm-airlock | E23: docs/v63-stage-open-work.json | F23: OUVERT | G23: Adaptations V63 d'un autre dossier conservées ; ce trio distinct n'est pas livré par leur présence. | H23: HISTORIQUE_V63 | I23: NON_EXECUTE | J23: docs/v63-stage-open-work.json | K23: Vérifier la présence dans la scène primaire pour E313 avant toute silhouette et traiter séparément les trois événements. | L23: pit
A24: PIT-ST020-EVACUATION | B24: The Pit | C24: Évacuation hors du toit et chronologie de Wolf | D24: 10_VIE_DES_STAGES!E62 ; ST020, arena-126-avpr-2007-hospital-roof | E24: docs/v63-stage-open-work.json | F24: OUVERT | G24: Sprite conservé mais inactif sur le toit, où il contredit E505. | H24: HISTORIQUE_V63 | I24: NON_EXECUTE | J24: docs/v63-stage-open-work.json | K24: Trouver une continuité narrative ou hors toit vérifiée ; équipement et chronologie de Wolf toujours ouverts. | L24: pit

Sheet SourcesV99
A1: Inventaire des classeurs et des originaux manquants
A2: Empreinte du fichier local pour les présents ; empreinte de la source identifiée pour les originaux absents.
A3: Synthèse : SyntheseV99 · filtres ligne 4 · en-têtes figés
A4: Classeur | B4: Disponibilité | C4: Fichier local / extractions disponibles | D4: SHA-256 | E4: Feuilles présentes | F4: Contenu / portée | G4: Limite
A5: catalogue_yautja_tous_medias.xlsx | B5: PRESENT_CONSERVE | C5: art-source/v6/catalogue/catalogue_yautja_tous_medias.xlsx | D5: 6b696cabe94f0821f4bc02a1587ca5782789ffcc58ad52339626cc173515e68e | E5: 12 | F5: Synthèse ; Index maître ; Films & animation ; Jeux vidéo ; Comics & romans ; Kenner ; NECA ; Fan-films ; Alias & doublons ; Clans & classes ; Exclusions ; Sources | G5: Original local conservé sans réécriture ; les cinq feuilles du V63 sont aussi présentes dans le nouveau suivi.
A6: THE_PIT_STAGES_V60_SUIVI.xlsx | B6: PRESENT_CONSERVE | C6: docs/THE_PIT_STAGES_V60_SUIVI.xlsx | D6: d1ef8866b4cd94e5e90130efe8ed62a6c099dc0093215bd17348ff25c946ef04 | E6: 2 | F6: Stages ; Animations | G6: Original local conservé sans réécriture ; les cinq feuilles du V63 sont aussi présentes dans le nouveau suivi.
A7: THE_PIT_STAGES_V61_SUIVI.xlsx | B7: PRESENT_CONSERVE | C7: docs/THE_PIT_STAGES_V61_SUIVI.xlsx | D7: 5dd113dfb7cb40f3517ba4f1081bd1ece977a9fba3e9cedc01de87835effd2e6 | E7: 2 | F7: AnimationsV61 ; Resteclasseur | G7: Original local conservé sans réécriture ; les cinq feuilles du V63 sont aussi présentes dans le nouveau suivi.
A8: THE_PIT_V62_SUIVI.xlsx | B8: PRESENT_CONSERVE | C8: docs/THE_PIT_V62_SUIVI.xlsx | D8: c7c9986d872faf0cbc8398e697a28b9eae57328989fb09eed2881c431c1b57bb | E8: 3 | F8: LotV62 ; CombattantsV54 ; Resteclasseur | G8: Original local conservé sans réécriture ; les cinq feuilles du V63 sont aussi présentes dans le nouveau suivi.
A9: THE_PIT_V63_SUIVI.xlsx | B9: PRESENT_CONSERVE | C9: docs/THE_PIT_V63_SUIVI.xlsx | D9: 192b168456091239e65939b99c4630de791cfaca4f33f61a1c6a8a032fc9c7af | E9: 5 | F9: LotV62 ; CombattantsV54 ; Resteclasseur ; LotV63 ; StagesV54 | G9: Original local conservé sans réécriture ; les cinq feuilles du V63 sont aussi présentes dans le nouveau suivi.
A10: Yautja_V6_Bible_Cumulative_et_Dialogues.xlsx | B10: ORIGINAL_MANQUANT | C10: app/game/clanWarBibleV6Source.json public/game/dialogues/v85/bible-dialogues.json public/game/dialogues/v85/bible-ships.json | D10: 87ad5d1a6eaf49f2908a4457ef3f97b8f34db481a24bbc121d2e924559b19183 | F10: Original privé absent ; extractions de guerre, dialogues et navire présentes. Les 139 feuilles du classeur ne sont pas 139 fonctions livrées. | G10: Les extractions ne remplacent pas le fichier privé original ; aucun chemin privé utilisateur n’est reproduit.
A11: Yautja_V3_Guerres_de_Clans_Trois_Modes.xlsx | B11: ORIGINAL_MANQUANT | C11: app/game/clanWarV85Source.json | D11: 3ef3712c9ffa865f918133bee7667155c1bb320f060b4a19cc58ff650ffd0dfa | F11: Original privé absent ; extraction de 39 feuilles / 679 fiches conservée. Aucun solde V6 ni identifiant W3 n'est confondu avec le modèle V3. | G11: Les extractions ne remplacent pas le fichier privé original ; aucun chemin privé utilisateur n’est reproduit.
A12: Classeur source THE PIT V54 | B12: ORIGINAL_MANQUANT | C12: docs/v63-workbook-roster-audit.json docs/v63-stage-open-work.json | D12: 32f2ee8e4fd801e7ca677a54862f2bd0123a2e78d12c015f64b50ab28184c380 | F12: Original privé absent ; réconciliations historiques V63 disponibles, non recertifiées comme livraison intégrale V99. | G12: Les extractions ne remplacent pas le fichier privé original ; aucun chemin privé utilisateur n’est reproduit.

Sheet PlanetesV99
A1: 30 planètes · données des cartes réellement exportées
A2: Continents physiques ≠ régions administratives. Les couleurs de surface ne sont pas celles du contrôle des clans.
A3: Synthèse : SyntheseV99 · filtres ligne 4 · en-têtes figés
A4: ID | B4: Planète | C4: Famille | D4: Biome terrestre | E4: Surface non jouable | F4: Texture | G4: Couleur de fond | H4: Couleur de détail | I4: Continents | J4: Régions | K4: Territoires | L4: Terres (%) | M4: Routes | N4: Graphe connecté | O4: Écart côtes interrégion max (°) | P4: Provenance / fidélité
A5: korthas | B5: Korthas | C5: classic | D5: temperate | E5: Mers de cobalt | F5: water | G5: #164e6d | H5: #4f9cac | I5: 5 | J5: 6 | K5: 36 | L5: 60.76 | M5: 70 | N5: TRUE | O5: 19.5 | P5: Noms et règles V3 ; géographie originale V96/V97
A6: thalassa | B6: Thalassa | C6: classic | D6: jungle | E6: Lagons turquoise | F6: water | G6: #177e8b | H6: #61dfd1 | I6: 3 | J6: 6 | K6: 36 | L6: 57.41 | M6: 58 | N6: TRUE | O6: 19.5 | P6: Carte originale du projet ; pas une planète canonique certifiée
A7: vitriol | B7: Vitriol | C7: exotic | D7: swamp | E7: Acide émeraude | F7: acid | G7: #628d25 | H7: #c6ef43 | I7: 4 | J7: 6 | K7: 36 | L7: 58 | M7: 54 | N7: TRUE | O7: 19.5 | P7: Carte originale du projet ; pas une planète canonique certifiée
A8: nivalis | B8: Nivalis | C8: classic | D8: snow | E8: Banquise azurée | F8: ice | G8: #73aabd | H8: #bceaf3 | I8: 6 | J8: 6 | K8: 36 | L8: 49.46 | M8: 35 | N8: TRUE | O8: 3.87 | P8: Carte originale du projet ; pas une planète canonique certifiée
A9: serak | B9: Serak | C9: classic | D9: desert | E9: Mers de dunes ocre | F9: sand | G9: #ad773f | H9: #e6b66b | I9: 2 | J9: 6 | K9: 36 | L9: 62.72 | M9: 58 | N9: TRUE | O9: 17.53 | P9: Carte originale du projet ; pas une planète canonique certifiée
A10: pyroclaste | B10: Pyroclaste | C10: classic | D10: volcanic | E10: Lave incandescente | F10: lava | G10: #8a3021 | H10: #ff8d39 | I10: 2 | J10: 6 | K10: 36 | L10: 65.83 | M10: 59 | N10: TRUE | O10: 19.5 | P10: Carte originale du projet ; pas une planète canonique certifiée
A11: halycon | B11: Halycon | C11: classic | D11: salt | E11: Saumure rose | F11: brine | G11: #a65883 | H11: #ef9cc1 | I11: 4 | J11: 6 | K11: 36 | L11: 53.78 | M11: 52 | N11: TRUE | O11: 19.5 | P11: Carte originale du projet ; pas une planète canonique certifiée
A12: uranth | B12: Uranth | C12: exotic | D12: irradiated | E12: Nappes radioactives | F12: radioactive | G12: #467b2b | H12: #a7ff38 | I12: 4 | J12: 6 | K12: 36 | L12: 59.06 | M12: 45 | N12: TRUE | O12: 11.99 | P12: Carte originale du projet ; pas une planète canonique certifiée
A13: amethys | B13: Améthys | C13: exotic | D13: crystal | E13: Océan de cristaux violets | F13: crystal | G13: #6e438d | H13: #be90ec | I13: 6 | J13: 6 | K13: 36 | L13: 54.77 | M13: 43 | N13: TRUE | O13: 19.5 | P13: Carte originale du projet ; pas une planète canonique certifiée
A14: mycelia | B14: Mycélia | C14: exotic | D14: fungal | E14: Nappes de spores | F14: spores | G14: #4e6176 | H14: #b9d788 | I14: 4 | J14: 6 | K14: 36 | L14: 60.25 | M14: 59 | N14: TRUE | O14: 19.5 | P14: Carte originale du projet ; pas une planète canonique certifiée
A15: nebulis | B15: Nébulis | C15: classic | D15: mountain | E15: Brume des vallées | F15: mist | G15: #768991 | H15: #adbfc1 | I15: 4 | J15: 6 | K15: 36 | L15: 60.95 | M15: 52 | N15: TRUE | O15: 19.5 | P15: Carte originale du projet ; pas une planète canonique certifiée
A16: abyssia | B16: Abyssia | C16: classic | D16: ocean | E16: Fosses indigo | F16: water | G16: #293f83 | H16: #6a80da | I16: 6 | J16: 6 | K16: 36 | L16: 51.24 | M16: 40 | N16: TRUE | O16: 19.5 | P16: Carte originale du projet ; pas une planète canonique certifiée
... A34: nyctera | B34: Nyctéra | C34: exotic | D34: fungal | E34: Spores violettes | F34: spores | G34: #68517f | H34: #b39ed6 | I34: 6 | J34: 6 | K34: 36 | L34: 55.19 | M34: 59 | N34: TRUE | O34: 19.46 | P34: Carte originale du projet ; pas une planète canonique certifiée

Sheet OuvragesV6
A1: 18 ouvrages V6 · état de consommation ligne par ligne
A2: Le nombre actuel 12/18 ne réécrit pas le suivi historique V88 à 8/18. Le contexte libre reste distinct de la campagne.
A3: Synthèse : SyntheseV99 · filtres ligne 4 · en-têtes figés
A4: ID source | B4: Ouvrage | C4: Feuille | D4: Ligne | E4: Cellules source | F4: État runtime | G4: Adaptateur | H4: Coût RAV | I4: Délai tours | J4: Opérateur source | K4: Périmètre / reste | L4: SHA-256 source V6
A5: W3-S01 | B5: Poste de veille | C5: Structures de guerre | D5: 6 | E5: C6, D6, E6, F6, G6, H6, I6, J6, K6 | F5: INTEGRE_LIBRE | G5: watch | H5: 6 | I5: 2 | J5: W3-U02 | K5: Définition acceptée par le runtime libre actuel ; raccord campagne et certification globale non déduits. | L5: 87ad5d1a6eaf49f2908a4457ef3f97b8f34db481a24bbc121d2e924559b19183
A6: W3-S02 | B6: Abri de relève | C6: Structures de guerre | D6: 7 | E6: C7, D7, E7, F7, G7, H7, I7, J7, K7 | F6: INTEGRE_LIBRE | G6: rest | H6: 8 | I6: 2 | J6: W3-U17 | K6: Définition acceptée par le runtime libre actuel ; raccord campagne et certification globale non déduits. | L6: 87ad5d1a6eaf49f2908a4457ef3f97b8f34db481a24bbc121d2e924559b19183
A7: W3-S03 | B7: Cache logistique | C7: Structures de guerre | D7: 8 | E7: C8, D8, E8, F8, G8, H8, I8, J8, K8 | F7: INTEGRE_LIBRE | G7: stock | H7: 10 | I7: 2 | J7: W3-U19 | K7: Définition acceptée par le runtime libre actuel ; raccord campagne et certification globale non déduits. | L7: 87ad5d1a6eaf49f2908a4457ef3f97b8f34db481a24bbc121d2e924559b19183
A8: W3-S04 | B8: Atelier d’ancrage | C8: Structures de guerre | D8: 9 | E8: C9, D9, E9, F9, G9, H9, I9, J9, K9 | F8: INTEGRE_LIBRE | G8: repair | H8: 12 | I8: 2 | J8: W3-U20 | K8: Définition acceptée par le runtime libre actuel ; raccord campagne et certification globale non déduits. | L8: 87ad5d1a6eaf49f2908a4457ef3f97b8f34db481a24bbc121d2e924559b19183
A9: W3-S05 | B9: Balise de route | C9: Structures de guerre | D9: 10 | E9: C10, D10, E10, F10, G10, H10, I10, J10, K10 | F9: INTEGRE_LIBRE | G9: navigation | H9: 4 | I9: 2 | J9: W3-U06 | K9: Définition acceptée par le runtime libre actuel ; raccord campagne et certification globale non déduits. | L9: 87ad5d1a6eaf49f2908a4457ef3f97b8f34db481a24bbc121d2e924559b19183
A10: W3-S06 | B10: Plateforme de tir | C10: Structures de guerre | D10: 11 | E10: C11, D11, E11, F11, G11, H11, I11, J11, K11 | F10: INTEGRE_LIBRE | G10: platform | H10: 10 | I10: 2 | J10: W3-U13 | K10: Définition acceptée par le runtime libre actuel ; raccord campagne et certification globale non déduits. | L10: 87ad5d1a6eaf49f2908a4457ef3f97b8f34db481a24bbc121d2e924559b19183
A11: W3-S07 | B11: Seuil renforcé | C11: Structures de guerre | D11: 12 | E11: C12, D12, E12, F12, G12, H12, I12, J12, K12 | F11: INTEGRE_LIBRE | G11: defense | H11: 12 | I11: 2 | J11: W3-U07 | K11: Définition acceptée par le runtime libre actuel ; raccord campagne et certification globale non déduits. | L11: 87ad5d1a6eaf49f2908a4457ef3f97b8f34db481a24bbc121d2e924559b19183
A12: W3-S08 | B12: Pont de cordes | C12: Structures de guerre | D12: 13 | E12: C13, D13, E13, F13, G13, H13, I13, J13, K13 | F12: INTEGRE_LIBRE | G12: bridge | H12: 14 | I12: 3 | J12: W3-U12 | K12: Définition acceptée par le runtime libre actuel ; raccord campagne et certification globale non déduits. | L12: 87ad5d1a6eaf49f2908a4457ef3f97b8f34db481a24bbc121d2e924559b19183
A13: W3-S09 | B13: Quai léger | C13: Structures de guerre | D13: 14 | E13: C14, D14, E14, F14, G14, H14, I14, J14, K14 | F13: OUVERT | K13: Raccorder un quai à une rive praticable et à un transport réellement identifié ; pas de téléportation de cargaison. | L13: 87ad5d1a6eaf49f2908a4457ef3f97b8f34db481a24bbc121d2e924559b19183
A14: W3-S10 | B14: Aire de montures | C14: Structures de guerre | D14: 15 | E14: C15, D15, E15, F15, G15, H15, I15, J15, K15 | F14: OUVERT | K14: Identifier et déplacer les montures existantes, leurs gardiens et leur capacité ; ne pas créer une monture depuis un compteur. | L14: 87ad5d1a6eaf49f2908a4457ef3f97b8f34db481a24bbc121d2e924559b19183
A15: W3-S11 | B15: Poste de soin | C15: Structures de guerre | D15: 16 | E15: C16, D16, E16, F16, G16, H16, I16, J16, K16 | F15: INTEGRE_LIBRE | G15: medical | H15: 14 | I15: 3 | J15: W3-U18 | K15: Définition acceptée par le runtime libre actuel ; raccord campagne et certification globale non déduits. | L15: 87ad5d1a6eaf49f2908a4457ef3f97b8f34db481a24bbc121d2e924559b19183
A16: W3-S12 | B16: Relais de signaux | C16: Structures de guerre | D16: 17 | E16: C17, D17, E17, F17, G17, H17, I17, J17, K17 | F16: INTEGRE_LIBRE | G16: relay | H16: 12 | I16: 2 | J16: W3-U28 | K16: Définition acceptée par le runtime libre actuel ; raccord campagne et certification globale non déduits. | L16: 87ad5d1a6eaf49f2908a4457ef3f97b8f34db481a24bbc121d2e924559b19183
A17: W3-S13 | B17: Écran de confinement | C17: Structures de guerre | D17: 18 | E17: C18, D18, E18, F18, G18, H18, I18, J18, K18 | F17: OUVERT | K17: Raccorder l'alimentation et le coût réel de confinement ; aucun effet gratuit déduit de la description. | L17: 87ad5d1a6eaf49f2908a4457ef3f97b8f34db481a24bbc121d2e924559b19183
A18: W3-S14 | B18: Emplacement de duel | C18: Structures de guerre | D18: 19 | E18: C19, D19, E19, F19, G19, H19, I19, J19, K19 | F18: OUVERT | K18: Raccorder un duel accepté par ses participants et son résultat réel ; pas de victoire automatique. | L18: 87ad5d1a6eaf49f2908a4457ef3f97b8f34db481a24bbc121d2e924559b19183
A19: W3-S15 | B19: Station d’écoute | C19: Structures de guerre | D19: 20 | E19: C20, D20, E20, F20, G20, H20, I20, J20, K20 | F19: OUVERT | K19: Raccorder des sons enregistrés et situés, leur portée et leur occultation ; une direction de voix écrite n'est pas un son. | L19: 87ad5d1a6eaf49f2908a4457ef3f97b8f34db481a24bbc121d2e924559b19183
A20: W3-S16 | B20: Dépôt de retour | C20: Structures de guerre | D20: 21 | E20: C21, D21, E21, F21, G21, H21, I21, J21, K21 | F20: INTEGRE_LIBRE | G20: extraction | H20: 14 | I20: 3 | J20: W3-U17 | K20: Définition acceptée par le runtime libre actuel ; raccord campagne et certification globale non déduits. | L20: 87ad5d1a6eaf49f2908a4457ef3f97b8f34db481a24bbc121d2e924559b19183
A21: W3-S17 | B21: Anneau de treuils | C21: Structures de guerre | D21: 22 | E21: C22, D22, E22, F22, G22, H22, I22, J22, K22 | F21: INTEGRE_LIBRE | G21: hoist | H21: 16 | I21: 3 | J21: W3-U20 | K21: Définition acceptée par le runtime libre actuel ; raccord campagne et certification globale non déduits. | L21: 87ad5d1a6eaf49f2908a4457ef3f97b8f34db481a24bbc121d2e924559b19183
A22: W3-S18 | B22: Plateforme d’escale | C22: Structures de guerre | D22: 23 | E22: C23, D23, E23, F23, G23, H23, I23, J23, K23 | F22: OUVERT | K22: Raccorder un navire acquis et une route orbitale effective ; l'inspection documentaire ne donne ni navire ni voyage. | L22: 87ad5d1a6eaf49f2908a4457ef3f97b8f34db481a24bbc121d2e924559b19183

Sheet PitOuvertV99
A1: The Pit · six dossiers personnages laissés ouverts
A2: Réconciliation V63 reprise avec ses cellules et limites ; les kits et identités ne sont pas recertifiés par le suivi V99.
A3: Synthèse : SyntheseV99 · filtres ligne 4 · en-têtes figés
A4: ID dossier | B4: Identité / incarnation | C4: Cellules personnages | D4: Cellules manquants | E4: Statut historique V63 | F4: Reste à faire | G4: Portée | H4: SHA-256 source V54
A5: add-bloodshed | B5: Predator du tournoi — Bloodshed | C5: 02_PERSONNAGES!A200:V200 | D5: 03_MANQUANTS!A5:L5 | E5: missing-named-fighter | F5: Identité du tournoi attestée par Marvel ; apparence native et kit jouable manquants. Les dessins anonymes fournis ne permettent pas une attribution certaine. | G5: Historique V63 ; aucune recertification runtime V99 | H5: 32f2ee8e4fd801e7ca677a54862f2bd0123a2e78d12c015f64b50ab28184c380
A6: add-last-hunt-super | B6: Super Predator — The Last Hunt | C6: 02_PERSONNAGES!A201:V201 | D6: 03_MANQUANTS!A6:L6 | E6: missing-named-fighter | F6: Dossier distinct de Mr. Black. Référence de tenue et arsenal à verrouiller ; aucun ajout par simple renommage. | G6: Historique V63 ; aucune recertification runtime V99 | H6: 32f2ee8e4fd801e7ca677a54862f2bd0123a2e78d12c015f64b50ab28184c380
A7: add-jaguar | B7: Predator jouable — AVP Jaguar | C7: 02_PERSONNAGES!A202:V202 | D7: 03_MANQUANTS!A7:L7 | E7: missing-game-incarnation | F7: Incarnation AVP Jaguar absente ; ne pas substituer Dark, Prince ou Jungle Hunter. | G7: Historique V63 ; aucune recertification runtime V99 | H7: 32f2ee8e4fd801e7ca677a54862f2bd0123a2e78d12c015f64b50ab28184c380
A8: add-avp-classic | B8: Predator jouable — AVP Classic 2000 | C8: 02_PERSONNAGES!A203:V203 | D8: 03_MANQUANTS!A8:L8 | E8: missing-game-incarnation | F8: Incarnation AVP Classic 2000 absente ; user-classic-2010 appartient au film Predators. | G8: Historique V63 ; aucune recertification runtime V99 | H8: 32f2ee8e4fd801e7ca677a54862f2bd0123a2e78d12c015f64b50ab28184c380
A9: add-blood-ties-father | B9: Predator père — Blood Ties | C9: 02_PERSONNAGES!A204:V204 | D9: 03_MANQUANTS!A9:L9 | E9: candidate-needs-identification | F9: Père de Blood Ties : attribution visuelle à établir avant création ou réaffectation. | G9: Historique V63 ; aucune recertification runtime V99 | H9: 32f2ee8e4fd801e7ca677a54862f2bd0123a2e78d12c015f64b50ab28184c380
A10: add-blood-ties-son | B10: Predator fils — Blood Ties | C10: 02_PERSONNAGES!A205:V205 | D10: 03_MANQUANTS!A10:L10 | E10: candidate-needs-identification | F10: Fils de Blood Ties : identité distincte à établir, sans fusion avec les cycles I et II. | G10: Historique V63 ; aucune recertification runtime V99 | H10: 32f2ee8e4fd801e7ca677a54862f2bd0123a2e78d12c015f64b50ab28184c380

Sheet StagesOuvertsV99
A1: The Pit · 522 descriptions conservées et traçables
A2: Statut historique V63 conservé ; pas de recertification littérale V99. Une absence de registre moderne ne prouve pas une absence d’animation legacy.
A3: Synthèse : SyntheseV99 · filtres ligne 4 · en-têtes figés
A4: Dossier | B4: Stage | C4: Œuvre | D4: Cible runtime | E4: Événement source | F4: Cellule exacte | G4: Description originale | H4: État historique V63 | I4: Certification V99
A5: ST001 | B5: Clairière des pièges | C5: Predator 1987 | D5: arena-103-predator-1987-final-trap-clearing | E5: ST001_BG_01 | F5: 10_VIE_DES_STAGES!E5 | G5: Feuilles secouées par une fuite d’oiseaux | H5: not-recertified-by-V63 | I5: NON_RECERTIFIE_V99
A6: ST001 | B6: Clairière des pièges | C6: Predator 1987 | D6: arena-103-predator-1987-final-trap-clearing | E6: ST001_BG_02 | F6: 10_VIE_DES_STAGES!E6 | G6: Insectes en lisière, jamais devant les silhouettes | H6: not-recertified-by-V63 | I6: NON_RECERTIFIE_V99
A7: ST001 | B7: Clairière des pièges | C7: Predator 1987 | D7: arena-103-predator-1987-final-trap-clearing | E7: ST001_BG_03 | F7: 10_VIE_DES_STAGES!E7 | G7: Lointaine patrouille armée avant le duel, absente du face-à-face final | H7: not-recertified-by-V63 | I7: NON_RECERTIFIE_V99
A8: ST002 | B8: Vaisseau des trophées | C8: Predator 2 | D8: arena-106-predator-2-1990-trophy-ship | E8: ST002_BG_01 | F8: 10_VIE_DES_STAGES!E8 | G8: Membres anonymes du clan observant sans intervenir | H8: not-recertified-by-V63 | I8: NON_RECERTIFIE_V99
A9: ST002 | B9: Vaisseau des trophées | C9: Predator 2 | D9: arena-106-predator-2-1990-trophy-ship | E9: ST002_BG_02 | F9: 10_VIE_DES_STAGES!E9 | G9: Éclairage de niches passant doucement d’un trophée à l’autre | H9: not-recertified-by-V63 | I9: NON_RECERTIFIE_V99
A10: ST002 | B10: Vaisseau des trophées | C10: Predator 2 | D10: arena-106-predator-2-1990-trophy-ship | E10: ST002_BG_03 | F10: 10_VIE_DES_STAGES!E10 | G10: Ouverture furtive de la rampe et vapeur basse | H10: not-recertified-by-V63 | I10: NON_RECERTIFIE_V99
A11: ST003 | B11: Chambre sacrificielle | C11: AVP 2004 | D11: arena-122-avp-2004-sacrificial-chamber | E11: ST003_BG_01 | F11: 10_VIE_DES_STAGES!E11 | G11: Ombre de xénomorphe derrière une grille | H11: not-recertified-by-V63 | I11: NON_RECERTIFIE_V99
A12: ST003 | B12: Chambre sacrificielle | C12: AVP 2004 | D12: arena-122-avp-2004-sacrificial-chamber | E12: ST003_BG_02 | F12: 10_VIE_DES_STAGES!E12 | G12: Hologramme du labyrinthe sur un socle | H12: not-recertified-by-V63 | I12: NON_RECERTIFIE_V99
A13: ST003 | B13: Chambre sacrificielle | C13: AVP 2004 | D13: arena-122-avp-2004-sacrificial-chamber | E13: ST003_BG_03 | F13: 10_VIE_DES_STAGES!E13 | G13: Vapeur froide et poussière aux joints des murs | H13: not-recertified-by-V63 | I13: NON_RECERTIFIE_V99
A14: ST004 | B14: Épave de Gunnison | C14: AVPR | D14: arena-127-avpr-2007-forest-crash | E14: ST004_BG_01 | F14: 10_VIE_DES_STAGES!E14 | G14: Balise endommagée clignotant lentement | H14: not-recertified-by-V63 | I14: NON_RECERTIFIE_V99
A15: ST004 | B15: Épave de Gunnison | C15: AVPR | D15: arena-127-avpr-2007-forest-crash | E15: ST004_BG_02 | F15: 10_VIE_DES_STAGES!E15 | G15: Silhouette xénomorphe traversant une brèche éloignée | H15: not-recertified-by-V63 | I15: NON_RECERTIFIE_V99
... A526: ST174 | B526: Predator hunting grounds airstrip | C526: Adaptation d'œuvre · référence précise à verrouiller | D526: arena-136-predator-hunting-grounds-airstrip | E526: ST174_BG_03 | F526: 10_VIE_DES_STAGES!E526 | G526: Silhouette de fond uniquement après validation de sa présence dans la scène | H526: not-recertified-by-V63 | I526: NON_RECERTIFIE_V99

Sheet ValidationsV99
A1: Preuves et périmètres de validation
A2: Le statut HISTORIQUE garde sa version ; un chemin de test ne signifie pas que ce test a été exécuté.
A3: Synthèse : SyntheseV99 · filtres ligne 4 · en-têtes figés
A4: ID preuve | B4: Périmètre vérifié | C4: Résultat | D4: Commande / mode opératoire | E4: Fichiers de preuve | F4: Limites
A5: V98-HISTORIQUE | B5: Trois modes avant V99 : 105 tests ciblés, 54 vérifications navigateur ; 17 répétitions Preserve distinctes des cas uniques | C5: HISTORIQUE | D5: Voir docs/integration-v98.md | E5: docs/integration-v98.md outputs/qa-three-modes-v98/verification.json | F5: Preuve historique, pas une nouvelle exécution V99 ni une certification complète des classeurs.
A6: V63-CLASSEUR-HISTORIQUE | B6: Lecture et compteurs du classeur V63 ; original Excel natif non lancé | C6: HISTORIQUE | D6: Voir docs/v63-followup-workbook-qa.json | E6: docs/v63-followup-workbook-qa.json | F6: Les valeurs historiques ne deviennent pas automatiquement des faits runtime V99.
A7: CLANS-V99-MODELE | B7: 101/101 tests ciblés ; 11 garnisons V99, 4 revue (480 relèves), 9 commandement V98, 49 planètes, 6 session, 22 durabilité. ESLint ciblé propre. | C7: PASS_CIBLE | D7: node --test --test-reporter=spec tests/clan-war-garrison-v99.test.mjs tests/clan-war-garrison-review-v99.test.mjs tests/clan-war-command-v98.test.mjs tests/clan-war-planets-engine-v96.test.mjs tests/clan-war-session-v85.test.mjs tests/clan-war-durability-v94.test.mjs | E7: docs/clan-war-garrison-v99.md tests/clan-war-garrison-v99.test.mjs tests/clan-war-garrison-review-v99.test.mjs | F7: Aucun revenu immédiat, clôture des règles V3, campagne ou merge déduit des tests.
A8: PRESERVE-V99-MODELE | B8: 40/40 tests ciblés : 26 régressions V66/V98, 9 V99, 5 revue ; moteur, rendu et persistance. | C8: PASS_CIBLE | D8: node --test tests/game-reserve-v66.test.mjs tests/game-reserve-campaign-slots-v66.test.mjs tests/game-reserve-tactical-v98.test.mjs tests/game-reserve-interception-review-v98.test.mjs tests/game-reserve-supply-denial-v99.test.mjs tests/game-reserve-logistics-review-v99.test.mjs | E8: docs/v99-preserve-hunt-supply-denial.md tests/game-reserve-supply-denial-v99.test.mjs tests/game-reserve-logistics-review-v99.test.mjs | F8: 3/80 secteurs et 8/100 combattants ; zéro nouvelle image ou animation produite par ce lot.
A9: HOMEWORLD-V99-MODELE | B9: 18/18 cas ciblés : 4 navigation V99, 7 oracle V98, 4 SSR, 3 revue indépendante. Froid 3,54 fois plus rapide sur la mesure documentée. | C9: PASS_CIBLE | D9: node --experimental-strip-types --test --test-reporter=spec --test-concurrency=1 tests/homeworld-navigation-v99.test.mjs tests/homeworld-wayfinding-adversarial-v98.test.mjs tests/homeworld-wayfinding-ui-v98.test.mjs tests/homeworld-navigation-review-v99.test.mjs | E9: docs/homeworld-navigation-v99.md tests/homeworld-navigation-v99.test.mjs tests/homeworld-navigation-review-v99.test.mjs | F9: Mesure locale modèle, trajet 7,6 % plus long. La preuve navigateur, depuis une fixture déclarée et avec marche réelle, est consignée séparément dans HOMEWORLD-V99-CHROMIUM.
A10: CHROMIUM-V99-CLANS-PRESERVE | B10: Clans 26/26 et Preserve 26/26 contrôles sur le build production corrigé ; reload avec carnet/runtime réels, booléen secured et prompt mobile vérifiés. | C10: PASS_CIBLE | D10: node scripts/qa-three-modes-v99.mjs ; build t-1gCnL18QyMeOAc2vfmd | E10: scripts/qa-three-modes-v99.mjs outputs/qa-three-modes-v99/production/result.json | F10: Les 27 contrôles précédents étaient préfinaux et ne sont pas additionnés. Homeworld est vérifié séparément dans HOMEWORLD-V99-CHROMIUM ; publication et fusion sont suivies dans integration-v99.md.
A11: EXCEL-V99-CIBLE | B11: 6/6 tests Node ; génération de véritables archives, 18 parties V63 byte-identiques, 5 feuilles et styles historiques conservés, relations OOXML et 12 caches de formules vérifiés. | C11: PASS_CIBLE | D11: node --test --test-reporter=spec tests/excel-followup-v99.test.mjs ; node scripts/build-excel-followup-v99.mjs --check | E11: tests/excel-followup-v99.test.mjs docs/v99-excel-followup-qa.json | F11: ZIP/XML standard et lecture indépendante ; application Excel native et moteur de calcul Excel non exécutés.
A12: HOMEWORLD-V99-CHROMIUM | B12: 23/23 contrôles Homeworld dans la recette production de 76 contrôles (26 Clans, 26 Preserve, 23 Homeworld, 1 absence d’erreurs). Marche clavier, Escalier du Conseil vers +1, recalcul, pause/reprise et sauvegarde/Continuer réellement exercés ; 21 captures de la recette inspectées. | C12: PASS_CIBLE | D12: Voir scripts/qa-three-modes-v99.mjs ; build production t-1gCnL18QyMeOAc2vfmd | E12: outputs/qa-three-modes-v99/production/result.json outputs/qa-three-modes-v99/production/inspection.json docs/homeworld-navigation-v99.md | F12: Fixture de jeunesse préparée via les modèles auteur, non progression narrative jouée dans ce navigateur ; horloge contrôlée pendant marche et connecteur. Froid 2 988 ms / chaud 210 ms, même worker, premier palier 18 points ; 22 empreintes runtime identiques avant/après. Aucun déploiement public ou campagne complète certifié.

Sheet EntreesV99
A1: Empreintes des entrées de génération
A2: Ces fichiers et leurs empreintes rendent le suivi vérifiable en CI ; --check refuse un suivi devenu périmé.
A3: Synthèse : SyntheseV99 · filtres ligne 4 · en-têtes figés
A4: Entrée reproductible | B4: SHA-256 actuel
A5: app/game/clanWarBibleV6Source.json | B5: ce27085c44196fefa600407f0bc46cbb74934eb5437126b29d03d35a1e7a751d
A6: app/game/clanWarV85Source.json | B6: 58c77e7f555db2f61c8cf3905c0ae94798db9bdd10f66a5d58efd2cfe5a29114
A7: app/game/data/pitStageCompositionV63.json | B7: d913c3910e52fb01b1efa7a21b7b8123db3431cf5ab53978df85ed016cc64845
A8: app/game/data/pitStageCompositionV65.json | B8: 4fee1202e0b39e1aedcb50f45ed5c15982f4de0563e2d8e8356b2d8dc4e9d87f
A9: app/game/data/pitUserHuntersV44.json | B9: dbdb6d2dc993a93481d2d96a4dbe99bd75f0e37f3a1b70a7e4124feae79af7d7
A10: app/game/data/pitUserHuntersV62.json | B10: 3a860e299afd833d2fc32af5395ad9397a960ff9b4956776ba67ab620e259c52
A11: app/game/data/pitUserHuntersV79.json | B11: dd16fed6bbcf2227281e20b62214731347bdb4a4dbd7a5739e7f5bc7eca88247
A12: app/game/data/pitUserVariantsV63.json | B12: 9cbef2a8938f7d766b6dc90bd99f0d89c86d305c080d9d3afe3dd1ee0844f3be
A13: app/game/pitArenaProduction.ts | B13: b49fbe048bce45c1328dd28e1c1985f6588a6f5a23d16f4323e2d995d8b94a7c
A14: app/game/pitArenaProductionData.generated.json | B14: c07d5d314269548b50f7a4d564fd6e9c6583d2ac5d6033c56254340909d01f5b
A15: app/game/pitStageCompositionV63.ts | B15: bd26ea648513d2fffe3473c01dfd903c90b6b0f8227c0bed29eb69008b1e6192
... A53: scripts/build-excel-followup-v99.py | B53: afe57e86a692f463e0452c2aa27aca163ca64ef897be4e218798ce0dc31905ce

Sheet JournalV99
A1: Méthode, statut des données et limites
A2: Les cinq onglets V63 originaux restent présents avec leurs valeurs, formules et objets d’origine.
A3: Synthèse : SyntheseV99 · filtres ligne 4 · en-têtes figés
A4: Sujet | B4: Décision / limite
A5: Méthode | B5: Exports runtime compilés avec esbuild verrouillé ; déclarations de validation explicites ; archive V63 conservée et augmentée avec ZIP/XML standard.
A6: Registre humain | B6: docs/v99-workstreams-source.json
A7: Régénération | B7: node scripts/build-excel-followup-v99.mjs
A8: Vérification CI | B8: node scripts/build-excel-followup-v99.mjs --check
A9: Préservation | B9: Base docs/THE_PIT_V63_SUIVI.xlsx · SHA-256 192b168456091239e65939b99c4630de791cfaca4f33f61a1c6a8a032fc9c7af
A10: Limite 1 | B10: Les cinq feuilles du suivi V63 et tous les classeurs antérieurs sont conservés ; ce nouveau classeur n'est pas une modification des originaux privés.
A11: Limite 2 | B11: Présence d'un fichier, code livré, test réussi, image, animation et parcours joué sont des états distincts. Aucun test n'est déclaré passé par la seule existence de son fichier.
A12: Limite 3 | B12: Les comptes runtime sont extraits du code actuel ; les états de validation sont des déclarations explicites assorties de preuves, jamais déduites d'un nom de fichier.
A13: Limite 4 | B13: Le nombre de planètes classiques exprime une direction de biome du projet ; il ne certifie pas une planète ou une continuité canonique 1:1.
A14: Limite 5 | B14: Les compteurs Excel ont une valeur mise en cache et sont recalculables à l'ouverture ; aucune application Excel native n'est déclarée testée dans cet environnement.
A15: Lecture des états | B15: OUVERT : prérequis ou livraison manquants ; EN_COURS : modification en cours ; A_VALIDER : preuve à obtenir ; LIVRE_PARTIEL : périmètre limité livré ; VALIDE_CIBLE : cas explicitement prouvés, sans clôture globale.
A16: Formules | B16: Les formules de SyntheseV99 comptent les lignes et statuts des nouveaux onglets. Valeurs en cache générées ; recalcul demandé à l’ouverture. Les textes source, même commençant par =, restent des textes.

Sheet SyntheseV100
A1: YAUTJA · suivi actif V100
A2: Arrêté au 2026-10-20 · sources, art, étude, combat, preuves et reste séparés
A3: Synthèse : SyntheseV100 · filtres ligne 4 · en-têtes figés
A4: Indicateur | B4: Valeur | C4: Portée / limite
A5: Gestes source prévus | B5: =COUNTA('AnimationsV100'!B5:B56) -> 52 | C5: 26 par personnage ;18 gestes et8 présentations.
A6: Orientations demandées | B6: =COUNTA('OrientationsV100'!B5:B108) -> 104 | C6: Chaque geste garde deux orientations natives distinctes.
A7: Gestes admis dans les deux sens | B7: =COUNTIF('AnimationsV100'!G5:G56,"ADMIS_DEUX_SENS") -> 52 | C7: Admission art seulement, pas personnage complet.
A8: Orientations admises | B8: =COUNTIF('OrientationsV100'!E5:E108,"ADMIS_ETUDE") -> 104 | C8: Aucun miroir ne remplace une orientation absente.
A9: Frames référencées | B9: 508 | C9: Inclut les tenues répétées ; voir dessins réellement distincts.
A10: Dessins distincts par orientation | B10: 504 | C10: Pixels visibles SHA natifs, sans agrandir ni interpoler ; ne pas confondre avec frames.
A11: Nouveaux gestes raccordés visuellement au duel | B11: =COUNTIF('AnimationsV100'!L5:L56,"RACCORDE_VISUEL") -> 8 | C11: Phases existantes du runtime ; cible Excel non imposée.
A12: Gestes historiques conservés au duel | B12: =COUNTIF('AnimationsV100'!L5:L56,"HISTORIQUE_LIE") -> 2 | C12: P10 Feral V59 garde sa portée historique.
A13: Études admises sans raccord duel | B13: =COUNTIF('AnimationsV100'!L5:L56,"ETUDE_SEULE") -> 42 | C13: Étude visuelle : aucun état de combat inventé.
A14: Gestes encore sans admission complète | B14: 0 | C14: Manques calculés ; zéro quand les 52 études BODY sont admises dans les deux sens.
A15: Études BODY admises pour les 52 gestes | B15: OUI | C15: Études BODY natives admises dans les deux sens uniquement ; ne signifie pas personnages ou mécaniques complets.
A16: Preuve navigateur des études BODY | B16: PASS_CIBLE_BODY | C16: Lecteur, vrai duel et costumes à prouver après gel.
A17: Habitants urbains abordables existants | B17: =COUNTA('ContactsV100'!A5:A20) -> 16 | C17: 16 habitants conservés ; pas16 nouveaux personnages.
A18: Escortes aptes par patient | B18: 2 | C18: Adaptation logistique libre, pas valeur source canonique.
A19: Coût local évacuation S | B19: 1 | C19: Débit à la résolution, après réservation des personnes.
A20: Planètes runtime | B20: =COUNTA('PlanetesV100'!A5:A34) -> 30 | C20: 30 cartes du projet,16 classiques et14 exotiques ; canon 1:1 non déduit.
A21: Ouvrages encore ouverts | B21: =COUNTIF('OuvragesV100'!F5:F22,"OUVERT") -> 6 | C21: 18 ouvrages source,12 acceptés en contexte libre.
A22: Dossiers Pit historiques encore ouverts | B22: =COUNTA('PitOuvertV100'!A5:A10) -> 6 | C22: Aucune clôture de ces six dossiers V63.
A23: Chantiers EN_COURS | B23: =COUNTIF('ChantiersV100'!F5:F10,"EN_COURS") -> 0 | C23: Validation limitée au périmètre explicite du registre.
A24: Chantiers A_VALIDER | B24: =COUNTIF('ChantiersV100'!F5:F10,"A_VALIDER") -> 0 | C24: Validation limitée au périmètre explicite du registre.
A25: Chantiers OUVERT | B25: =COUNTIF('ChantiersV100'!F5:F10,"OUVERT") -> 1 | C25: Validation limitée au périmètre explicite du registre.
A26: Chantiers LIVRE_PARTIEL | B26: =COUNTIF('ChantiersV100'!F5:F10,"LIVRE_PARTIEL") -> 0 | C26: Validation limitée au périmètre explicite du registre.
A27: Chantiers VALIDE_CIBLE | B27: =COUNTIF('ChantiersV100'!F5:F10,"VALIDE_CIBLE") -> 5 | C27: Validation limitée au périmètre explicite du registre.
A28: Feuilles historiques V99 conservées | B28: 15 | C28: docs/YAUTJA_V99_SUIVI.xlsx
A29: Application Excel native vérifiée | B29: NON | C29: ZIP/XML, formules et caches vérifiés ; aucun moteur Excel exécuté.

Sheet ChantiersV100
A1: Chantiers V100 · livraison et preuves ciblées
A2: Les validations de développement ne deviennent pas des preuves production ; lire chaque reste.
A3: Synthèse : SyntheseV100 · filtres ligne 4 · en-têtes figés
A4: ID | B4: Domaine | C4: Chantier | D4: Source / cellules | E4: Implémentation | F4: Statut | G4: Périmètre | H4: Tests déclarés | I4: Navigateur | J4: Preuves / références | K4: Reste ouvert | L4: Responsable
A5: PIT-V100-FERAL | B5: The Pit | C5: Feral : dix-huit gestes et huit présentations source | D5: V54 : 05_MOVES_PROPOSES!D10:U10 ; 07_PRESENTATIONS!C10:J10 | E5: app/game/data/pitWorkbookAnimationPlanV100.json app/game/data/pitWorkbookAnimationsV100.json app/game/pitWorkbookCombatRegistryV100.ts | F5: VALIDE_CIBLE | G5: Le nombre de gestes admis, de dessins distincts et de raccordements visuels est recalculé depuis le runtime. Une étude ne crée pas les mécaniques du classeur. | H5: PASS 195 tests V100 et régressions V98/V99, dont les 15 tests animation/mesure ; zéro cas ignoré. | I5: PASS_PRODUCTION : 2 182 contrôles lecteur, 191 duel, 127 + 64 captures inspectées ; 52 études BODY et 104 sens, huit nouveaux raccords visuels. | J5: tests/pit-workbook-animation-v100.test.mjs scripts/qa-pit-workbook-v100.mjs scripts/qa-pit-combat-v100.mjs docs/v100-validation-summary.json | K5: Implémenter séparément les mécaniques source, entités/accessoires, victimes synchronisées et variantes encore ouvertes. La validation présente couvre les études BODY consultables et les raccords visuels existants. | L5: animation_engine_v100
A6: PIT-V100-SCAR | B6: The Pit | C6: Scar : dix-huit gestes et huit présentations source | D6: V54 : 05_MOVES_PROPOSES!D7:U7 ; 07_PRESENTATIONS!C7:J7 | E6: app/game/data/pitWorkbookAnimationPlanV100.json app/game/data/pitWorkbookAnimationsV100.json | F6: VALIDE_CIBLE | G6: Les admissions concernent l’apparence BODY d’origine et les orientations réellement dessinées. Les costumes fournis ne sont pas implicitement animés. | H6: PASS 195 tests V100 et régressions V98/V99, dont les 15 tests animation/mesure ; zéro cas ignoré. | I6: PASS_PRODUCTION : 2 182 contrôles lecteur, 191 duel, 127 + 64 captures inspectées ; 52 études BODY et 104 sens, huit nouveaux raccords visuels. | J6: tests/pit-workbook-animation-v100.test.mjs scripts/qa-pit-workbook-v100.mjs scripts/qa-pit-combat-v100.mjs docs/v100-validation-summary.json | K6: Implémenter séparément les mécaniques source, entités/accessoires, victimes synchronisées et variantes encore ouvertes. La validation présente couvre les études BODY consultables et les raccords visuels existants. | L6: animation_source_v100
A7: PIT-V100-LECTURE | B7: The Pit | C7: Lecteurs publics et laboratoire des gestes du classeur | D7: 52 cellules V54 identifiées ; matrice V100 et admissions natives explicites | E7: app/game/PitWorkbookAnimationViewerV100.tsx app/pit-lab/PitWorkbookAnimationLabV100.tsx app/game/PitSelectionFlow.tsx app/game/pitWorkbookAnimationV100.ts | F7: VALIDE_CIBLE | G7: Lecture, curseur, pause et orientations natives ; absence visible pour les gestes sans dessins. L’atelier historique /pit-lab reste public ; les trois routes QA locales gardent leur protection distincte. | H7: PASS 195 tests V100 et régressions V98/V99, dont les 15 tests animation/mesure ; zéro cas ignoré. | I7: PASS_PRODUCTION : 2 182 contrôles lecteur, 191 duel, 127 + 64 captures inspectées ; 52 études BODY et 104 sens, huit nouveaux raccords visuels. | J7: scripts/qa-pit-workbook-v100.mjs scripts/qa-pit-combat-v100.mjs docs/v100-validation-summary.json | K7: Implémenter séparément les mécaniques source, entités/accessoires, victimes synchronisées et variantes encore ouvertes. La validation présente couvre les études BODY consultables et les raccords visuels existants. | L7: qa_v100
A8: HOMEWORLD-V100-CONTACTS | B8: Homeworld | C8: Aborder seize habitants urbains existants | D8: Composition native V78/V84/V92 ; routines, étages et repères déjà connus | E8: app/game/systems/homeworldStreetContactsV100.ts app/game/systems/homeworldResidentVisibilityV100.ts app/game/HomeworldStreetConversationV100.tsx app/game/HomeworldHub.tsx app/game/HomeworldWorldSceneV77.tsx | F8: VALIDE_CIBLE | G8: Approche réelle à moins de96 unités, même étage et sol praticable, sans traverser le décor ; trois sujets locaux et repères déjà visités, sans déplacement ni récompense de campagne. | H8: PASS 43 tests ciblés modèle/SSR/callback et régressions ; déclaration explicite du lot | I8: PASS_PRODUCTION : 14 contrôles Homeworld dans la recette combinée de 37 ; captures desktop/mobile inspectées. Étage 0 au navigateur, autres contextes vérifiés au modèle. | J8: tests/homeworld-street-contacts-v100.test.mjs scripts/qa-worlds-v100.mjs outputs/qa-v100/dev-final/result.json docs/homeworld-street-contacts-v100.md docs/v100-validation-summary.json | K8: Valider le build final production. Les seize habitants existaient déjà ; la recette navigateur cible un contact avec marche clavier réelle depuis une fixture explicite, pas une campagne jouée ni seize conversations parcourues en navigateur. Les refus de mauvais étage, propriétaire ou visibilité sont prouvés par modèle/SSR/callback ; cette recette V100 ne prétend pas jouer un changement d’étage. | L8: homeworld_v100
A9: CLANS-V100-EVACUATION | B9: Guerre de clans | C9: Évacuer des blessés existants avec escortes réelles | D9: CON-R08/CON-R10 et EVOL-R14/EVOL-R15 ; adaptation logistique libre déclarée | E9: app/game/systems/clanWarEvacuationV100.ts app/game/systems/clanWarV85.ts app/game/ClanWarEvacuationV100.tsx app/game/ClanWarCommandV98.tsx | F9: VALIDE_CIBLE | G9: Route voisine amie, deux escortes aptes par patient, huit personnes maximum et S1 local à la résolution ; confirmation du dernier garde, blessés conservés et soins séparés. | H9: PASS 114 tests ciblés, dont 17 nouveaux, parmi lesquels 8 de revue indépendante ; déclaration explicite du lot | I9: PASS_PRODUCTION : 22 contrôles Clans dans la recette combinée de 37, dont archive après changement réel de planète ; captures inspectées, aucune guérison automatique. | J9: tests/clan-war-evacuation-v100.test.mjs tests/clan-war-evacuation-review-v100.test.mjs scripts/qa-worlds-v100.mjs outputs/qa-v100/dev-final/result.json docs/v100-validation-summary.json | K9: Valider le build final production. Le convoi P08/P02/P07 part d’une fixture explicite ; cette preuve ne clôt ni les règles V3/V6 globales, ni les six ouvrages encore ouverts, ni le raccord campagne. | L9: clans_v100
A10: PRESERVE-V100-HERITAGE | B10: Preserve Hunt | C10: Conserver les travaux V99 sans nouvelle clôture V100 | D10: SyntheseV99/ChantiersV99 et registre historique V99 préservés | F10: OUVERT | G10: Le lot V100 ne recertifie pas les missions, animations et secteurs restants de Preserve Hunt. | H10: HISTORIQUE : voir les feuilles V99 inchangées | I10: HISTORIQUE : aucune nouvelle recette Preserve V100 déclarée | J10: docs/YAUTJA_V99_SUIVI.xlsx | K10: Les limites historiques restent ouvertes : terrain3/80 secteurs,8/100 combattants, animations et missions à poursuivre ; une validation V99 n’est pas une nouvelle livraison V100. | L10: suivi_v100

Sheet AnimationsV100
A1: 52 gestes source · Feral et Scar
A2: 26 cellules exactes par personnage ; admission BODY native ≠ mécanique du classeur achevée.
A3: Synthèse : SyntheseV100 · filtres ligne 4 · en-têtes figés
A4: Personnage | B4: Geste source | C4: Commande source | D4: Libellé | E4: Feuille source | F4: Cellule | G4: Admission art | H4: Frames droite | I4: Frames gauche | J4: Dessins distincts droite | K4: Dessins distincts gauche | L4: Étude / combat | M4: Phases runtime raccordées | N4: Preuve finale | O4: Atlas natif | P4: SHA classeur V54 | Q4: SHA extraction V56 | R4: Timings proposés Excel | S4: Portée admission | T4: Texte source exact | U4: Reste / limite
A5: feral-hunter | B5: M_F006_5L | C5: 5L | D5: Jab de contrôle | E5: 05_MOVES_PROPOSES | F5: D10 | G5: ADMIS_DEUX_SENS | H5: 3 | I5: 3 | J5: 3 | K5: 3 | L5: RACCORDE_VISUEL | M5: pit.stand.light.startup pit.stand.light.active pit.stand.light.recovery | N5: PASS_CIBLE_BODY | O5: feral-source-5l-v100 | P5: 32f2ee8e4fd801e7ca677a54862f2bd0123a2e78d12c015f64b50ab28184c380 | Q5: fc8e1c6c81de62d8966e04746ed0751b0eeefc62f0458728c818896ad79972f4 | R5: 5 / 3 / 10 | S5: six dessins 5L · droite/gauche · préparation/contact/retour | T5: M_F006_5L · Jab de contrôle Commande L · Haut · Base de duel Arme : Lance scindée ; bouclier ; lance-carreaux Le bras avant frappe court ; la main et les lames éventuelles gardent leur côté réel. Préparation / actif / récupération : 5 / 3 / 10 images · dégâts 45 · coût 0 % Contre-jeu : Garde adaptée à la hauteur ; projection esquivable/techable ; punir la récupération. Règles de cancel à tester ; aucune boucle infinie ; pas d'invulnérabilité déduite du visuel. Corps : F006_ACT_5L Entité : Aucune · équipement : Voir 06_ARMES Adaptation originale sourcée · Cible de design à 60 Hz, non implémentée | U5: Admission visuelle de portée limitée. Entités, accessoires, variantes, mécanique source et preuve finale restent distincts. Seules les six premières cellules 5L du prototype001 sont admises ; E10/5M reste refusé. Référence BODY fixe246px approuvée depuis tête≈13 et vraies soles≈258 de la première pose. Pivots placés entre les pieds au support alpha128 revu visuellement ; quelques pixels alpha3 détachés sont conservés et ne définissent pas les pieds. Deux côtés natifs, aucun miroir. Les durées Excel5/3/10 servent à l’inspection ; le vrai coup conserve4/3/9.
A6: feral-hunter | B6: M_F006_5M | C6: 5M | D6: Revers d'ouverture | E6: 05_MOVES_PROPOSES | F6: E10 | G6: ADMIS_DEUX_SENS | H6: 3 | I6: 3 | J6: 3 | K6: 3 | L6: ETUDE_SEULE | N6: PASS_CIBLE_BODY | O6: feral-source-5m-v100 | P6: 32f2ee8e4fd801e7ca677a54862f2bd0123a2e78d12c015f64b50ab28184c380 | Q6: fc8e1c6c81de62d8966e04746ed0751b0eeefc62f0458728c818896ad79972f4 | R6: 9 / 4 / 16 | S6: source-E10-5M-body-cycle | T6: M_F006_5M · Revers d'ouverture Commande M · Milieu · Base de duel Arme : Lance scindée ; bouclier ; lance-carreaux Rotation du buste et revers du gantelet ; pas de projectile associé à un simple coup. Préparation / actif / récupération : 9 / 4 / 16 images · dégâts 70 · coût 0 % Contre-jeu : Garde adaptée à la hauteur ; projection esquivable/techable ; punir la récupération. Règles de cancel à tester ; aucune boucle infinie ; pas d'invulnérabilité déduite du visuel. Corps : F006_ACT_5M Entité : Aucune · équipement : Voir 06_ARMES Adaptation originale sourcée · Cible de design à 60 Hz, non implémentée | U6: Admission visuelle de portée limitée. Entités, accessoires, variantes, mécanique source et preuve finale restent distincts. Originaux PNG copiés inchangés ; trois vrais dessins articulés par côté, calibration debout exclue. Double revue root/QA et texte exact E10 relu. Pivots manuels entre les deux appuis, soles alpha128 revues ; référence debout fixe indépendante par page, jamais par pose. Étude de revers source distincte de la percée à la lance actuelle ; aucune nouvelle liaison au coup moyen debout.
A7: feral-hunter | B7: M_F006_5H | C7: 5H | D7: Frappe d'engagement | E7: 05_MOVES_PROPOSES | F7: F10 | G7: ADMIS_DEUX_SENS | H7: 5 | I7: 5 | J7: 4 | K7: 4 | L7: HISTORIQUE_LIE | M7: pit.stand.heavy.startup pit.stand.heavy.active pit.stand.heavy.recovery | N7: PASS_CIBLE_BODY | O7: feral-actions-v59 | P7: 32f2ee8e4fd801e7ca677a54862f2bd0123a2e78d12c015f64b50ab28184c380 | Q7: fc8e1c6c81de62d8966e04746ed0751b0eeefc62f0458728c818896ad79972f4 | R7: 16 / 5 / 26 | S7: historical-native-shield-engagement-body-cycle | T7: M_F006_5H · Frappe d'engagement Commande H · Milieu · Base de duel Arme : Lance scindée ; bouclier ; lance-carreaux Avance du pied puis frappe lourde au contact avec l'arme de mêlée réellement portée. Préparation / actif / récupération : 16 / 5 / 26 images · dégâts 110 · coût 0 % Contre-jeu : Garde adaptée à la hauteur ; projection esquivable/techable ; punir la récupération. Règles de cancel à tester ; aucune boucle infinie ; pas d'invulnérabilité déduite du visuel. Corps : F006_ACT_5H Entité : Aucune · équipement : Voir 06_ARMES Adaptation originale sourcée · Cible de design à 60 Hz, non implémentée | U7: Admission visuelle de portée limitée. Entités, accessoires, variantes, mécanique source et preuve finale restent distincts. Réemploi des originaux BODY V59 déjà présents : pas d’engagement, frappe de bouclier au contact puis retrait,4dessins distincts par côté. Correspondance sourceF10/5H approuvée ; ne représente pas le déploiement/contre distinct deQ10/S2. La lecture conserve les durées natives13/5/22 du coup lourd actuel, ses effets et replays ; la cible Excel16/5/26 n’est pas appliquée.
A8: feral-hunter | B8: M_F006_2L | C8: 2L | D8: Arrêt de cheville | E8: 05_MOVES_PROPOSES | F8: G10 | G8: ADMIS_DEUX_SENS | H8: 3 | I8: 3 | J8: 3 | K8: 3 | L8: RACCORDE_VISUEL | M8: pit.crouch.light.startup pit.crouch.light.active pit.crouch.light.recovery | N8: PASS_CIBLE_BODY | O8: feral-source-2l-v100 | P8: 32f2ee8e4fd801e7ca677a54862f2bd0123a2e78d12c015f64b50ab28184c380 | Q8: fc8e1c6c81de62d8966e04746ed0751b0eeefc62f0458728c818896ad79972f4 | R8: 6 / 3 / 12 | S8: source-G10-2L-body-cycle | T8: M_F006_2L · Arrêt de cheville Commande 2+L · Bas · Base de duel Arme : Lance scindée ; bouclier ; lance-carreaux Appui bas et coup court à la jambe ; silhouette accroupie dédiée. Préparation / actif / récupération : 6 / 3 / 12 images · dégâts 35 · coût 0 % Contre-jeu : Garde adaptée à la hauteur ; projection esquivable/techable ; punir la récupération. Règles de cancel à tester ; aucune boucle infinie ; pas d'invulnérabilité déduite du visuel. Corps : F006_ACT_2L Entité : Aucune · équipement : Voir 06_ARMES Adaptation originale sourcée · Cible de design à 60 Hz, non implémentée | U8: Admission visuelle de portée limitée. Entités, accessoires, variantes, mécanique source et preuve finale restent distincts. Originaux PNG copiés inchangés ; trois vrais dessins articulés par côté, calibration debout exclue. Double revue root/QA et texte exact G10 relu. Pivots manuels entre les deux appuis, soles alpha128 revues ; référence debout fixe indépendante par page, jamais par pose. Raccordement visuel aux phases de la posture existante, règles/durées du duel conservées ; propriétés de garde, anti-air, dégâts et cancels Excel non implémentés.
A9: feral-hunter | B9: M_F006_2M | C9: 2M | D9: Balayage de contrôle | E9: 05_MOVES_PROPOSES | F9: H10 | G9: ADMIS_DEUX_SENS | H9: 3 | I9: 3 | J9: 3 | K9: 3 | L9: RACCORDE_VISUEL | M9: pit.crouch.medium.startup pit.crouch.medium.active pit.crouch.medium.recovery | N9: PASS_CIBLE_BODY | O9: feral-source-2m-v100 | P9: 32f2ee8e4fd801e7ca677a54862f2bd0123a2e78d12c015f64b50ab28184c380 | Q9: fc8e1c6c81de62d8966e04746ed0751b0eeefc62f0458728c818896ad79972f4 | R9: 11 / 4 / 21 | S9: source-H10-low-leg-sweep-body-cycle | T9: M_F006_2M · Balayage de contrôle Commande 2+M · Bas · Base de duel Arme : Lance scindée ; bouclier ; lance-carreaux Jambe ou manche balaie au ras du sol sans allonger artificiellement les membres. Préparation / actif / récupération : 11 / 4 / 21 images · dégâts 65 · coût 0 % Contre-jeu : Garde adaptée à la hauteur ; projection esquivable/techable ; punir la récupération. Règles de cancel à tester ; aucune boucle infinie ; pas d'invulnérabilité déduite du visuel. Corps : F006_ACT_2M Entité : Aucune · équipement : Voir 06_ARMES Adaptation originale sourcée · Cible de design à 60 Hz, non implémentée | U9: Admission visuelle de portée limitée. Entités, accessoires, variantes, mécanique source et preuve finale restent distincts. Original PNG inchangé ; rangée debout de calibration exclue du geste. Trois vrais dessins par côté : garde basse, balayage de jambe vers l’avant, retour. Double revue anatomique root/QA ; référence fixe388px depuis la tête aux semelles debout, pivots manuels entre appuis ou sur le pied porteur du balayage. La lecture suit les durées proposées11/4/21 ; le raccordement natif conserve les règles et durées actuelles du coup moyen accroupi, sans imposer les dégâts/hauteurs/cancels Excel.
A10: feral-hunter | B10: M_F006_2H | C10: 2H | D10: Interception montante | E10: 05_MOVES_PROPOSES | F10: I10 | G10: ADMIS_DEUX_SENS | H10: 3 | I10: 3 | J10: 3 | K10: 3 | L10: RACCORDE_VISUEL | M10: pit.crouch.heavy.startup pit.crouch.heavy.active pit.crouch.heavy.recovery | N10: PASS_CIBLE_BODY | O10: feral-source-2h-v100 | P10: 32f2ee8e4fd801e7ca677a54862f2bd0123a2e78d12c015f64b50ab28184c380 | Q10: fc8e1c6c81de62d8966e04746ed0751b0eeefc62f0458728c818896ad79972f4 | R10: 14 / 5 / 29 | S10: source-I10-2H-body-cycle | T10: M_F006_2H · Interception montante Commande 2+H · Milieu / anti-air · Base de duel Arme : Lance scindée ; bouclier ; lance-carreaux Montée du bras depuis la garde basse, zone de frappe limitée au geste. Préparation / actif / récupération : 14 / 5 / 29 images · dégâts 90 · coût 0 % Contre-jeu : Garde adaptée à la hauteur ; projection esquivable/techable ; punir la récupération. Règles de cancel à tester ; aucune boucle infinie ; pas d'invulnérabilité déduite du visuel. Corps : F006_ACT_2H Entité : Aucune · équipement : Voir 06_ARMES Adaptation originale sourcée · Cible de design à 60 Hz, non implémentée | U10: Admission visuelle de portée limitée. Entités, accessoires, variantes, mécanique source et preuve finale restent distincts. Originaux PNG copiés inchangés ; trois vrais dessins articulés par côté, calibration debout exclue. Double revue root/QA et texte exact I10 relu. Pivots manuels entre les deux appuis, soles alpha128 revues ; référence debout fixe indépendante par page, jamais par pose. Raccordement visuel aux phases de la posture existante, règles/durées du duel conservées ; propriétés de garde, anti-air, dégâts et cancels Excel non implémentés.
A11: feral-hunter | B11: M_F006_jL | C11: jL | D11: Contact aérien court | E11: 05_MOVES_PROPOSES | F11: J10 | G11: ADMIS_DEUX_SENS | H11: 3 | I11: 3 | J11: 3 | K11: 3 | L11: RACCORDE_VISUEL | M11: pit.air.light.startup pit.air.light.active pit.air.light.recovery | N11: PASS_CIBLE_BODY | O11: feral-source-jl-v100 | P11: 32f2ee8e4fd801e7ca677a54862f2bd0123a2e78d12c015f64b50ab28184c380 | Q11: fc8e1c6c81de62d8966e04746ed0751b0eeefc62f0458728c818896ad79972f4 | R11: 6 / 3 / 12 | S11: source-J10-jL-native-air-knee-fall | T11: M_F006_jL · Contact aérien court Commande Air+L · Haut · Base de duel Arme : Lance scindée ; bouclier ; lance-carreaux Genou ou coude bref en vol, sans nouveau saut ou vol permanent. Préparation / actif / récupération : 6 / 3 / 12 images · dégâts 35 · coût 0 % Contre-jeu : Garde adaptée à la hauteur ; projection esquivable/techable ; punir la récupération. Règles de cancel à tester ; aucune boucle infinie ; pas d'invulnérabilité déduite du visuel. Corps : F006_ACT_jL Entité : Aucune · équipement : Voir 06_ARMES Adaptation originale sourcée · Cible de design à 60 Hz, non implémentée | U11: Admission visuelle de portée limitée. Entités, accessoires, variantes, mécanique source et preuve finale restent distincts. Originaux inchangés, références debout0 exclues, trois gestes articulés par côté et double revue root/QA. Échelle fixe par page depuis le vrai masque aux semelles alpha128 ; pivots aériens depuis le haut du bassin + distance debout aux soles, jamais depuis les pieds repliés. Repères source conservés dans le manifeste d’admission. Genou court en vol puis reprise de chute, compatible avec les phases de light réellement aérien ; altitude, trajectoire, durées et dégâts historiques restent ceux du moteur.
A12: feral-hunter | B12: M_F006_jM | C12: jM | D12: Coupe aérienne | E12: 05_MOVES_PROPOSES | F12: K10 | G12: ADMIS_DEUX_SENS | H12: 3 | I12: 3 | J12: 3 | K12: 3 | L12: ETUDE_SEULE | N12: PASS_CIBLE_BODY | O12: feral-source-jm-v100 | P12: 32f2ee8e4fd801e7ca677a54862f2bd0123a2e78d12c015f64b50ab28184c380 | Q12: fc8e1c6c81de62d8966e04746ed0751b0eeefc62f0458728c818896ad79972f4 | R12: 10 / 5 / 18 | S12: source-K10-jM-native-body-study-both-facings | T12: M_F006_jM · Coupe aérienne Commande Air+M · Haut · Base de duel Arme : Lance scindée ; bouclier ; lance-carreaux Revers en l'air cohérent avec l'arme disponible, puis reprise du même cycle de chute. Préparation / actif / récupération : 10 / 5 / 18 images · dégâts 65 · coût 0 % Contre-jeu : Garde adaptée à la hauteur ; projection esquivable/techable ; punir la récupération. Règles de cancel à tester ; aucune boucle infinie ; pas d'invulnérabilité déduite du visuel. Corps : F006_ACT_jM Entité : Aucune · équipement : Voir 06_ARMES Adaptation originale sourcée · Cible de design à 60 Hz, non implémentée | U12: Admission visuelle de portée limitée. Entités, accessoires, variantes, mécanique source et preuve finale restent distincts. Originaux PNG inchangés et copies byte-identiques ; double revue root/QA, calibrations0 exclues. Échelle fixe propre à chaque page, vraie référence masque→semelles alpha128. Revers aérien suivi de rotation/retrait, deux sens natifs indépendants ; pivots virtuels issus du bassin et de la distance debout vers les semelles, jamais des orteils en vol. Étude indépendante : aucune identité du medium actuel à la lance scindée empruntée pour certifier ce revers. Les durées Excel réparties servent uniquement à cette lecture, sans modifier simulation/replays/coûts/règles.
A13: feral-hunter | B13: M_F006_jH | C13: jH | D13: Descente engagée | E13: 05_MOVES_PROPOSES | F13: L10 | G13: ADMIS_DEUX_SENS | H13: 3 | I13: 3 | J13: 3 | K13: 3 | L13: ETUDE_SEULE | N13: PASS_CIBLE_BODY | O13: feral-source-jh-v100 | P13: 32f2ee8e4fd801e7ca677a54862f2bd0123a2e78d12c015f64b50ab28184c380 | Q13: fc8e1c6c81de62d8966e04746ed0751b0eeefc62f0458728c818896ad79972f4 | R13: 15 / 6 / 24 | S13: source-L10-jH-native-descending-landing-study | T13: M_F006_jH · Descente engagée Commande Air+H · Haut · Base de duel Arme : Lance scindée ; bouclier ; lance-carreaux Poids engagé vers le sol ; la réception a sa propre récupération. Préparation / actif / récupération : 15 / 6 / 24 images · dégâts 100 · coût 0 % Contre-jeu : Garde adaptée à la hauteur ; projection esquivable/techable ; punir la récupération. Règles de cancel à tester ; aucune boucle infinie ; pas d'invulnérabilité déduite du visuel. Corps : F006_ACT_jH Entité : Aucune · équipement : Voir 06_ARMES Adaptation originale sourcée · Cible de design à 60 Hz, non implémentée | U13: Admission visuelle de portée limitée. Entités, accessoires, variantes, mécanique source et preuve finale restent distincts. Originaux inchangés, références debout0 exclues, trois gestes articulés par côté et double revue root/QA. Échelle fixe par page depuis le vrai masque aux semelles alpha128 ; pivots aériens depuis le haut du bassin + distance debout aux soles, jamais depuis les pieds repliés. Repères source conservés dans le manifeste d’admission. Lourde descendante avec réception distincte accroupie ; étude seule, aucun atterrissage, anti-air ou raccord de récupération encore aérienne imposé au moteur.
A14: feral-hunter | B14: M_F006_TH_F | C14: TH_F | D14: Projection avant | E14: 05_MOVES_PROPOSES | F14: M10 | G14: ADMIS_DEUX_SENS | H14: 6 | I14: 6 | J14: 6 | K14: 6 | L14: ETUDE_SEULE | N14: PASS_CIBLE_BODY | O14: feral-source-th_f-v100 | P14: 32f2ee8e4fd801e7ca677a54862f2bd0123a2e78d12c015f64b50ab28184c380 | Q14: fc8e1c6c81de62d8966e04746ed0751b0eeefc62f0458728c818896ad79972f4 | R14: 8 / 3 / 30 | S14: source-M10-TH_F-native-body-study-both-facings | T14: M_F006_TH_F · Projection avant Commande L+M · Projection · Base de duel Arme : Lance scindée ; bouclier ; lance-carreaux Saisie proche, pivot des hanches et rejet devant ; une échappée de projection reste possible. Préparation / actif / récupération : 8 / 3 / 30 images · dégâts 110 · coût 0 % Contre-jeu : Garde adaptée à la hauteur ; projection esquivable/techable ; punir la récupération. Règles de cancel à tester ; aucune boucle infinie ; pas d'invulnérabilité déduite du visuel. Corps : F006_ACT_TH_F Entité : Aucune · équipement : Voir 06_ARMES Adaptation originale sourcée · Cible de design à 60 Hz, non implémentée | U14: Admission visuelle de portée limitée. Entités, accessoires, variantes, mécanique source et preuve finale restent distincts. Originaux PNG inchangés et copies byte-identiques ; double revue root/QA, calibrations0 exclues. Échelle fixe propre à chaque page, vraie référence masque→semelles alpha128. Six étapes de saisie/rotation/rejet/suivi/reprise par sens, avec mannequin gris distinct. Pivots isolés sur les seuls pieds Feral, jamais sur la victime. Bouclier parfois occlus dans le rejet/retrait : aucune manipulation ou rétraction d’accessoire certifiée. Aucune projection du duel ou synchronisation de victime ajoutée. 022A+023B droite et036A+037B gauche revus comme projection vers la cible initiale. Les durées Excel réparties servent uniquement à cette lecture, sans modifier simulation/replays/coûts/règles.
A15: feral-hunter | B15: M_F006_TH_B | C15: TH_B | D15: Projection arrière | E15: 05_MOVES_PROPOSES | F15: N10 | G15: ADMIS_DEUX_SENS | H15: 6 | I15: 6 | J15: 6 | K15: 6 | L15: ETUDE_SEULE | N15: PASS_CIBLE_BODY | O15: feral-source-th_b-v100 | P15: 32f2ee8e4fd801e7ca677a54862f2bd0123a2e78d12c015f64b50ab28184c380 | Q15: fc8e1c6c81de62d8966e04746ed0751b0eeefc62f0458728c818896ad79972f4 | R15: 10 / 3 / 32 | S15: source-N10-TH_B-native-body-study-both-facings | T15: M_F006_TH_B · Projection arrière Commande 4+L+M · Projection · Base de duel Arme : Lance scindée ; bouclier ; lance-carreaux Le corps tourne sans téléportation, puis la cible est rejetée derrière sur un point valide. Préparation / actif / récupération : 10 / 3 / 32 images · dégâts 110 · coût 0 % Contre-jeu : Garde adaptée à la hauteur ; projection esquivable/techable ; punir la récupération. Règles de cancel à tester ; aucune boucle infinie ; pas d'invulnérabilité déduite du visuel. Corps : F006_ACT_TH_B Entité : Aucune · équipement : Voir 06_ARMES Adaptation originale sourcée · Cible de design à 60 Hz, non implémentée | U15: Admission visuelle de portée limitée. Entités, accessoires, variantes, mécanique source et preuve finale restent distincts. Originaux PNG inchangés et copies byte-identiques ; double revue root/QA, calibrations0 exclues. Échelle fixe propre à chaque page, vraie référence masque→semelles alpha128. Six étapes de saisie/rotation/rejet/suivi/reprise par sens, avec mannequin gris distinct. Pivots isolés sur les seuls pieds Feral, jamais sur la victime. Bouclier parfois occlus dans le rejet/retrait : aucune manipulation ou rétraction d’accessoire certifiée. Aucune projection du duel ou synchronisation de victime ajoutée. La séquence initialement gauche039A+040B rejette derrière vers la droite, puis garde orientée vers cette nouvelle cible ; le texte N10 ne prescrit pas le retour au sens initial. Essai043 coupé exclu. Les durées Excel réparties servent uniquement à cette lecture, sans modifier simulation/replays/coûts/règles.
A16: feral-hunter | B16: M_F006_6M | C16: 6M | D16: Pas de rupture | E16: 05_MOVES_PROPOSES | F16: O10 | G16: ADMIS_DEUX_SENS | H16: 3 | I16: 3 | J16: 3 | K16: 3 | L16: ETUDE_SEULE | N16: PASS_CIBLE_BODY | O16: feral-source-6m-v100 | P16: 32f2ee8e4fd801e7ca677a54862f2bd0123a2e78d12c015f64b50ab28184c380 | Q16: fc8e1c6c81de62d8966e04746ed0751b0eeefc62f0458728c818896ad79972f4 | R16: 17 / 5 / 26 | S16: source-O10-approach-shoulder-contact-return-study | T16: M_F006_6M · Pas de rupture Commande 6+M · Milieu · Base de duel Arme : Lance scindée ; bouclier ; lance-carreaux Pas d'approche et frappe de l'épaule ou du manche ; trajectoire spécifique à la masse de ce personnage. Préparation / actif / récupération : 17 / 5 / 26 images · dégâts 90 · coût 0 % Contre-jeu : Garde adaptée à la hauteur ; projection esquivable/techable ; punir la récupération. Règles de cancel à tester ; aucune boucle infinie ; pas d'invulnérabilité déduite du visuel. Corps : F006_ACT_6M Entité : Aucune · équipement : Voir 06_ARMES Adaptation originale sourcée · Cible de design à 60 Hz, non implémentée | U16: Admission visuelle de portée limitée. Entités, accessoires, variantes, mécanique source et preuve finale restent distincts. Deux originaux inchangés, trois dessins du geste par côté, référence debout0 exclue. Double revue root/QA deO10 : pas d’approche, heurt d’épaule avant avec bras en retrait, retour en garde. Références debout fixes570/572px par page ; pivots entre appuis relus sur les vraies semelles, pas sur les lames. Étude indépendante : aucun6M, déplacement, choc, dégât ou cancel ajouté au duel.
A17: feral-hunter | B17: M_F006_S1 | C17: S1 | D17: Carreaux guidés | E17: 05_MOVES_PROPOSES | F17: P10 | G17: ADMIS_DEUX_SENS | H17: 5 | I17: 5 | J17: 4 | K17: 4 | L17: HISTORIQUE_LIE | M17: pit.stand.technique.feral-guided-bolts-v58.startup pit.stand.technique.feral-guided-bolts-v58.active pit.stand.technique.feral-guided-bolts-v58.recovery | N17: PASS_CIBLE_BODY | O17: feral-actions-v59 | P17: 32f2ee8e4fd801e7ca677a54862f2bd0123a2e78d12c015f64b50ab28184c380 | Q17: fc8e1c6c81de62d8966e04746ed0751b0eeefc62f0458728c818896ad79972f4 | R17: 23 / 6 / 30 | S17: historical-native-guided-bolts-body-cycle | T17: M_F006_S1 · Carreaux guidés Commande 236+S · Selon trajectoire / prototype · Spécial Arme : Lance-carreaux Le masque fixe un point à l'instant du départ ; trois carreaux rejoignent ce point, sans poursuite infinie de la cible. Préparation / actif / récupération : 23 / 6 / 30 images · dégâts 115 · coût 30 % Contre-jeu : Changer de hauteur après acquisition ; démasqué, trajectoire directe seulement. Feral : carreaux distincts et visée dépendante du masque ; aucune conversion en canon plasma. Anatomie Feral spécifique ; pas de canon d'épaule classique ; la visée dépend du masque. Corps : F006_ACT_S1 Entité : E_F006_bolt · équipement : W_F006_lance-carreaux Adaptation originale sourcée · Cible de design ; le coût est un % de jauge, pas la valeur actuelle du moteur | U17: Admission visuelle de portée limitée. Entités, accessoires, variantes, mécanique source et preuve finale restent distincts. Réutilisation des originaux V59 déjà revus et joués, quatre dessins distincts par orientation. La bouche physique et les anciens replays restent inchangés. Ce cycle ne certifie ni sortie/rangement du lanceur ni la cible de timings Excel.
A18: feral-hunter | B18: M_F006_S2 | C18: S2 | D18: Déploiement du bouclier | E18: 05_MOVES_PROPOSES | F18: Q10 | G18: ADMIS_DEUX_SENS | H18: 6 | I18: 6 | J18: 6 | K18: 6 | L18: ETUDE_SEULE | N18: PASS_CIBLE_BODY | O18: feral-workbook-s2-v100 | P18: 32f2ee8e4fd801e7ca677a54862f2bd0123a2e78d12c015f64b50ab28184c380 | Q18: fc8e1c6c81de62d8966e04746ed0751b0eeefc62f0458728c818896ad79972f4 | R18: 9 / 18 / 25 | S18: source-action-native-shield-deployment-guard-edge-bash-recoil-fold-return-inspection-only | T18: M_F006_S2 · Déploiement du bouclier Commande 214+S · Selon trajectoire / prototype · Spécial Arme : Bouclier de poignet Les segments s'ouvrent devant l'avant-bras ; garde directionnelle puis coup de bord à courte portée. Préparation / actif / récupération : 9 / 18 / 25 images · dégâts 70 · coût 15 % Contre-jeu : Projection, frappe arrière ou attente ; la garde n'est pas permanente. Technique proposée pour The Pit ; valeurs à équilibrer. Anatomie Feral spécifique ; pas de canon d'épaule classique ; la visée dépend du masque. Corps : F006_ACT_S2 Entité : E_F006_shield · équipement : W_F006_bouclier-poignet Adaptation originale sourcée · Cible de design ; le coût est un % de jauge, pas la valeur actuelle du moteur | U18: Admission visuelle de portée limitée. Entités, accessoires, variantes, mécanique source et preuve finale restent distincts. Six vrais dessins du geste par côté, sur deux originaux inchangés ; calibrations debout exclues. Références fixes329/336px et pivots d’appui revus par page. Double revue producteur/moteur : déploiement des segments, garde directionnelle, coup de bord, recul, repli et retour. La lecture52ticks est une étude indépendante deQ10 ; aucune mécanique de garde/contre, entité de bouclier, durée de duel ou inventaire ajouté.
A19: feral-hunter | B19: M_F006_S3 | C19: S3 | D19: Lance scindée | E19: 05_MOVES_PROPOSES | F19: R10 | G19: ADMIS_DEUX_SENS | H19: 6 | I19: 6 | J19: 6 | K19: 6 | L19: ETUDE_SEULE | N19: PASS_CIBLE_BODY | O19: feral-workbook-s3-v100 | P19: 32f2ee8e4fd801e7ca677a54862f2bd0123a2e78d12c015f64b50ab28184c380 | Q19: fc8e1c6c81de62d8966e04746ed0751b0eeefc62f0458728c818896ad79972f4 | R19: 16 / 7 / 24 | S19: source-action-native-whole-spear-twist-separate-left-strike-right-counter-align-rejoin-inspection-only | T19: M_F006_S3 · Lance scindée Commande 623+S · Selon trajectoire / prototype · Spécial Arme : Lance séparable Dissociation mécanique de la lance en deux armes ; courte chaîne alternée, puis remise en place. Préparation / actif / récupération : 16 / 7 / 24 images · dégâts 110 · coût 10 % Contre-jeu : Punir le changement de prise ; ne pas afficher simultanément lance entière et moitiés. Technique proposée pour The Pit ; valeurs à équilibrer. Anatomie Feral spécifique ; pas de canon d'épaule classique ; la visée dépend du masque. Corps : F006_ACT_S3 Entité : Aucune · équipement : W_F006_lance-scindee Adaptation originale sourcée · Cible de design ; le coût est un % de jauge, pas la valeur actuelle du moteur | U19: Admission visuelle de portée limitée. Entités, accessoires, variantes, mécanique source et preuve finale restent distincts. R10. Six actual action drawings per facing, independently redrawn. Whole spear twists and separates into exactly two halves; left-hand strike then genuine right-hand counter (shield stays on left), alignment and rejoined whole. QA independent review approved the alternation and source sequence. Old B2/B3 same-left counter is EXCLUDED; unsafe A6/A7 are EXCLUDED. No third intact spear appears with halves. Slight drawing/design variation remains a visual-study scope, no new spear entity or duel mechanic. Fixed reviewed page body references and manually reviewed feet anchors. Independent engine review approved all four exact original pages; public copies are byte-identical and SHA-verified. Calibrations are excluded; playback durations are for visual inspection, not source mechanics.
A20: feral-hunter | B20: M_F006_S4 | C20: S4 | D20: Mine d'interdiction | E20: 05_MOVES_PROPOSES | F20: S10 | G20: ADMIS_DEUX_SENS | H20: 6 | I20: 6 | J20: 6 | K20: 6 | L20: ETUDE_SEULE | N20: PASS_CIBLE_BODY | O20: feral-workbook-s4-v100 | P20: 32f2ee8e4fd801e7ca677a54862f2bd0123a2e78d12c015f64b50ab28184c380 | Q20: fc8e1c6c81de62d8966e04746ed0751b0eeefc62f0458728c818896ad79972f4 | R20: 34 / 90 / 30 | S20: source-action-native-body-inspection-only-s4 | T20: M_F006_S4 · Mine d'interdiction Commande 22+S · Selon trajectoire / prototype · Spécial Arme : Mine de chasse Pose visible, clignotement d'armement puis activation de proximité ; armer n'inflige pas déjà des dégâts. Préparation / actif / récupération : 34 / 90 / 30 images · dégâts 105 · coût 35 % Contre-jeu : Frapper la mine, sauter son rayon ou provoquer l'activation à distance. Dispositif seulement si documenté pour le costume ; sinon option de gameplay explicitement dérivée. Anatomie Feral spécifique ; pas de canon d'épaule classique ; la visée dépend du masque. Corps : F006_ACT_S4 Entité : E_F006_mine · équipement : W_F006_mine Adaptation originale sourcée · Cible de design ; le coût est un % de jauge, pas la valeur actuelle du moteur | U20: Admission visuelle de portée limitée. Entités, accessoires, variantes, mécanique source et preuve finale restent distincts. S10. Six genuine BODY stages each facing: retrieve one device, crouch/place, release, step back, watch OFF and settle armed RED, with AMBER/OFF/RED states. One circular openwork crown only; no hip duplicate. Explicit bounded root review accepts remaining native drawing variation: mine normalized width is about19–21% larger on pageB than pageA (about3–4 display pixels at BODY128); stable physical scale or complete E_F006_mine is NOT certified. The source does not specify an exact device dimension. This is a free gameplay-derived study, not canon certification. Proximity activation, entity ownership, damage, explosion and duel binding remain UNIMPLEMENTED by this art. QA approved anatomy, actual alpha gutters and body movement; fixed body references A388/B314 with manually reviewed feet pivots. Calibrations are excluded; playback durations are for visual inspection, not source mechanics. Independent engine review opened the exact originals and public copies were verified byte-identical against declared SHA-256.
A21: feral-hunter | B21: M_F006_SUPER | C21: SUPER | D21: La signature — Pression et bouclier | E21: 05_MOVES_PROPOSES | F21: T10 | G21: ADMIS_DEUX_SENS | H21: 6 | I21: 6 | J21: 6 | K21: 6 | L21: ETUDE_SEULE | N21: PASS_CIBLE_BODY | O21: feral-workbook-super-v100 | P21: 32f2ee8e4fd801e7ca677a54862f2bd0123a2e78d12c015f64b50ab28184c380 | Q21: fc8e1c6c81de62d8966e04746ed0751b0eeefc62f0458728c818896ad79972f4 | R21: 24 / 8 / 48 | S21: source-action-native-shield-opener-draw-left-launcher-aim-recoil-recover-body-study-only | T21: M_F006_SUPER · La signature — Pression et bouclier Commande 236236+S · Ouverture bloquable · Super Arme : Lance-carreaux Confirme un contact court, puis prolonge « Carreaux guidés » dans une séquence à caméra bornée. Si le premier contact est gardé, la scène ne se déclenche pas. Préparation / actif / récupération : 24 / 8 / 48 images · dégâts 280 · coût 100 % Contre-jeu : Garder l'amorce ou sortir de portée ; récupération longue si manqué. Pas de nouveaux pouvoirs. Réutilise uniquement armes/entités autorisées pour le costume ; la cinématique n'efface pas les blessures. Corps : F006_ACT_SUPER Entité : E_F006_bolt · équipement : W_F006_lance-carreaux Adaptation originale sourcée · Super original non implémenté | U21: Admission visuelle de portée limitée. Entités, accessoires, variantes, mécanique source et preuve finale restent distincts. T10. Six actual stages each facing. Physically explicit staging keeps existing launcher secured low on LEFT side during LEFT shield bash, then LEFT fingers visibly draw it while that forearm shield folds, then raise/aim, mechanical recoil and recovery. Empty attachment during rightA2 is not a second launcher: no red receiver there. LEFT launcher and LEFT shield remain on their anatomical side; right wrist blades retracted. Independent QA review approved new03A pages and selected oldB complements. Right01b LEFT5 with missing launcher is excluded; old incorrect03/02 bash cells are excluded. No hit-confirm, super resource, actual bolt entity, inventory state, damage or duel binding is added. Fixed standing references and reviewed feet midpoint anchors. Calibrations are excluded; playback durations are for visual inspection, not source mechanics. Independent engine review opened all four originals; public copies are byte-identical and SHA-verified.
A22: feral-hunter | B22: M_F006_EQUIP | C22: EQUIP | D22: Préparer / ranger l'arme | E22: 05_MOVES_PROPOSES | F22: U10 | G22: ADMIS_DEUX_SENS | H22: 6 | I22: 6 | J22: 6 | K22: 6 | L22: ETUDE_SEULE | N22: PASS_CIBLE_BODY | O22: feral-workbook-equip-v100 | P22: 32f2ee8e4fd801e7ca677a54862f2bd0123a2e78d12c015f64b50ab28184c380 | Q22: fc8e1c6c81de62d8966e04746ed0751b0eeefc62f0458728c818896ad79972f4 | R22: 20 / 0 / 20 | S22: source-action-native-draw-two-halves-connect-split-guide-stow-inspection-only | T22: M_F006_EQUIP · Préparer / ranger l'arme Commande S+H · Sans dégâts · Équipement Arme : Lance scindée ; bouclier ; lance-carreaux Animation lisible de sortie ou rangement ; attaques d'arme interdites jusqu'à la fin de l'action. Les armes perdues ne réapparaissent pas. Préparation / actif / récupération : 20 / 0 / 20 images · dégâts 0 · coût 0 % Contre-jeu : Punir le changement de prise ; on ne s'équipe pas pendant une saisie, un hitstun ou un saut. Anatomie Feral spécifique ; pas de canon d'épaule classique ; la visée dépend du masque. Corps : F006_ACT_EQUIP Entité : Aucune · équipement : Voir feuille 06_ARMES Adaptation originale sourcée · Transition proposée ; inventaire à intégrer | U22: Admission visuelle de portée limitée. Entités, accessoires, variantes, mécanique source et preuve finale restent distincts. U10. Six actual action drawings per direction, preserving the left forearm shield, fully retracted right wrist blades, two physically drawn spear halves and their hip holders. No intact third spear while halves are held. Fixed standing body references A372px/B302px and manually reviewed feet midpoint pivots. No inventory, damage, equipment state or duel binding is added. Independent engine review approved the exact original pages; public copies are byte-identical and SHA-verified. Calibrations are excluded; playback durations are for visual inspection, not source mechanics.
A23: feral-hunter | B23: CIN_F006_INTRO | C23: INTRO | D23: Entrée — La visée retournée | E23: 07_PRESENTATIONS | F23: C10 | G23: ADMIS_DEUX_SENS | H23: 6 | I23: 6 | J23: 6 | K23: 6 | L23: ETUDE_SEULE | N23: PASS_CIBLE_BODY | O23: feral-workbook-intro-v100 | P23: 32f2ee8e4fd801e7ca677a54862f2bd0123a2e78d12c015f64b50ab28184c380 | Q23: fc8e1c6c81de62d8966e04746ed0751b0eeefc62f0458728c818896ad79972f4 | R23: Présentation : durées source proposées | S23: source-presentation-native-shield-deploy-mask-aim-spear-split-body-study-only | T23: CIN_F006_INTRO · Entrée — La visée retournée Le bouclier se déploie dans un cliquetis d'os et de métal. Le masque fixe un point puis la lance se sépare. Déclenchement : Avant le premier round ; 3 plans puis retour sans déplacement des collisions. 0–1 s : intention lisible ; 1–3 s : geste ; 3–5 s : pose de sortie. Taunt cible 0,8–1,2 s. Durées proposées. Sprite : F006_CIN_INTRO · objets : E_F006_bolt ; E_F006_shield ; E_F006_mine Lore : Anatomie Feral spécifique ; pas de canon d'épaule classique ; la visée dépend du masque. Adaptation / embranchement alternatif | U23: Admission visuelle de portée limitée. Entités, accessoires, variantes, mécanique source et preuve finale restent distincts. C10. Six actual authored action stages each facing: left shield starts deployment, full guard opens, mask fixes a point, two-hand grip, torsion, complete spear separation. Independent final QA opened all four originals and approved actual1..3; left B2 and B3 preserve two distinct sections, no rejoined third staff. Shield remains anatomical LEFT; intact spear begins RIGHT. Fixed mask-crown-to-Feral-soles references exclude hair and weapon tips. Native spacing edits preserve complete poses and true transparent gutters. No intro collision, three-plan staging, equipment inventory or sound mechanic is certified. Calibrations are excluded; playback durations are for visual inspection, not source mechanics.
A24: feral-hunter | B24: CIN_F006_VICTOIRE | C24: VICTOIRE | D24: Garder la preuve | E24: 07_PRESENTATIONS | F24: D10 | G24: ADMIS_DEUX_SENS | H24: 5 | I24: 5 | J24: 5 | K24: 5 | L24: ETUDE_SEULE | N24: PASS_CIBLE_BODY | O24: feral-workbook-victoire-v100 | P24: 32f2ee8e4fd801e7ca677a54862f2bd0123a2e78d12c015f64b50ab28184c380 | Q24: fc8e1c6c81de62d8966e04746ed0751b0eeefc62f0458728c818896ad79972f4 | R24: Présentation : durées source proposées | S24: source-presentation-native-recover-rejoin-bolt-check-listening-body-study-only | T24: CIN_F006_VICTOIRE · Garder la preuve Il récupère les parties de sa lance, contrôle les carreaux restants et écoute les bois plutôt que saluer des spectateurs. Déclenchement : Victoire de match ; ne pas déclencher de récompense de campagne depuis un duel libre. 0–1 s : intention lisible ; 1–3 s : geste ; 3–5 s : pose de sortie. Taunt cible 0,8–1,2 s. Durées proposées. Sprite : F006_CIN_VICTOIRE · objets : E_F006_bolt ; E_F006_shield ; E_F006_mine Lore : Anatomie Feral spécifique ; pas de canon d'épaule classique ; la visée dépend du masque. Adaptation / embranchement alternatif | U24: Admission visuelle de portée limitée. Entités, accessoires, variantes, mécanique source et preuve finale restent distincts. D10. Five actual action drawings each facing: recover first dropped spear part, recover second, rejoin mechanical spear, inspect remaining bolts in existing LEFT launcher, listen alertly without salute. QA opened final B08 in both directions and approved the mechanical two-ended red-core spear held RIGHT and short launcher LEFT, with correct two-arm grips. Drawing A carries a source ellipse between the assembled weapon and later launcher already in hand: no continuous launcher draw or inventory transition is claimed. Final B calibration0 and unneeded intermediate1 excluded, with genuine check2/listen3 retained. Native spear detail/shaft angle varies between independently authored sheets; no exact prop scale, forest decor, sound, ammunition counter or campaign victory lifecycle certified. Fixed body references use MASK crown and Feral feet, excluding spear tips and ground parts. Right final B08 abdomen is noticeably redder than page A; this native color variation is recorded, not claimed as a coherent skin-color transition. Calibrations are excluded; playback durations are for visual inspection, not source mechanics.
A25: feral-hunter | B25: CIN_F006_DEFAITE | C25: DEFAITE | D25: La garde cède | E25: 07_PRESENTATIONS | F25: E10 | G25: ADMIS_DEUX_SENS | H25: 6 | I25: 6 | J25: 6 | K25: 6 | L25: ETUDE_SEULE | N25: PASS_CIBLE_BODY | O25: feral-workbook-defaite-v100 | P25: 32f2ee8e4fd801e7ca677a54862f2bd0123a2e78d12c015f64b50ab28184c380 | Q25: fc8e1c6c81de62d8966e04746ed0751b0eeefc62f0458728c818896ad79972f4 | R25: Présentation : durées source proposées | S25: source-presentation-native-after-ko-shield-collapse-mask-search-fall-study-only | T25: CIN_F006_DEFAITE · La garde cède Le bouclier se replie de travers ; il cherche sa visée et chute dans la boue. Aucun canon plasma ne surgit. Déclenchement : Après KO ; toutes les entités offensives sont coupées avant la scène. 0–1 s : intention lisible ; 1–3 s : geste ; 3–5 s : pose de sortie. Taunt cible 0,8–1,2 s. Durées proposées. Sprite : F006_CIN_DEFAITE · objets : E_F006_bolt ; E_F006_shield ; E_F006_mine Lore : Anatomie Feral spécifique ; pas de canon d'épaule classique ; la visée dépend du masque. Adaptation / embranchement alternatif | U25: Admission visuelle de portée limitée. Entités, accessoires, variantes, mécanique source et preuve finale restent distincts. E10. Six actual source stages per direction: crooked left shield, loss of support, right hand seeks mask, knees ground, side fall, final collapse in a small local mud trace. Anatomical left shield/right wrist blades stay on their limbs. QA independent review approved the replacement A pages and complete final left B7. Right A reaches two knees earlier than left, allowed by the exact source. No offensive projectile/plasma, death entity, opponent or campaign state is added. Ground anchors manually reviewed on support feet/knees and collapsed ground-contact baseline. Fixed body references A-right645/A-left624/B336, never per-pose flattened height. Calibrations are excluded; playback durations are for visual inspection, not source mechanics. Independent engine review opened all three originals; public copies verified byte-identical and SHA-checked.
A26: feral-hunter | B26: CIN_F006_TAUNT_1 | C26: TAUNT_1 | D26: Le défi | E26: 07_PRESENTATIONS | F26: F10 | G26: ADMIS_DEUX_SENS | H26: 6 | I26: 6 | J26: 6 | K26: 6 | L26: ETUDE_SEULE | N26: PASS_CIBLE_BODY | O26: feral-workbook-taunt-1-v100 | P26: 32f2ee8e4fd801e7ca677a54862f2bd0123a2e78d12c015f64b50ab28184c380 | Q26: fc8e1c6c81de62d8966e04746ed0751b0eeefc62f0458728c818896ad79972f4 | R26: Présentation : durées source proposées | S26: source-presentation-native-right-blades-left-shield-rim-clack-voluntary-open-guard-body-study-only | T26: CIN_F006_TAUNT_1 · Le défi Il fait claquer le bord du bouclier contre sa lame, puis laisse volontairement une ouverture. Déclenchement : En garde neutre ; interrompable ; aucune invulnérabilité ni bonus caché. 0–1 s : intention lisible ; 1–3 s : geste ; 3–5 s : pose de sortie. Taunt cible 0,8–1,2 s. Durées proposées. Sprite : F006_CIN_TAUNT_1 · objets : E_F006_bolt ; E_F006_shield ; E_F006_mine Lore : Anatomie Feral spécifique ; pas de canon d'épaule classique ; la visée dépend du masque. Adaptation / embranchement alternatif | U26: Admission visuelle de portée limitée. Entités, accessoires, variantes, mécanique source et preuve finale restent distincts. F10. Six actual action stages each facing: approach right wrist blades to left shield, contact the shield seen in thin metallic edge profile, clack/compress, separate, deliberately expose/open guard with the same two blades, return. Root and producer review accept contact on the visible metal thickness of the rim, rather than imposing a particular orange paint pixel. The roots of the right blades are occluded by the open right palm in the exposed pose, remain aligned with the same gauntlet and are visible before/after; no extra hand or detached weapon is introduced. Correct anatomical LEFT shield and RIGHT blades persist. Native alpha2 gutters and all selected cells are safe. This is authored BODY choreography only: no sound event, taunt AI effect or combat opening mechanic implemented. Fixed reviewed MASK-crown-to-soles reference excludes hair and weapons. Independent final QA agreed with this contact/occlusion reading and approved both complete pages; contradictory earlier concerns are preserved in the intake ledger. Calibrations are excluded; playback durations are for visual inspection, not source mechanics.
A27: feral-hunter | B27: CIN_F006_TAUNT_2 | C27: TAUNT_2 | D27: Vérifier l'arme | E27: 07_PRESENTATIONS | F27: G10 | G27: ADMIS_DEUX_SENS | H27: 6 | I27: 6 | J27: 6 | K27: 6 | L27: ETUDE_SEULE | N27: PASS_CIBLE_BODY | O27: feral-workbook-taunt-2-v100 | P27: 32f2ee8e4fd801e7ca677a54862f2bd0123a2e78d12c015f64b50ab28184c380 | Q27: fc8e1c6c81de62d8966e04746ed0751b0eeefc62f0458728c818896ad79972f4 | R27: Présentation : durées source proposées | S27: source-action-native-body-inspection-only-taunt-2 | T27: CIN_F006_TAUNT_2 · Vérifier l'arme Feral interrompt un instant sa garde pour vérifier lance-carreaux. La caméra reste fixe ; le geste utilise un accessoire réellement équipé. Déclenchement : Variation seulement ; aucune arme nouvelle ne peut apparaître pour le taunt. 0–1 s : intention lisible ; 1–3 s : geste ; 3–5 s : pose de sortie. Taunt cible 0,8–1,2 s. Durées proposées. Sprite : F006_CIN_TAUNT_2 · objets : E_F006_bolt ; E_F006_shield ; E_F006_mine Lore : Anatomie Feral spécifique ; pas de canon d'épaule classique ; la visée dépend du masque. Adaptation / embranchement alternatif | U27: Admission visuelle de portée limitée. Entités, accessoires, variantes, mécanique source et preuve finale restent distincts. G10. Six genuine action drawings per direction: raise existing LEFT-hand three-rail launcher, rotate/inspect, RIGHT hand checks housing, release inspection, lower, settle. Same red receiver and rails, no extra ammo, reload, shoulder cannon or projectile. Left-hand grip and folded bracer side are stable; right wrist blades retracted. Independent QA review favorable. Fixed body references A272/B373 and manually reviewed feet anchors. Presentation study only, no new combat or equipment mechanic. Calibrations are excluded; playback durations are for visual inspection, not source mechanics. Independent engine review opened the exact originals and public copies were verified byte-identical against declared SHA-256.
A28: feral-hunter | B28: CIN_F006_FATALITE_1 | C28: FATALITE_1 | D28: À portée de lame | E28: 07_PRESENTATIONS | F28: H10 | G28: ADMIS_DEUX_SENS | H28: 6 | I28: 6 | J28: 6 | K28: 6 | L28: ETUDE_SEULE | N28: PASS_CIBLE_BODY | O28: feral-workbook-fatalite-1-v100 | P28: 32f2ee8e4fd801e7ca677a54862f2bd0123a2e78d12c015f64b50ab28184c380 | Q28: fc8e1c6c81de62d8966e04746ed0751b0eeefc62f0458728c818896ad79972f4 | R28: Présentation : durées source proposées | S28: source-presentation-native-full-choreography-gray-mannequin-basalt-scene-study-only | T28: CIN_F006_FATALITE_1 · À portée de lame La lance plaque la cible contre un relief ; le bouclier ferme le cadre avant le coup final. Un projectile de carreau n'est ajouté que si son masque est encore fonctionnel. Déclenchement : Seulement après victoire finale, contre une menace hostile adulte ; interdite en entraînement, entre alliés ou sur un civil désarmé. 0–1 s : intention lisible ; 1–3 s : geste ; 3–5 s : pose de sortie. Taunt cible 0,8–1,2 s. Durées proposées. Sprite : F006_CIN_FATALITE_1 · objets : E_F006_bolt ; E_F006_shield ; E_F006_mine Lore : Anatomie Feral spécifique ; pas de canon d'épaule classique ; la visée dépend du masque. Adaptation / embranchement alternatif | U28: Admission visuelle de portée limitée. Entités, accessoires, variantes, mécanique source et preuve finale restent distincts. H10. Six actual stages each facing: prepare, whole spear pin against small basalt support, anatomical LEFT shield screen, final contact truly hidden by opaque shield, effortful withdrawal, threat check and fold. QA independently approved all selected steps. Cropped right03b3 and unsafe originalA lower rows excluded. One spear, left shield stable, no projectile/gore or victory substitution. Gray articulated adult-sized mannequin and basalt are explicit scene-study stand-ins baked into these images: no real narrative victim, independent opponent synchronization, fatality input, lifecycle or duel binding implemented. Native spear-head detail varies between independently authored views; exact canon set/victim not certified. Fixed reviewed Feral body references and manually reviewed Feral-foot baselines exclude mannequin/slab feet. Calibrations are excluded; playback durations are for visual inspection, not source mechanics. Independent engine review opened every selected original; public PNG copies are byte-identical and SHA-verified.
A29: feral-hunter | B29: CIN_F006_FATALITE_2 | C29: FATALITE_2 | D29: Autre issue — À portée de lame | E29: 07_PRESENTATIONS | F29: I10 | G29: ADMIS_DEUX_SENS | H29: 7 | I29: 7 | J29: 7 | K29: 7 | L29: ETUDE_SEULE | N29: PASS_CIBLE_BODY | O29: feral-workbook-fatalite-2-v100 | P29: 32f2ee8e4fd801e7ca677a54862f2bd0123a2e78d12c015f64b50ab28184c380 | Q29: fc8e1c6c81de62d8966e04746ed0751b0eeefc62f0458728c818896ad79972f4 | R29: Présentation : durées source proposées | S29: source-presentation-native-parry-second-blade-withdraw-check-stow-gray-mannequin-study-only | T29: CIN_F006_FATALITE_2 · Autre issue — À portée de lame La première coupe dévie l'arme. Le chasseur entre au contact et termine avec la seconde lame. Il vérifie la fin de la menace puis rentre l'arme. Adapter les prises à Feral. Déclenchement : Seulement après victoire finale, contre une menace hostile adulte ; interdite en entraînement, entre alliés ou sur un civil désarmé. Variante validée seulement si l'arme correspondante est portée. 0–1 s : intention lisible ; 1–3 s : geste ; 3–5 s : pose de sortie. Taunt cible 0,8–1,2 s. Durées proposées. Sprite : F006_CIN_FATALITE_2 · objets : E_F006_bolt ; E_F006_shield ; E_F006_mine Lore : Anatomie Feral spécifique ; pas de canon d'épaule classique ; la visée dépend du masque. Adaptation / embranchement alternatif | U29: Admission visuelle de portée limitée. Entités, accessoires, variantes, mécanique source et preuve finale restent distincts. I10. Seven actual stages each facing: parry first training blade, close step, second blade contact, withdrawal and mannequin blade drops, threat check, join/control weapon, genuine final STOW with both compact halves at hips and hands released. Source does not prescribe first/second hand: left parry then right strike is valid. Corrected left shield stays on near anatomical LEFT arm. QA approved final left stow3; unsafe upper0/1 never counted or played. Packing from joined staff to compact hips is an endpoint ellipse, no new equipment/inventory mechanic. Gray articulated mannequin is an explicit scene-study stand-in: no real opponent duplicated in combat, independent victim/lifecycle synchronization absent. No gore/projectile or renamed victory pose. One fixed Feral body reference per page, reviewed Feral-feet anchors exclude mannequin feet. Calibrations are excluded; playback durations are for visual inspection, not source mechanics. Independent engine review opened every selected original; public PNG copies are byte-identical and SHA-verified.
A30: feral-hunter | B30: CIN_F006_CLEMENCE | C30: CLEMENCE | D30: Le duel suffit | E30: 07_PRESENTATIONS | F30: J10 | G30: ADMIS_DEUX_SENS | H30: 6 | I30: 6 | J30: 6 | K30: 6 | L30: ETUDE_SEULE | N30: PASS_CIBLE_BODY | O30: feral-workbook-clemence-v100 | P30: 32f2ee8e4fd801e7ca677a54862f2bd0123a2e78d12c015f64b50ab28184c380 | Q30: fc8e1c6c81de62d8966e04746ed0751b0eeefc62f0458728c818896ad79972f4 | R30: Présentation : durées source proposées | S30: source-presentation-native-disarm-breathing-space-case-recovery-exit-mannequin-scene-study-only | T30: CIN_F006_CLEMENCE · Le duel suffit Feral désarme l'adversaire, recule d'un pas et lui laisse reprendre son souffle. Il reprend l'objet de la mission sans prélever de trophée anatomique. Déclenchement : Version d'entraînement / allié / option violence réduite ; même durée de sortie. 0–1 s : intention lisible ; 1–3 s : geste ; 3–5 s : pose de sortie. Taunt cible 0,8–1,2 s. Durées proposées. Sprite : F006_CIN_CLEMENCE · objets : E_F006_bolt ; E_F006_shield ; E_F006_mine Lore : Anatomie Feral spécifique ; pas de canon d'épaule classique ; la visée dépend du masque. Adaptation / embranchement alternatif | U30: Admission visuelle de portée limitée. Entités, accessoires, variantes, mécanique source et preuve finale restent distincts. J10. Six actual action stages each facing: hook/disarm intact training blade, step back, open left palm allowing unharmed partner to breathe, take existing sealed mission case by handle, rise holding case, real departure step. Independent final QA opened all four originals and confirmed case present from A1 onward, not spawned at pickup; same two-latch closed case remains identifiable despite minor native proportions/trim variation. Shield stays anatomical LEFT, intact spear RIGHT and blades retracted. Final exit turns intentionally away from the partner and is not an erroneous mirrored facing. Gray articulated adult-sized neutral mannequin, dropped blade and case are baked scene-study props; no narrative victim, synchronized real opponent, campaign mission object/reward or inventory/disarm mechanic is implemented. Fixed MASK-crown-to-Feral-soles scale and manually reviewed Feral feet exclude mannequin, blade and case ground pixels. Calibrations are excluded; playback durations are for visual inspection, not source mechanics.
A31: scar | B31: M_F003_5L | C31: 5L | D31: Jab de contrôle | E31: 05_MOVES_PROPOSES | F31: D7 | G31: ADMIS_DEUX_SENS | H31: 3 | I31: 3 | J31: 3 | K31: 3 | L31: RACCORDE_VISUEL | M31: pit.stand.light.startup pit.stand.light.active pit.stand.light.recovery | N31: PASS_CIBLE_BODY | O31: scar-workbook-5L-v100 | P31: 32f2ee8e4fd801e7ca677a54862f2bd0123a2e78d12c015f64b50ab28184c380 | Q31: fc8e1c6c81de62d8966e04746ed0751b0eeefc62f0458728c818896ad79972f4 | R31: 5 / 3 / 10 | S31: source-D7-5L-body-cycle | T31: M_F003_5L · Jab de contrôle Commande L · Haut · Base de duel Arme : Lames ; combistick ; shuriken ; canon Le bras avant frappe court ; la main et les lames éventuelles gardent leur côté réel. Préparation / actif / récupération : 5 / 3 / 10 images · dégâts 45 · coût 0 % Contre-jeu : Garde adaptée à la hauteur ; projection esquivable/techable ; punir la récupération. Règles de cancel à tester ; aucune boucle infinie ; pas d'invulnérabilité déduite du visuel. Corps : F003_ACT_5L Entité : Aucune · équipement : Voir 06_ARMES Adaptation originale sourcée · Cible de design à 60 Hz, non implémentée | U31: Admission visuelle de portée limitée. Entités, accessoires, variantes, mécanique source et preuve finale restent distincts. Original PNG inchangé ; trois dessins distincts par orientation et accessoires BODY conservés. Double revue anatomique producteur/QA, pieds et référence debout fixes relus ; références de calibration exclues. Les cibles Excel servent uniquement à la lecture de cette étude ; le coup léger existant conserve ses durées, ses dégâts et ses règles actuelles.
A32: scar | B32: M_F003_5M | C32: 5M | D32: Revers d'ouverture | E32: 05_MOVES_PROPOSES | F32: E7 | G32: ADMIS_DEUX_SENS | H32: 3 | I32: 3 | J32: 3 | K32: 3 | L32: ETUDE_SEULE | N32: PASS_CIBLE_BODY | O32: scar-workbook-5m-v100 | P32: 32f2ee8e4fd801e7ca677a54862f2bd0123a2e78d12c015f64b50ab28184c380 | Q32: fc8e1c6c81de62d8966e04746ed0751b0eeefc62f0458728c818896ad79972f4 | R32: 9 / 4 / 16 | S32: source-E7-5M-body-cycle | T32: M_F003_5M · Revers d'ouverture Commande M · Milieu · Base de duel Arme : Lames ; combistick ; shuriken ; canon Rotation du buste et revers du gantelet ; pas de projectile associé à un simple coup. Préparation / actif / récupération : 9 / 4 / 16 images · dégâts 70 · coût 0 % Contre-jeu : Garde adaptée à la hauteur ; projection esquivable/techable ; punir la récupération. Règles de cancel à tester ; aucune boucle infinie ; pas d'invulnérabilité déduite du visuel. Corps : F003_ACT_5M Entité : Aucune · équipement : Voir 06_ARMES Adaptation originale sourcée · Cible de design à 60 Hz, non implémentée | U32: Admission visuelle de portée limitée. Entités, accessoires, variantes, mécanique source et preuve finale restent distincts. Originaux inchangés ; références debout de chaque page exclues, trois dessins articulés par côté et échelle corporelle fixe par page. Double revue producteur/QA, cellule E7 relue. Vrai revers au gantelet, distinct de la percée au combistick actuelle ; étude indépendante sans nouveau raccord au coup moyen debout.
A33: scar | B33: M_F003_5H | C33: 5H | D33: Frappe d'engagement | E33: 05_MOVES_PROPOSES | F33: F7 | G33: ADMIS_DEUX_SENS | H33: 4 | I33: 4 | J33: 4 | K33: 4 | L33: ETUDE_SEULE | N33: PASS_CIBLE_BODY | O33: scar-workbook-5h-v100 | P33: 32f2ee8e4fd801e7ca677a54862f2bd0123a2e78d12c015f64b50ab28184c380 | Q33: fc8e1c6c81de62d8966e04746ed0751b0eeefc62f0458728c818896ad79972f4 | R33: 16 / 5 / 26 | S33: source-F7-native-alpha-heavy-wrist-blade-study-only | T33: M_F003_5H · Frappe d'engagement Commande H · Milieu · Base de duel Arme : Lames ; combistick ; shuriken ; canon Avance du pied puis frappe lourde au contact avec l'arme de mêlée réellement portée. Préparation / actif / récupération : 16 / 5 / 26 images · dégâts 110 · coût 0 % Contre-jeu : Garde adaptée à la hauteur ; projection esquivable/techable ; punir la récupération. Règles de cancel à tester ; aucune boucle infinie ; pas d'invulnérabilité déduite du visuel. Corps : F003_ACT_5H Entité : Aucune · équipement : Voir 06_ARMES Adaptation originale sourcée · Cible de design à 60 Hz, non implémentée | U33: Admission visuelle de portée limitée. Entités, accessoires, variantes, mécanique source et preuve finale restent distincts. Deux nouvelles pages alpha natives, quatre gestes indépendants par sens : pas/engagement, lourde des lames anatomiques droites, retrait puis garde. Combistick continuellement dans la main anatomique gauche. Originaux imagegen inchangés et copies byte-identiques ; revues root/producteur, moteur et QA favorables, gouttières réelles, aucun magenta mesuré. Référence fixe masque→ligne des semelles alpha128 sur le vrai retour debout de chaque page : droite447, gauche385 ; pointe de lance et dreads exclues. Les pivots horizontaux sont les milieux des deux vrais pieds, jamais la pointe ou le seul pied le plus bas ; ROIs conservées dans reference-and-foot-review.json. La lecture source16/5/13/13 est indépendante de toute simulation. Remplace uniquement le recours historique V34 du lecteur ; page originale V34, son SHA et ses clips heavy de duel inchangés. Aucune nouvelle liaison mécanique au heavy actuel nommé Ascension au plasma.
A34: scar | B34: M_F003_2L | C34: 2L | D34: Arrêt de cheville | E34: 05_MOVES_PROPOSES | F34: G7 | G34: ADMIS_DEUX_SENS | H34: 3 | I34: 3 | J34: 3 | K34: 3 | L34: RACCORDE_VISUEL | M34: pit.crouch.light.startup pit.crouch.light.active pit.crouch.light.recovery | N34: PASS_CIBLE_BODY | O34: scar-workbook-2L-v100 | P34: 32f2ee8e4fd801e7ca677a54862f2bd0123a2e78d12c015f64b50ab28184c380 | Q34: fc8e1c6c81de62d8966e04746ed0751b0eeefc62f0458728c818896ad79972f4 | R34: 6 / 3 / 12 | S34: source-G7-2L-body-cycle | T34: M_F003_2L · Arrêt de cheville Commande 2+L · Bas · Base de duel Arme : Lames ; combistick ; shuriken ; canon Appui bas et coup court à la jambe ; silhouette accroupie dédiée. Préparation / actif / récupération : 6 / 3 / 12 images · dégâts 35 · coût 0 % Contre-jeu : Garde adaptée à la hauteur ; projection esquivable/techable ; punir la récupération. Règles de cancel à tester ; aucune boucle infinie ; pas d'invulnérabilité déduite du visuel. Corps : F003_ACT_2L Entité : Aucune · équipement : Voir 06_ARMES Adaptation originale sourcée · Cible de design à 60 Hz, non implémentée | U34: Admission visuelle de portée limitée. Entités, accessoires, variantes, mécanique source et preuve finale restent distincts. Original PNG inchangé ; trois dessins distincts par orientation et accessoires BODY conservés. Double revue anatomique producteur/QA, pieds et référence debout fixes relus ; références de calibration exclues. Les cibles Excel servent uniquement à la lecture de cette étude ; le coup léger existant conserve ses durées, ses dégâts et ses règles actuelles.
A35: scar | B35: M_F003_2M | C35: 2M | D35: Balayage de contrôle | E35: 05_MOVES_PROPOSES | F35: H7 | G35: ADMIS_DEUX_SENS | H35: 3 | I35: 3 | J35: 3 | K35: 3 | L35: RACCORDE_VISUEL | M35: pit.crouch.medium.startup pit.crouch.medium.active pit.crouch.medium.recovery | N35: PASS_CIBLE_BODY | O35: scar-workbook-2m-v100 | P35: 32f2ee8e4fd801e7ca677a54862f2bd0123a2e78d12c015f64b50ab28184c380 | Q35: fc8e1c6c81de62d8966e04746ed0751b0eeefc62f0458728c818896ad79972f4 | R35: 11 / 4 / 21 | S35: source-H7-2M-body-cycle | T35: M_F003_2M · Balayage de contrôle Commande 2+M · Bas · Base de duel Arme : Lames ; combistick ; shuriken ; canon Jambe ou manche balaie au ras du sol sans allonger artificiellement les membres. Préparation / actif / récupération : 11 / 4 / 21 images · dégâts 65 · coût 0 % Contre-jeu : Garde adaptée à la hauteur ; projection esquivable/techable ; punir la récupération. Règles de cancel à tester ; aucune boucle infinie ; pas d'invulnérabilité déduite du visuel. Corps : F003_ACT_2M Entité : Aucune · équipement : Voir 06_ARMES Adaptation originale sourcée · Cible de design à 60 Hz, non implémentée | U35: Admission visuelle de portée limitée. Entités, accessoires, variantes, mécanique source et preuve finale restent distincts. Originaux inchangés ; références debout de chaque page exclues, trois dessins articulés par côté et échelle corporelle fixe par page. Double revue producteur/QA, cellule H7 relue. Contact de balayage ancré sur le pied porteur : X385 droite et629,5 gauche (semelles alpha128, bande8px), pas au milieu de la jambe étendue et de l’appui. Phases du coup moyen accroupi actuel conservées ; hauteurs, dégâts et cancels Excel ne sont pas implémentés.
A36: scar | B36: M_F003_2H | C36: 2H | D36: Interception montante | E36: 05_MOVES_PROPOSES | F36: I7 | G36: ADMIS_DEUX_SENS | H36: 3 | I36: 3 | J36: 3 | K36: 3 | L36: ETUDE_SEULE | N36: PASS_CIBLE_BODY | O36: scar-workbook-2h-v100 | P36: 32f2ee8e4fd801e7ca677a54862f2bd0123a2e78d12c015f64b50ab28184c380 | Q36: fc8e1c6c81de62d8966e04746ed0751b0eeefc62f0458728c818896ad79972f4 | R36: 14 / 5 / 29 | S36: source-I7-grounded-rising-wrist-blade-study | T36: M_F003_2H · Interception montante Commande 2+H · Milieu / anti-air · Base de duel Arme : Lames ; combistick ; shuriken ; canon Montée du bras depuis la garde basse, zone de frappe limitée au geste. Préparation / actif / récupération : 14 / 5 / 29 images · dégâts 90 · coût 0 % Contre-jeu : Garde adaptée à la hauteur ; projection esquivable/techable ; punir la récupération. Règles de cancel à tester ; aucune boucle infinie ; pas d'invulnérabilité déduite du visuel. Corps : F003_ACT_2H Entité : Aucune · équipement : Voir 06_ARMES Adaptation originale sourcée · Cible de design à 60 Hz, non implémentée | U36: Admission visuelle de portée limitée. Entités, accessoires, variantes, mécanique source et preuve finale restent distincts. Étude native BODY sourceI7 ; garde basse puis montée réelle des lames, pieds au sol, retour. À gauche, une garde basse déjà admise005/index3 est explicitement partagée puis contact/reprise014/index2/3 ; la préparation014/index1 tournée à droite reste exclue. Cinq nouveaux dessins et une posture partagée, pas six nouveaux dessins. Les références debout fixes413/419/258px et les pivots de chaque page restent conservés. Double revue producteur/QA. Aucun raccord supplémentaire au profil lourd actuellement nommé Ascension au plasma ; propriétés anti-air/hauteur/dégâts Excel non implémentées.
A37: scar | B37: M_F003_jL | C37: jL | D37: Contact aérien court | E37: 05_MOVES_PROPOSES | F37: J7 | G37: ADMIS_DEUX_SENS | H37: 3 | I37: 3 | J37: 3 | K37: 3 | L37: ETUDE_SEULE | N37: PASS_CIBLE_BODY | O37: scar-workbook-jl-v100 | P37: 32f2ee8e4fd801e7ca677a54862f2bd0123a2e78d12c015f64b50ab28184c380 | Q37: fc8e1c6c81de62d8966e04746ed0751b0eeefc62f0458728c818896ad79972f4 | R37: 6 / 3 / 12 | S37: source-J7-jL-body-study-both-native-facings | T37: M_F003_jL · Contact aérien court Commande Air+L · Haut · Base de duel Arme : Lames ; combistick ; shuriken ; canon Genou ou coude bref en vol, sans nouveau saut ou vol permanent. Préparation / actif / récupération : 6 / 3 / 12 images · dégâts 35 · coût 0 % Contre-jeu : Garde adaptée à la hauteur ; projection esquivable/techable ; punir la récupération. Règles de cancel à tester ; aucune boucle infinie ; pas d'invulnérabilité déduite du visuel. Corps : F003_ACT_jL Entité : Aucune · équipement : Voir 06_ARMES Adaptation originale sourcée · Cible de design à 60 Hz, non implémentée | U37: Admission visuelle de portée limitée. Entités, accessoires, variantes, mécanique source et preuve finale restent distincts. Originaux PNG inchangés et copies vérifiées ; deux orientations indépendantes, texte sourceJ7 et anatomie revus par producteur/QA. Référence corporelle fixe propre à chaque page, calibrations exclues quand distinctes du geste. Pivots virtuels depuis le haut de ceinture/bassin et distance debout aux semelles, repères conservés dans leDTO. Gestes en vol et reprise de chute conservés sans agrandir les membres repliés. Lecture indépendante des règles, dégâts, coûts et cancels du classeur.
A38: scar | B38: M_F003_jM | C38: jM | D38: Coupe aérienne | E38: 05_MOVES_PROPOSES | F38: K7 | G38: ADMIS_DEUX_SENS | H38: 3 | I38: 3 | J38: 3 | K38: 3 | L38: ETUDE_SEULE | N38: PASS_CIBLE_BODY | O38: scar-workbook-jm-v100 | P38: 32f2ee8e4fd801e7ca677a54862f2bd0123a2e78d12c015f64b50ab28184c380 | Q38: fc8e1c6c81de62d8966e04746ed0751b0eeefc62f0458728c818896ad79972f4 | R38: 10 / 5 / 18 | S38: source-K7-jM-body-study-both-native-facings | T38: M_F003_jM · Coupe aérienne Commande Air+M · Haut · Base de duel Arme : Lames ; combistick ; shuriken ; canon Revers en l'air cohérent avec l'arme disponible, puis reprise du même cycle de chute. Préparation / actif / récupération : 10 / 5 / 18 images · dégâts 65 · coût 0 % Contre-jeu : Garde adaptée à la hauteur ; projection esquivable/techable ; punir la récupération. Règles de cancel à tester ; aucune boucle infinie ; pas d'invulnérabilité déduite du visuel. Corps : F003_ACT_jM Entité : Aucune · équipement : Voir 06_ARMES Adaptation originale sourcée · Cible de design à 60 Hz, non implémentée | U38: Admission visuelle de portée limitée. Entités, accessoires, variantes, mécanique source et preuve finale restent distincts. Originaux PNG inchangés et copies vérifiées ; deux orientations indépendantes, texte sourceK7 et anatomie revus par producteur/QA. Référence corporelle fixe propre à chaque page, calibrations exclues quand distinctes du geste. Pivots virtuels depuis le haut de ceinture/bassin et distance debout aux semelles, repères conservés dans leDTO. Gestes en vol et reprise de chute conservés sans agrandir les membres repliés. Lecture indépendante des règles, dégâts, coûts et cancels du classeur.
A39: scar | B39: M_F003_jH | C39: jH | D39: Descente engagée | E39: 05_MOVES_PROPOSES | F39: L7 | G39: ADMIS_DEUX_SENS | H39: 3 | I39: 3 | J39: 3 | K39: 3 | L39: ETUDE_SEULE | N39: PASS_CIBLE_BODY | O39: scar-workbook-jh-v100 | P39: 32f2ee8e4fd801e7ca677a54862f2bd0123a2e78d12c015f64b50ab28184c380 | Q39: fc8e1c6c81de62d8966e04746ed0751b0eeefc62f0458728c818896ad79972f4 | R39: 15 / 6 / 24 | S39: source-L7-jH-body-study-both-native-facings | T39: M_F003_jH · Descente engagée Commande Air+H · Haut · Base de duel Arme : Lames ; combistick ; shuriken ; canon Poids engagé vers le sol ; la réception a sa propre récupération. Préparation / actif / récupération : 15 / 6 / 24 images · dégâts 100 · coût 0 % Contre-jeu : Garde adaptée à la hauteur ; projection esquivable/techable ; punir la récupération. Règles de cancel à tester ; aucune boucle infinie ; pas d'invulnérabilité déduite du visuel. Corps : F003_ACT_jH Entité : Aucune · équipement : Voir 06_ARMES Adaptation originale sourcée · Cible de design à 60 Hz, non implémentée | U39: Admission visuelle de portée limitée. Entités, accessoires, variantes, mécanique source et preuve finale restent distincts. Originaux PNG inchangés et copies vérifiées ; deux orientations indépendantes, texte sourceL7 et anatomie revus par producteur/QA. Référence corporelle fixe propre à chaque page, calibrations exclues quand distinctes du geste. Pivots virtuels depuis le haut de ceinture/bassin et distance debout aux semelles, repères conservés dans leDTO. Préparation gauche32/index1 reliée au contact/réception27/index2/3 ; ancienne préparation27/index1 touchant le bord reste exclue. Réception réellement au sol, aucune phase aérienne/atterrissage du duel forcée. Lecture indépendante des règles, dégâts, coûts et cancels du classeur.
A40: scar | B40: M_F003_TH_F | C40: TH_F | D40: Projection avant | E40: 05_MOVES_PROPOSES | F40: M7 | G40: ADMIS_DEUX_SENS | H40: 6 | I40: 6 | J40: 6 | K40: 6 | L40: ETUDE_SEULE | N40: PASS_CIBLE_BODY | O40: scar-workbook-th_f-v100 | P40: 32f2ee8e4fd801e7ca677a54862f2bd0123a2e78d12c015f64b50ab28184c380 | Q40: fc8e1c6c81de62d8966e04746ed0751b0eeefc62f0458728c818896ad79972f4 | R40: 8 / 3 / 30 | S40: source-M7-TH_F-body-study-both-native-facings | T40: M_F003_TH_F · Projection avant Commande L+M · Projection · Base de duel Arme : Lames ; combistick ; shuriken ; canon Saisie proche, pivot des hanches et rejet devant ; une échappée de projection reste possible. Préparation / actif / récupération : 8 / 3 / 30 images · dégâts 110 · coût 0 % Contre-jeu : Garde adaptée à la hauteur ; projection esquivable/techable ; punir la récupération. Règles de cancel à tester ; aucune boucle infinie ; pas d'invulnérabilité déduite du visuel. Corps : F003_ACT_TH_F Entité : Aucune · équipement : Voir 06_ARMES Adaptation originale sourcée · Cible de design à 60 Hz, non implémentée | U40: Admission visuelle de portée limitée. Entités, accessoires, variantes, mécanique source et preuve finale restent distincts. Originaux PNG inchangés et copies vérifiées ; deux orientations indépendantes, texte sourceM7 et anatomie revus par producteur/QA. Référence corporelle fixe propre à chaque page, calibrations exclues quand distinctes du geste. Étude avec mannequin gris, prise/bascule/rejet/suivi/retour dessinés ; pivot isolé sur les appuis du chasseur, jamais sur le mannequin. Aucune victime de duel synchronisée ni projection mécanique ajoutée. À gauche, finale30/index5 coupée exclue, remplacée par33/index0 ; prise de lance23/index1 occluse, manipulation/rangement non certifiés. Lecture indépendante des règles, dégâts, coûts et cancels du classeur.
A41: scar | B41: M_F003_TH_B | C41: TH_B | D41: Projection arrière | E41: 05_MOVES_PROPOSES | F41: N7 | G41: ADMIS_DEUX_SENS | H41: 6 | I41: 6 | J41: 6 | K41: 6 | L41: ETUDE_SEULE | N41: PASS_CIBLE_BODY | O41: scar-workbook-th_b-v100 | P41: 32f2ee8e4fd801e7ca677a54862f2bd0123a2e78d12c015f64b50ab28184c380 | Q41: fc8e1c6c81de62d8966e04746ed0751b0eeefc62f0458728c818896ad79972f4 | R41: 10 / 3 / 32 | S41: source-N7-TH_B-body-study-both-native-facings | T41: M_F003_TH_B · Projection arrière Commande 4+L+M · Projection · Base de duel Arme : Lames ; combistick ; shuriken ; canon Le corps tourne sans téléportation, puis la cible est rejetée derrière sur un point valide. Préparation / actif / récupération : 10 / 3 / 32 images · dégâts 110 · coût 0 % Contre-jeu : Garde adaptée à la hauteur ; projection esquivable/techable ; punir la récupération. Règles de cancel à tester ; aucune boucle infinie ; pas d'invulnérabilité déduite du visuel. Corps : F003_ACT_TH_B Entité : Aucune · équipement : Voir 06_ARMES Adaptation originale sourcée · Cible de design à 60 Hz, non implémentée | U41: Admission visuelle de portée limitée. Entités, accessoires, variantes, mécanique source et preuve finale restent distincts. Originaux PNG inchangés et copies vérifiées ; deux orientations indépendantes, texte sourceN7 et anatomie revus par producteur/QA. Référence corporelle fixe propre à chaque page, calibrations exclues quand distinctes du geste. Étude avec mannequin gris, prise/bascule/rejet/suivi/retour dessinés ; pivot isolé sur les appuis du chasseur, jamais sur le mannequin. Aucune victime de duel synchronisée ni projection mécanique ajoutée. Rotation du corps et destination du mannequin derrière l’orientation initiale conservées. Lecture indépendante des règles, dégâts, coûts et cancels du classeur.
A42: scar | B42: M_F003_6M | C42: 6M | D42: Pas de rupture | E42: 05_MOVES_PROPOSES | F42: O7 | G42: ADMIS_DEUX_SENS | H42: 3 | I42: 3 | J42: 3 | K42: 3 | L42: ETUDE_SEULE | N42: PASS_CIBLE_BODY | O42: scar-workbook-6m-v100 | P42: 32f2ee8e4fd801e7ca677a54862f2bd0123a2e78d12c015f64b50ab28184c380 | Q42: fc8e1c6c81de62d8966e04746ed0751b0eeefc62f0458728c818896ad79972f4 | R42: 17 / 5 / 26 | S42: source-O7-6M-body-study-both-native-facings | T42: M_F003_6M · Pas de rupture Commande 6+M · Milieu · Base de duel Arme : Lames ; combistick ; shuriken ; canon Pas d'approche et frappe de l'épaule ou du manche ; trajectoire spécifique à la masse de ce personnage. Préparation / actif / récupération : 17 / 5 / 26 images · dégâts 90 · coût 0 % Contre-jeu : Garde adaptée à la hauteur ; projection esquivable/techable ; punir la récupération. Règles de cancel à tester ; aucune boucle infinie ; pas d'invulnérabilité déduite du visuel. Corps : F003_ACT_6M Entité : Aucune · équipement : Voir 06_ARMES Adaptation originale sourcée · Cible de design à 60 Hz, non implémentée | U42: Admission visuelle de portée limitée. Entités, accessoires, variantes, mécanique source et preuve finale restent distincts. Originaux PNG inchangés et copies vérifiées ; deux orientations indépendantes, texte sourceO7 et anatomie revus par producteur/QA. Référence corporelle fixe propre à chaque page, calibrations exclues quand distinctes du geste. Pas, heurt d’épaule avec bras compact, retour en garde ; aucune nouvelle commande6M ni translation de duel ajoutée. Lecture indépendante des règles, dégâts, coûts et cancels du classeur.
A43: scar | B43: M_F003_S1 | C43: S1 | D43: Allonge télescopique | E43: 05_MOVES_PROPOSES | F43: P7 | G43: ADMIS_DEUX_SENS | H43: 6 | I43: 6 | J43: 6 | K43: 6 | L43: ETUDE_SEULE | N43: PASS_CIBLE_BODY | O43: scar-special-s1-body-v100 | P43: 32f2ee8e4fd801e7ca677a54862f2bd0123a2e78d12c015f64b50ab28184c380 | Q43: fc8e1c6c81de62d8966e04746ed0751b0eeefc62f0458728c818896ad79972f4 | R43: 17 / 5 / 24 | S43: Native BODY artwork, source action choreography, alpha separation and manually reviewed foot pivots; not confirmation of combat mechanics. | T43: M_F003_S1 · Allonge télescopique Commande 236+S · Selon trajectoire / prototype · Spécial Arme : Combistick Le bâton s'allonge depuis les deux mains ; estoc long, puis rétraction. La pointe guide la zone de frappe. Préparation / actif / récupération : 17 / 5 / 24 images · dégâts 100 · coût 0 % Contre-jeu : Entrer sous l'allonge ou punir le retrait. Technique proposée pour The Pit ; valeurs à équilibrer. Ne pas anticiper la marque au début du récit ; alliance avec Lex, fin alternative signalée. Corps : F003_ACT_S1 Entité : Aucune · équipement : W_F003_combistick Adaptation originale sourcée · Cible de design ; le coût est un % de jauge, pas la valeur actuelle du moteur | U43: Admission visuelle de portée limitée. Entités, accessoires, variantes, mécanique source et preuve finale restent distincts. Six independently articulated drawings for each facing, with preparation, equipment action and recovery. Feet and complete weapon tips visually inspected; all12source cells have clear alpha gutters and zero visible border pixels. One fixed bodyHeightPx from the first upright head-to-feet reference for the whole atlas, no per-pose fitting. Horizontal pivots manually reviewed between actual supporting feet; vertical candidates reviewed as feet, not weapon tips. Original PNG copied byte-identically. No mirror, rigging, crop rewrite, chroma cleanup or pixel editing. BODY-only visual sequence: source mechanical phases and inventory/duel synchronization remain separate. Source-P7 admise comme étude BODY indépendante ; aucune nouvelle commande, entité, arme d’inventaire ou règle de duel n’est raccordée.
A44: scar | B44: M_F003_S2 | C44: S2 | D44: Étoile déployée | E44: 05_MOVES_PROPOSES | F44: Q7 | G44: ADMIS_DEUX_SENS | H44: 6 | I44: 6 | J44: 6 | K44: 6 | L44: ETUDE_SEULE | N44: PASS_CIBLE_BODY | O44: scar-special-s2-body-v100 | P44: 32f2ee8e4fd801e7ca677a54862f2bd0123a2e78d12c015f64b50ab28184c380 | Q44: fc8e1c6c81de62d8966e04746ed0751b0eeefc62f0458728c818896ad79972f4 | R44: 23 / 4 / 29 | S44: Native BODY artwork, source action choreography, alpha separation and manually reviewed foot pivots; not confirmation of combat mechanics. | T44: M_F003_S2 · Étoile déployée Commande 214+S · Selon trajectoire / prototype · Spécial Arme : Shuriken Ouverture mécanique des branches dans la main ; lancer et rotation lisible. Ne pas substituer le disque circulaire. Préparation / actif / récupération : 23 / 4 / 29 images · dégâts 90 · coût 25 % Contre-jeu : Esquiver la ligne ; projectile dissipé après contact selon les règles du duel. Technique proposée pour The Pit ; valeurs à équilibrer. Ne pas anticiper la marque au début du récit ; alliance avec Lex, fin alternative signalée. Corps : F003_ACT_S2 Entité : E_F003_shuriken · équipement : W_F003_shuriken Adaptation originale sourcée · Cible de design ; le coût est un % de jauge, pas la valeur actuelle du moteur | U44: Admission visuelle de portée limitée. Entités, accessoires, variantes, mécanique source et preuve finale restent distincts. Six independently articulated drawings for each facing, with preparation, equipment action and recovery. Feet and complete weapon tips visually inspected; all12source cells have clear alpha gutters and zero visible border pixels. One fixed bodyHeightPx from the first upright head-to-feet reference for the whole atlas, no per-pose fitting. Horizontal pivots manually reviewed between actual supporting feet; vertical candidates reviewed as feet, not weapon tips. Original PNG copied byte-identically. No mirror, rigging, crop rewrite, chroma cleanup or pixel editing. BODY-only visual sequence: source mechanical phases and inventory/duel synchronization remain separate. Corrected replacement for suspended S2 admission: ONE shuriken only. After extraction, hip slots are plain empty straps in every postdraw pose including left release and both returns. Actual hand opening, throwing, followthrough and reset remain six native drawings per facing. No restocking at belt, invented second device/holster explanation, inventory or projectile mechanic. First left reach is partly occluded by its hand; later half-open to fully-open weapon stages remain visible. This candidate uses a new public filename so the previously admitted PNG is preserved byte-identically. Independent engine and QA continuity review opened the corrected native source; the public copy is byte-identical and SHA-verified. Source cell is Q7.
A45: scar | B45: M_F003_S3 | C45: S3 | D45: Tir de plasma | E45: 05_MOVES_PROPOSES | F45: R7 | G45: ADMIS_DEUX_SENS | H45: 6 | I45: 6 | J45: 6 | K45: 6 | L45: ETUDE_SEULE | N45: PASS_CIBLE_BODY | O45: scar-special-s3-body-v100 | P45: 32f2ee8e4fd801e7ca677a54862f2bd0123a2e78d12c015f64b50ab28184c380 | Q45: fc8e1c6c81de62d8966e04746ed0751b0eeefc62f0458728c818896ad79972f4 | R45: 20 / 3 / 28 | S45: Native BODY artwork, source action choreography, alpha separation and manually reviewed foot pivots; not confirmation of combat mechanics. | T45: M_F003_S3 · Tir de plasma Commande 623+S · Selon trajectoire / prototype · Spécial Arme : Canon d'épaule Le canon s'aligne ; la bouche s'illumine puis libère un trait rectiligne. Le corps peut être puni durant la visée. Préparation / actif / récupération : 20 / 3 / 28 images · dégâts 105 · coût 25 % Contre-jeu : Baisser la tête sous le tir haut, sauter ou punir la récupération. Technique proposée pour The Pit ; valeurs à équilibrer. Ne pas anticiper la marque au début du récit ; alliance avec Lex, fin alternative signalée. Corps : F003_ACT_S3 Entité : E_F003_plasma · équipement : W_F003_canon-epaule Adaptation originale sourcée · Cible de design ; le coût est un % de jauge, pas la valeur actuelle du moteur | U45: Admission visuelle de portée limitée. Entités, accessoires, variantes, mécanique source et preuve finale restent distincts. Six independently articulated drawings for each facing, with preparation, equipment action and recovery. Feet and complete weapon tips visually inspected; all six source cells per orientation have clear alpha gutters and zero visible border pixels. One fixed body reference per native page, no per-pose fitting. Horizontal pivots manually reviewed between actual supporting feet; vertical candidates reviewed as feet, not weapon tips. Original PNG copied byte-identically. No mirror, rigging, crop rewrite, chroma cleanup or pixel editing. BODY-only visual sequence: source mechanical phases and inventory/duel synchronization remain separate. BODY-only aimed-shoulder posture, bracing, recoil absorption and same-facing return, with exactly one caster on continuous pedestal bolted to pauldron. Turret starts already aligned; body alignment is shown through stance/shoulder changes. Charge/muzzle flash/plasma projectile are deliberately absent from BODY and require separate entity/effect integration. These drawings do not implement an attack, projectile, cost or guarantee. Right recoil was redrawn with horizontal head and visible mount, avoiding the prior hidden turret. Two independent pages preserve six real stages per direction; every admitted PNG remains byte-identical to imagegen output. Independent engine and QA source/anatomy review approved as BODY study only; public PNG copies byte-identical and SHA-verified.
A46: scar | B46: M_F003_S4 | C46: S4 | D46: Garde de chasseur | E46: 05_MOVES_PROPOSES | F46: S7 | G46: ADMIS_DEUX_SENS | H46: 6 | I46: 6 | J46: 6 | K46: 6 | L46: ETUDE_SEULE | N46: PASS_CIBLE_BODY | O46: scar-special-s4-body-v100 | P46: 32f2ee8e4fd801e7ca677a54862f2bd0123a2e78d12c015f64b50ab28184c380 | Q46: fc8e1c6c81de62d8966e04746ed0751b0eeefc62f0458728c818896ad79972f4 | R46: 5 / 14 / 30 | S46: Native BODY artwork, source action choreography, alpha separation and manually reviewed foot pivots; not confirmation of combat mechanics. | T46: M_F003_S4 · Garde de chasseur Commande 22+S · Selon trajectoire / prototype · Spécial Arme : Gantelet / bras Dévie une frappe de contact, puis répond du coude. Échoue contre une projection et ne renvoie pas automatiquement les tirs. Préparation / actif / récupération : 5 / 14 / 30 images · dégâts 85 · coût 10 % Contre-jeu : Feinter, attendre la fin de fenêtre ou projeter. Technique proposée pour The Pit ; valeurs à équilibrer. Ne pas anticiper la marque au début du récit ; alliance avec Lex, fin alternative signalée. Corps : F003_ACT_S4 Entité : Aucune · équipement : Corps / gantelet de la tenue Adaptation originale sourcée · Cible de design ; le coût est un % de jauge, pas la valeur actuelle du moteur | U46: Admission visuelle de portée limitée. Entités, accessoires, variantes, mécanique source et preuve finale restent distincts. Six independently articulated drawings for each facing, with preparation, equipment action and recovery. Feet and complete weapon tips visually inspected; all12source cells have clear alpha gutters and zero visible border pixels. One fixed bodyHeightPx from the first upright head-to-feet reference for the whole atlas, no per-pose fitting. Horizontal pivots manually reviewed between actual supporting feet; vertical candidates reviewed as feet, not weapon tips. Original PNG copied byte-identically. No mirror, rigging, crop rewrite, chroma cleanup or pixel editing. BODY-only visual sequence: source mechanical phases and inventory/duel synchronization remain separate. Wrist blades retracted; outward bent-forearm deflection then sharply bent protruding elbow counter, hand tucked against torso. No jab, projectile reflection or mechanical invulnerability claimed. Admission indépendante BODY après seconde revue. Aucune mécanique de super/contre, scène complète, gravure/ombre, Lex, récompense ou état de victime n’est créée par ce lecteur.
A47: scar | B47: M_F003_SUPER | C47: SUPER | D47: La signature — Duel à portée moyenne | E47: 05_MOVES_PROPOSES | F47: T7 | G47: ADMIS_DEUX_SENS | H47: 6 | I47: 6 | J47: 6 | K47: 6 | L47: ETUDE_SEULE | N47: PASS_CIBLE_BODY | O47: scar-special-super-body-v100 | P47: 32f2ee8e4fd801e7ca677a54862f2bd0123a2e78d12c015f64b50ab28184c380 | Q47: fc8e1c6c81de62d8966e04746ed0751b0eeefc62f0458728c818896ad79972f4 | R47: 24 / 8 / 48 | S47: Native BODY artwork, source action choreography, alpha separation and manually reviewed foot pivots; not confirmation of combat mechanics. | T47: M_F003_SUPER · La signature — Duel à portée moyenne Commande 236236+S · Ouverture bloquable · Super Arme : Combistick Confirme un contact court, puis prolonge « Allonge télescopique » dans une séquence à caméra bornée. Si le premier contact est gardé, la scène ne se déclenche pas. Préparation / actif / récupération : 24 / 8 / 48 images · dégâts 280 · coût 100 % Contre-jeu : Garder l'amorce ou sortir de portée ; récupération longue si manqué. Pas de nouveaux pouvoirs. Réutilise uniquement armes/entités autorisées pour le costume ; la cinématique n'efface pas les blessures. Corps : F003_ACT_SUPER Entité : Aucune · équipement : W_F003_combistick Adaptation originale sourcée · Super original non implémenté | U47: Admission visuelle de portée limitée. Entités, accessoires, variantes, mécanique source et preuve finale restent distincts. Six independently articulated drawings for each facing, with preparation, equipment action and recovery. Feet and complete weapon tips visually inspected; all12source cells have clear alpha gutters and zero visible border pixels. One fixed bodyHeightPx from the first upright head-to-feet reference for the whole atlas, no per-pose fitting. Horizontal pivots manually reviewed between actual supporting feet; vertical candidates reviewed as feet, not weapon tips. Original PNG copied byte-identically. No mirror, rigging, crop rewrite, chroma cleanup or pixel editing. BODY-only visual sequence: source mechanical phases and inventory/duel synchronization remain separate. Short butt opening, telescopic extension, full thrust, withdrawal and reset. Hit-confirm/cost/collision mechanics are source targets, not implemented by this BODY atlas. Admission indépendante BODY après seconde revue. Aucune mécanique de super/contre, scène complète, gravure/ombre, Lex, récompense ou état de victime n’est créée par ce lecteur.
... A56: scar | B56: CIN_F003_CLEMENCE | C56: CLEMENCE | D56: Le duel suffit | E56: 07_PRESENTATIONS | F56: J7 | G56: ADMIS_DEUX_SENS | H56: 6 | I56: 6 | J56: 6 | K56: 6 | L56: ETUDE_SEULE | N56: PASS_CIBLE_BODY | O56: scar-special-clemence-body-v100 | P56: 32f2ee8e4fd801e7ca677a54862f2bd0123a2e78d12c015f64b50ab28184c380 | Q56: fc8e1c6c81de62d8966e04746ed0751b0eeefc62f0458728c818896ad79972f4 | R56: Présentation : durées source proposées | S56: Native BODY artwork, source action choreography, alpha separation and manually reviewed foot pivots; not confirmation of combat mechanics. | T56: CIN_F003_CLEMENCE · Le duel suffit Scar désarme l'adversaire, recule d'un pas et lui laisse reprendre son souffle. Il reprend l'objet de la mission sans prélever de trophée anatomique. Déclenchement : Version d'entraînement / allié / option violence réduite ; même durée de sortie. 0–1 s : intention lisible ; 1–3 s : geste ; 3–5 s : pose de sortie. Taunt cible 0,8–1,2 s. Durées proposées. Sprite : F003_CIN_CLEMENCE · objets : E_F003_shuriken ; E_F003_plasma Lore : Ne pas anticiper la marque au début du récit ; alliance avec Lex, fin alternative signalée. Adaptation / embranchement alternatif | U56: Admission visuelle de portée limitée. Entités, accessoires, variantes, mécanique source et preuve finale restent distincts. Six independently articulated drawings for each facing, with preparation, equipment action and recovery. Feet and complete weapon tips visually inspected; all six source cells per orientation have clear alpha gutters and zero visible border pixels. One fixed body reference per native page, no per-pose fitting. Horizontal pivots manually reviewed between actual supporting feet; vertical candidates reviewed as feet, not weapon tips. Original PNG copied byte-identically. No mirror, rigging, crop rewrite, chroma cleanup or pixel editing. BODY-only visual sequence: source mechanical phases and inventory/duel synchronization remain separate. Controlled lateral spear action, open stop hand, step back, ground reach and neutral missiontoken retrieval, calm exit. Spear keeps ONE frontpoint and a blunt rearend throughout; no secondtip appears after the stopgesture. Exactly two arms and continuous ownedweapon grip. Opponent, targetweapon and actual missionobject provenance remain scene dependencies; BODY grants no disarm mechanic, inventoryreward or anatomicaltrophy. Two independent pages preserve six real stages per direction; every admitted PNG remains byte-identical to imagegen output. Independent engine and QA source/anatomy review approved as BODY study only; fixed mask-to-soles references per native page, public copies byte-identical and SHA-verified.

Sheet OrientationsV100
A1: 104 orientations natives · frames et pixels distincts
A2: Une tenue répétée ne crée pas un dessin inédit ; les pages et leurs empreintes restent explicites.
A3: Synthèse : SyntheseV100 · filtres ligne 4 · en-têtes figés
A4: Personnage | B4: Geste source | C4: Cellule | D4: Orientation | E4: État art | F4: Frames référencées | G4: Dessins distincts | H4: Clips natifs | I4: Pages et SHA-256 | J4: Clips, rectangles, pivots, durées et pixels SHA
A5: feral-hunter | B5: M_F006_5L | C5: D10 | D5: right | E5: ADMIS_ETUDE | F5: 3 | G5: 3 | H5: workbook.M_F006_5L | I5: /game/sprites/v100/pit/feral/001-normals-5l-5m.png · cc17f91b2471c6731d3449983d35cf627162ae4803cafdfed997007354fc5735 | J5: workbook.M_F006_5L[0] · /game/sprites/v100/pit/feral/001-normals-5l-5m.png · rect 0,0,486,270 · pivot 263,260 · 5 ticks60 · 0557aa31458d3d200be53dca66b89f8747bbe633b143fd068e3eaf167ccbe57b workbook.M_F006_5L[1] · /game/sprites/v100/pit/feral/001-normals-5l-5m.png · rect 485,0,562,270 · pivot 253,260 · 3 ticks60 · 11ae1ffbb9beed8eebb042c6510348de8a55562a0297030f23099dfcffc3eb96 workbook.M_F006_5L[2] · /game/sprites/v100/pit/feral/001-normals-5l-5m.png · rect 1046,0,490,263 · pivot 195,259 · 10 ticks60 · 66cc49885e991a7c17e9cce386c835349b47934023994a9920c3ae1ef2b5f336
A6: feral-hunter | B6: M_F006_5L | C6: D10 | D6: left | E6: ADMIS_ETUDE | F6: 3 | G6: 3 | H6: workbook.M_F006_5L | I6: /game/sprites/v100/pit/feral/001-normals-5l-5m.png · cc17f91b2471c6731d3449983d35cf627162ae4803cafdfed997007354fc5735 | J6: workbook.M_F006_5L[0] · /game/sprites/v100/pit/feral/001-normals-5l-5m.png · rect 0,269,486,246 · pivot 286,241 · 5 ticks60 · 3a1ee86aa6355a2d7f534a4d82dd5ab0c71631be9cd48fa1723559b62393d9d5 workbook.M_F006_5L[1] · /game/sprites/v100/pit/feral/001-normals-5l-5m.png · rect 485,269,562,246 · pivot 310,244 · 3 ticks60 · f9a203db64b01202f333c0b90d78ffcb1144f098184ff937464e93ccb700f752 workbook.M_F006_5L[2] · /game/sprites/v100/pit/feral/001-normals-5l-5m.png · rect 1046,262,490,256 · pivot 228,250 · 10 ticks60 · 72db8080443d0124ba1cda830e97ec4464a33378b687f8ffe246c88ffb7febc6
A7: feral-hunter | B7: M_F006_5M | C7: E10 | D7: right | E7: ADMIS_ETUDE | F7: 3 | G7: 3 | H7: workbook.M_F006_5M | I7: /game/sprites/v100/pit/feral/007-stand-5m-forward.png · c1b95635c5581dd0fa520e779e461433528640a1e83f2b0488ad05bc1acdcdbd | J7: workbook.M_F006_5M[0] · /game/sprites/v100/pit/feral/007-stand-5m-forward.png · rect 0,0,504,511 · pivot 250.5,500 · 9 ticks60 · a024f17a5f812723e61af434187653aa4719bef1088893c9166b4f2df6b32fb9 workbook.M_F006_5M[1] · /game/sprites/v100/pit/feral/007-stand-5m-forward.png · rect 503,0,590,511 · pivot 277,502 · 4 ticks60 · bd9c2b7daae85d86636f975185edb7e3a8d601f117ec24e7f7def997f4b678af workbook.M_F006_5M[2] · /game/sprites/v100/pit/feral/007-stand-5m-forward.png · rect 1092,0,444,511 · pivot 183,500 · 16 ticks60 · 0a348fdc648918c5e262473d7e7ea238499c99f192270072340479f33ce61541
A8: feral-hunter | B8: M_F006_5M | C8: E10 | D8: left | E8: ADMIS_ETUDE | F8: 3 | G8: 3 | H8: workbook.M_F006_5M | I8: /game/sprites/v100/pit/feral/007-stand-5m-forward.png · c1b95635c5581dd0fa520e779e461433528640a1e83f2b0488ad05bc1acdcdbd | J8: workbook.M_F006_5M[0] · /game/sprites/v100/pit/feral/007-stand-5m-forward.png · rect 0,510,480,514 · pivot 279,482 · 9 ticks60 · 3bd8fb8f7815e1d9c55e2559fcd22d9e9197775d3adc2dcb6892176e3bfb0ef5 workbook.M_F006_5M[1] · /game/sprites/v100/pit/feral/007-stand-5m-forward.png · rect 479,510,597,514 · pivot 333,481 · 4 ticks60 · a7e2f7e936ce86ab45ceb30f7c927ee3b8b262bf1224e4d35c019f0fe97fa6b5 workbook.M_F006_5M[2] · /game/sprites/v100/pit/feral/007-stand-5m-forward.png · rect 1075,510,461,514 · pivot 241,482 · 16 ticks60 · 0e7100d152cfb3332128e170d1083e70e246d145f71413245ad4b94a7c7fcaa5
A9: feral-hunter | B9: M_F006_5H | C9: F10 | D9: right | E9: ADMIS_ETUDE | F9: 5 | G9: 4 | H9: pit.stand.heavy.startup pit.stand.heavy.active pit.stand.heavy.recovery | I9: /game/sprites/v59/pit/feral/shield-right.png · a562123e1c19cc98b8614d479ef9f70b5499482142a8895f2aaaa7e8cd0953d2 | J9: pit.stand.heavy.startup[0] · /game/sprites/v59/pit/feral/shield-right.png · rect 0,0,768,504 · pivot 397,492 · 6 ticks60 · a1b88db38daa820e8d4a16508780ddfaa3488fd35302e2bcdf90558cd4a80431 pit.stand.heavy.startup[1] · /game/sprites/v59/pit/feral/shield-right.png · rect 768,0,768,504 · pivot 294,493 · 7 ticks60 · c623e3178b4dd24f1c8922ea638c2a6dba684ed861d074bd271383db7283ff77 pit.stand.heavy.active[0] · /game/sprites/v59/pit/feral/shield-right.png · rect 0,504,850,520 · pivot 391,479 · 5 ticks60 · 9196b355deb865e26665c0fdaca2f7408739a56fb0019f739d3c12297a6011b7 pit.stand.heavy.recovery[0] · /game/sprites/v59/pit/feral/shield-right.png · rect 0,504,850,520 · pivot 391,479 · 8 ticks60 · 9196b355deb865e26665c0fdaca2f7408739a56fb0019f739d3c12297a6011b7 pit.stand.heavy.recovery[1] · /game/sprites/v59/pit/feral/shield-right.png · rect 850,504,686,520 · pivot 246,478 · 14 ticks60 · 171a854be7309fda53aad7f2b1f2c0ae29b81e9897a1130fa0b97f61874af48f
A10: feral-hunter | B10: M_F006_5H | C10: F10 | D10: left | E10: ADMIS_ETUDE | F10: 5 | G10: 4 | H10: pit.stand.heavy.startup pit.stand.heavy.active pit.stand.heavy.recovery | I10: /game/sprites/v59/pit/feral/shield-left.png · b5f2f91c9beb78c9d78bd83f30ae40af54f3f5546e919a6016ac3299eff27585 | J10: pit.stand.heavy.startup[0] · /game/sprites/v59/pit/feral/shield-left.png · rect 0,0,820,490 · pivot 518,480 · 6 ticks60 · bed3ae060a6a9299fb5e28b9cf1211f727d94a9193d175508a4e3265cd3e0ad1 pit.stand.heavy.startup[1] · /game/sprites/v59/pit/feral/shield-left.png · rect 820,0,716,490 · pivot 369,479 · 7 ticks60 · 537ea667631c65e0389fc7eb58d24392ce2045e1debe08f376fe2a4eee8e3011 pit.stand.heavy.active[0] · /game/sprites/v59/pit/feral/shield-left.png · rect 0,490,875,534 · pivot 560,472 · 5 ticks60 · ff7b9069f139e2008a2a5f9c63325749ab9952a487bb121f6d077d9a7c09da25 pit.stand.heavy.recovery[0] · /game/sprites/v59/pit/feral/shield-left.png · rect 0,490,875,534 · pivot 560,472 · 8 ticks60 · ff7b9069f139e2008a2a5f9c63325749ab9952a487bb121f6d077d9a7c09da25 pit.stand.heavy.recovery[1] · /game/sprites/v59/pit/feral/shield-left.png · rect 875,490,661,534 · pivot 354,480 · 14 ticks60 · 58b02370e846f1b9e3b46f9e10ccc9b2f2bbda1085933dba8ffd674077758bcc
A11: feral-hunter | B11: M_F006_2L | C11: G10 | D11: right | E11: ADMIS_ETUDE | F11: 3 | G11: 3 | H11: workbook.M_F006_2L | I11: /game/sprites/v100/pit/feral/002-crouch-2l.png · 9cc63fc5a91565f6bb281c11138000e3b1078245581aabd65b60d53d372eb605 | J11: workbook.M_F006_2L[0] · /game/sprites/v100/pit/feral/002-crouch-2l.png · rect 375,0,367,505 · pivot 187.5,477 · 6 ticks60 · 945285422666c87b0f7b8a075e28306f460a08ba4228459b6d03dcbf78feb8c2 workbook.M_F006_2L[1] · /game/sprites/v100/pit/feral/002-crouch-2l.png · rect 741,0,430,505 · pivot 180.5,475 · 3 ticks60 · 3ad36382c8e1f5e545494fe312d54fca7d9f9e085a2eb57e679d506f979f1e15 workbook.M_F006_2L[2] · /game/sprites/v100/pit/feral/002-crouch-2l.png · rect 1170,0,366,505 · pivot 163,477 · 12 ticks60 · a21239de9a14737006ddda88646e7953ce11feee99d7a9eb6c3dab33601eebd5
A12: feral-hunter | B12: M_F006_2L | C12: G10 | D12: left | E12: ADMIS_ETUDE | F12: 3 | G12: 3 | H12: workbook.M_F006_2L | I12: /game/sprites/v100/pit/feral/013-crouch-2l-left.png · d6faa6692304c6191bc28f1ee1d3e8856603a62b263c320f3de4f9e7f169fdb6 | J12: workbook.M_F006_2L[0] · /game/sprites/v100/pit/feral/013-crouch-2l-left.png · rect 549,0,475,838 · pivot 254,715 · 6 ticks60 · aa6364611cbb77f65978493aa4f5f19c93404fc191e50b667be15b7340817e7b workbook.M_F006_2L[1] · /game/sprites/v100/pit/feral/013-crouch-2l-left.png · rect 0,837,598,699 · pivot 382.5,578 · 3 ticks60 · 3df4e682a5439fd174e993d9750683a2786c00285cb860dbc353a974a44d4979 workbook.M_F006_2L[2] · /game/sprites/v100/pit/feral/013-crouch-2l-left.png · rect 597,837,427,699 · pivot 222.5,592 · 12 ticks60 · e6a45deda8836fa98a9cab9528193d551c9e737bf7e2ed9505dceb33756cc256
A13: feral-hunter | B13: M_F006_2M | C13: H10 | D13: right | E13: ADMIS_ETUDE | F13: 3 | G13: 3 | H13: workbook.M_F006_2M | I13: /game/sprites/v100/pit/feral/005-crouch-2m.png · 91ab7a7ac6dc903dce4aa15ee2f39a9b8bf35113eb8d2bb3ea688debe610208f | J13: workbook.M_F006_2M[0] · /game/sprites/v100/pit/feral/005-crouch-2m.png · rect 0,425,499,277 · pivot 281,259 · 11 ticks60 · b46b788aedc6a6231cd5d4b479bb3a707e310fdad41c7a7aab352de57d3bf935 workbook.M_F006_2M[1] · /game/sprites/v100/pit/feral/005-crouch-2m.png · rect 498,425,552,277 · pivot 161,262 · 4 ticks60 · 52bd209f28a2db01923dbfbf3a77cadb86bbbf085957c79972f4358318b66f85 workbook.M_F006_2M[2] · /game/sprites/v100/pit/feral/005-crouch-2m.png · rect 1049,425,487,277 · pivot 180,260 · 21 ticks60 · d1025d38b5d53e79c2531ec86a9fae793d289e0d37e0559bf72ffae6a473be62
A14: feral-hunter | B14: M_F006_2M | C14: H10 | D14: left | E14: ADMIS_ETUDE | F14: 3 | G14: 3 | H14: workbook.M_F006_2M | I14: /game/sprites/v100/pit/feral/005-crouch-2m.png · 91ab7a7ac6dc903dce4aa15ee2f39a9b8bf35113eb8d2bb3ea688debe610208f | J14: workbook.M_F006_2M[0] · /game/sprites/v100/pit/feral/005-crouch-2m.png · rect 0,701,490,323 · pivot 306,271 · 11 ticks60 · d0d937e283a158579d400849cb53103102e3d86b35048349593f4bfeacb1ed68 workbook.M_F006_2M[1] · /game/sprites/v100/pit/feral/005-crouch-2m.png · rect 489,701,552,323 · pivot 406,274 · 4 ticks60 · 59e52d2fd0d976efec86c54c1dbc91f1532b96479581c2a08c69ee7e2b35b906 workbook.M_F006_2M[2] · /game/sprites/v100/pit/feral/005-crouch-2m.png · rect 1040,701,496,323 · pivot 215,272 · 21 ticks60 · 280f87e37297336afe41835106381c1c63234013b146beed3251cbb752af52e6
A15: feral-hunter | B15: M_F006_2H | C15: I10 | D15: right | E15: ADMIS_ETUDE | F15: 3 | G15: 3 | H15: workbook.M_F006_2H | I15: /game/sprites/v100/pit/feral/011-crouch-2h-right.png · 4f094d0f2d3cccadd5f661158d4b4f412c1d769da823fca2e9e00cabd5b3d40d | J15: workbook.M_F006_2H[0] · /game/sprites/v100/pit/feral/011-crouch-2h-right.png · rect 489,0,535,733 · pivot 273.5,696 · 14 ticks60 · 29f1d121175486b728a2c8fb5aac5a754250904195d9c7bf42953ada98f3065d workbook.M_F006_2H[1] · /game/sprites/v100/pit/feral/011-crouch-2h-right.png · rect 0,732,545,804 · pivot 249.5,753 · 5 ticks60 · 72deb45e485ecfead67c40018172abb335c91f3e373d75d846e53256f1df4355 workbook.M_F006_2H[2] · /game/sprites/v100/pit/feral/011-crouch-2h-right.png · rect 544,732,480,804 · pivot 250.5,748 · 29 ticks60 · 6666790f9af392a8fb4cfe821444b56e9776a1df6c39adff0f923e9563dcaafb
A16: feral-hunter | B16: M_F006_2H | C16: I10 | D16: left | E16: ADMIS_ETUDE | F16: 3 | G16: 3 | H16: workbook.M_F006_2H | I16: /game/sprites/v100/pit/feral/012-crouch-2h-left.png · 1cf32461860771ded634e7ec9ba119a15f29c13f4ef5341d97c1ae5129042c6b | J16: workbook.M_F006_2H[0] · /game/sprites/v100/pit/feral/012-crouch-2h-left.png · rect 543,0,481,770 · pivot 259.5,718 · 14 ticks60 · 20a2f2ece3a0b669838fdf2c9e695a8f85561f637ee0d46e964d412aa100a22b workbook.M_F006_2H[1] · /game/sprites/v100/pit/feral/012-crouch-2h-left.png · rect 0,769,572,767 · pivot 346,679 · 5 ticks60 · 49b5a8f3bb5761aef115dfdf9c60888149ccb81558819e96963973a8fd53e9a6 workbook.M_F006_2H[2] · /game/sprites/v100/pit/feral/012-crouch-2h-left.png · rect 571,769,453,767 · pivot 244,676 · 29 ticks60 · b75d04d133f1335dc4143cf30c76dd9ea4ef3605d1437cc43576369cec03dadc
... A108: scar | B108: CIN_F003_CLEMENCE | C108: J7 | D108: left | E108: ADMIS_ETUDE | F108: 6 | G108: 6 | H108: workbook.CIN_F003_CLEMENCE | I108: /game/sprites/v100/pit/scar/scar-special-clemence-left.png · 559366b2e7d9c5d90f471f4cab4e0034b274540243148dd3adfd93c5717c5788 | J108: workbook.CIN_F003_CLEMENCE[0] · /game/sprites/v100/pit/scar/scar-special-clemence-left.png · rect 0,0,731,371 · pivot 443,315 · 30 ticks60 · 3159bd8f570dcebc70bf4593c930fa5529659eab51091771a6a09970e72a2c37 workbook.CIN_F003_CLEMENCE[1] · /game/sprites/v100/pit/scar/scar-special-clemence-left.png · rect 730,0,806,371 · pivot 438,314 · 30 ticks60 · 53861f450b918ec8725debd92a6e8979e7a45049a2e95d91dabb5f8be7cf8c2a workbook.CIN_F003_CLEMENCE[2] · /game/sprites/v100/pit/scar/scar-special-clemence-left.png · rect 0,370,755,322 · pivot 445,271 · 60 ticks60 · 43d4883da3bc51aa925626d74953596b09e893fb2029be77aebcc60852d0da3d workbook.CIN_F003_CLEMENCE[3] · /game/sprites/v100/pit/scar/scar-special-clemence-left.png · rect 754,370,782,322 · pivot 411,277 · 60 ticks60 · ef91ba5ca13dea2151c851657f8a7dd8e04baa769254b28f469c8c80439d1442 workbook.CIN_F003_CLEMENCE[4] · /game/sprites/v100/pit/scar/scar-special-clemence-left.png · rect 0,691,797,333 · pivot 481,263 · 60 ticks60 · 60adb02e5e6f4b5779afe290da029b6d882155e6b53d2cd7acc5bfef821be263 workbook.CIN_F003_CLEMENCE[5] · /game/sprites/v100/pit/scar/scar-special-clemence-left.png · rect 796,691,740,333 · pivot 364,267 · 60 ticks60 · 60ecee94ac3e72fa8f2bcc18f88ebe8c39588dc22013f8640796e75a674596a2

Sheet ContactsV100
A1: Homeworld · habitants déjà présents devenus abordables
A2: Distance, niveau, visibilité et sol sont recontrôlés à l’interaction ; aucune nouvelle identité créée.
A3: Synthèse : SyntheseV100 · filtres ligne 4 · en-têtes figés
A4: ID habitant | B4: Nom | C4: Travail | D4: Étage | E4: Quartier | F4: Rayon strict | G4: Portée / preuve
A5: urban-v78:extra:quay-0 | B5: Nom propre non renseigné | C5: Porteur de cargaisons | D5: 0 | E5: port | F5: 96 | G5: Habitant déjà dessiné et conservé ; approche réelle sur même étage et sol libre. Un contact navigateur ciblé, pas 16 parcours navigateur.
A6: urban-v78:extra:quay-1 | B6: Nom propre non renseigné | C6: Navigatrice | D6: 0 | E6: port | F6: 96 | G6: Habitant déjà dessiné et conservé ; approche réelle sur même étage et sol libre. Un contact navigateur ciblé, pas 16 parcours navigateur.
A7: urban-v78:extra:quay-2 | B7: Nom propre non renseigné | C7: Tailleur de parures | D7: 0 | E7: port | F7: 96 | G7: Habitant déjà dessiné et conservé ; approche réelle sur même étage et sol libre. Un contact navigateur ciblé, pas 16 parcours navigateur.
A8: urban-v78:extra:quay-3 | B8: Nom propre non renseigné | C8: Navigatrice | D8: 0 | E8: port | F8: 96 | G8: Habitant déjà dessiné et conservé ; approche réelle sur même étage et sol libre. Un contact navigateur ciblé, pas 16 parcours navigateur.
A9: urban-v78:extra:quay-4 | B9: Nom propre non renseigné | C9: Porteur de cargaisons | D9: 0 | E9: port | F9: 96 | G9: Habitant déjà dessiné et conservé ; approche réelle sur même étage et sol libre. Un contact navigateur ciblé, pas 16 parcours navigateur.
A10: urban-v78:extra:quay-5 | B10: Nom propre non renseigné | C10: Navigatrice | D10: 0 | E10: port | F10: 96 | G10: Habitant déjà dessiné et conservé ; approche réelle sur même étage et sol libre. Un contact navigateur ciblé, pas 16 parcours navigateur.
A11: urban-v78:extra:quay-6 | B11: Nom propre non renseigné | C11: Tailleur de parures | D11: 0 | E11: port | F11: 96 | G11: Habitant déjà dessiné et conservé ; approche réelle sur même étage et sol libre. Un contact navigateur ciblé, pas 16 parcours navigateur.
A12: urban-v78:extra:lower-0 | B12: Nom propre non renseigné | C12: Émissaire de clan | D12: -1A | E12: undercity | F12: 96 | G12: Habitant déjà dessiné et conservé ; approche réelle sur même étage et sol libre. Un contact navigateur ciblé, pas 16 parcours navigateur.
A13: urban-v78:extra:lower-2 | B13: Nom propre non renseigné | C13: Porteur de minerai | D13: -1A | E13: undercity | F13: 96 | G13: Habitant déjà dessiné et conservé ; approche réelle sur même étage et sol libre. Un contact navigateur ciblé, pas 16 parcours navigateur.
A14: urban-v78:extra:lower-3 | B14: Nom propre non renseigné | C14: Émissaire de clan | D14: -1A | E14: undercity | F14: 96 | G14: Habitant déjà dessiné et conservé ; approche réelle sur même étage et sol libre. Un contact navigateur ciblé, pas 16 parcours navigateur.
A15: urban-v78:extra:lower-5 | B15: Nom propre non renseigné | C15: Tailleur de parures | D15: -1A | E15: undercity | F15: 96 | G15: Habitant déjà dessiné et conservé ; approche réelle sur même étage et sol libre. Un contact navigateur ciblé, pas 16 parcours navigateur.
A16: urban-v78:extra:lower-6 | B16: Nom propre non renseigné | C16: Aspirant | D16: -1A | E16: undercity | F16: 96 | G16: Habitant déjà dessiné et conservé ; approche réelle sur même étage et sol libre. Un contact navigateur ciblé, pas 16 parcours navigateur.
... A20: urban-v84:kennel-care | B20: Nom propre non renseigné | C20: Soigneuse des chiens de chasse | D20: 0 | E20: port | F20: 96 | G20: Habitant déjà dessiné et conservé ; approche réelle sur même étage et sol libre. Un contact navigateur ciblé, pas 16 parcours navigateur.

Sheet PlanetesV100
A1: 30 planètes · export courant conservant la provenance
A2: Cartes originales du projet ; continents physiques et régions administratives restent distincts.
A3: Synthèse : SyntheseV100 · filtres ligne 4 · en-têtes figés
A4: ID | B4: Planète | C4: Famille | D4: Biome | E4: Surface non jouable | F4: Continents | G4: Régions | H4: Territoires | I4: Routes connectées | J4: Provenance
A5: korthas | B5: Korthas | C5: classic | D5: temperate | E5: Mers de cobalt | F5: 5 | G5: 6 | H5: 36 | I5: TRUE | J5: Noms et règles V3 ; géographie originale V96/V97
A6: thalassa | B6: Thalassa | C6: classic | D6: jungle | E6: Lagons turquoise | F6: 3 | G6: 6 | H6: 36 | I6: TRUE | J6: Carte originale du projet ; pas une planète canonique certifiée
A7: vitriol | B7: Vitriol | C7: exotic | D7: swamp | E7: Acide émeraude | F7: 4 | G7: 6 | H7: 36 | I7: TRUE | J7: Carte originale du projet ; pas une planète canonique certifiée
A8: nivalis | B8: Nivalis | C8: classic | D8: snow | E8: Banquise azurée | F8: 6 | G8: 6 | H8: 36 | I8: TRUE | J8: Carte originale du projet ; pas une planète canonique certifiée
A9: serak | B9: Serak | C9: classic | D9: desert | E9: Mers de dunes ocre | F9: 2 | G9: 6 | H9: 36 | I9: TRUE | J9: Carte originale du projet ; pas une planète canonique certifiée
A10: pyroclaste | B10: Pyroclaste | C10: classic | D10: volcanic | E10: Lave incandescente | F10: 2 | G10: 6 | H10: 36 | I10: TRUE | J10: Carte originale du projet ; pas une planète canonique certifiée
A11: halycon | B11: Halycon | C11: classic | D11: salt | E11: Saumure rose | F11: 4 | G11: 6 | H11: 36 | I11: TRUE | J11: Carte originale du projet ; pas une planète canonique certifiée
A12: uranth | B12: Uranth | C12: exotic | D12: irradiated | E12: Nappes radioactives | F12: 4 | G12: 6 | H12: 36 | I12: TRUE | J12: Carte originale du projet ; pas une planète canonique certifiée
A13: amethys | B13: Améthys | C13: exotic | D13: crystal | E13: Océan de cristaux violets | F13: 6 | G13: 6 | H13: 36 | I13: TRUE | J13: Carte originale du projet ; pas une planète canonique certifiée
A14: mycelia | B14: Mycélia | C14: exotic | D14: fungal | E14: Nappes de spores | F14: 4 | G14: 6 | H14: 36 | I14: TRUE | J14: Carte originale du projet ; pas une planète canonique certifiée
A15: nebulis | B15: Nébulis | C15: classic | D15: mountain | E15: Brume des vallées | F15: 4 | G15: 6 | H15: 36 | I15: TRUE | J15: Carte originale du projet ; pas une planète canonique certifiée
A16: abyssia | B16: Abyssia | C16: classic | D16: ocean | E16: Fosses indigo | F16: 6 | G16: 6 | H16: 36 | I16: TRUE | J16: Carte originale du projet ; pas une planète canonique certifiée
... A34: nyctera | B34: Nyctéra | C34: exotic | D34: fungal | E34: Spores violettes | F34: 6 | G34: 6 | H34: 36 | I34: TRUE | J34: Carte originale du projet ; pas une planète canonique certifiée

Sheet OuvragesV100
A1: Ouvrages V6 · six dossiers toujours ouverts
A2: L’évacuation V100 ne clôt ni montures, ni quai, ni escale, ni les autres prérequis matériels.
A3: Synthèse : SyntheseV100 · filtres ligne 4 · en-têtes figés
A4: ID source | B4: Ouvrage | C4: Feuille | D4: Ligne | E4: Cellules source | F4: État runtime | G4: Adaptateur | H4: Reste / périmètre | I4: SHA source V6
A5: W3-S01 | B5: Poste de veille | C5: Structures de guerre | D5: 6 | E5: C6, D6, E6, F6, G6, H6, I6, J6, K6 | F5: INTEGRE_LIBRE | G5: watch | H5: Définition acceptée par le runtime libre actuel ; raccord campagne et certification globale non déduits. | I5: 87ad5d1a6eaf49f2908a4457ef3f97b8f34db481a24bbc121d2e924559b19183
A6: W3-S02 | B6: Abri de relève | C6: Structures de guerre | D6: 7 | E6: C7, D7, E7, F7, G7, H7, I7, J7, K7 | F6: INTEGRE_LIBRE | G6: rest | H6: Définition acceptée par le runtime libre actuel ; raccord campagne et certification globale non déduits. | I6: 87ad5d1a6eaf49f2908a4457ef3f97b8f34db481a24bbc121d2e924559b19183
A7: W3-S03 | B7: Cache logistique | C7: Structures de guerre | D7: 8 | E7: C8, D8, E8, F8, G8, H8, I8, J8, K8 | F7: INTEGRE_LIBRE | G7: stock | H7: Définition acceptée par le runtime libre actuel ; raccord campagne et certification globale non déduits. | I7: 87ad5d1a6eaf49f2908a4457ef3f97b8f34db481a24bbc121d2e924559b19183
A8: W3-S04 | B8: Atelier d’ancrage | C8: Structures de guerre | D8: 9 | E8: C9, D9, E9, F9, G9, H9, I9, J9, K9 | F8: INTEGRE_LIBRE | G8: repair | H8: Définition acceptée par le runtime libre actuel ; raccord campagne et certification globale non déduits. | I8: 87ad5d1a6eaf49f2908a4457ef3f97b8f34db481a24bbc121d2e924559b19183
A9: W3-S05 | B9: Balise de route | C9: Structures de guerre | D9: 10 | E9: C10, D10, E10, F10, G10, H10, I10, J10, K10 | F9: INTEGRE_LIBRE | G9: navigation | H9: Définition acceptée par le runtime libre actuel ; raccord campagne et certification globale non déduits. | I9: 87ad5d1a6eaf49f2908a4457ef3f97b8f34db481a24bbc121d2e924559b19183
A10: W3-S06 | B10: Plateforme de tir | C10: Structures de guerre | D10: 11 | E10: C11, D11, E11, F11, G11, H11, I11, J11, K11 | F10: INTEGRE_LIBRE | G10: platform | H10: Définition acceptée par le runtime libre actuel ; raccord campagne et certification globale non déduits. | I10: 87ad5d1a6eaf49f2908a4457ef3f97b8f34db481a24bbc121d2e924559b19183
A11: W3-S07 | B11: Seuil renforcé | C11: Structures de guerre | D11: 12 | E11: C12, D12, E12, F12, G12, H12, I12, J12, K12 | F11: INTEGRE_LIBRE | G11: defense | H11: Définition acceptée par le runtime libre actuel ; raccord campagne et certification globale non déduits. | I11: 87ad5d1a6eaf49f2908a4457ef3f97b8f34db481a24bbc121d2e924559b19183
A12: W3-S08 | B12: Pont de cordes | C12: Structures de guerre | D12: 13 | E12: C13, D13, E13, F13, G13, H13, I13, J13, K13 | F12: INTEGRE_LIBRE | G12: bridge | H12: Définition acceptée par le runtime libre actuel ; raccord campagne et certification globale non déduits. | I12: 87ad5d1a6eaf49f2908a4457ef3f97b8f34db481a24bbc121d2e924559b19183
A13: W3-S09 | B13: Quai léger | C13: Structures de guerre | D13: 14 | E13: C14, D14, E14, F14, G14, H14, I14, J14, K14 | F13: OUVERT | H13: Raccorder un quai à une rive praticable et à un transport réellement identifié ; pas de téléportation de cargaison. | I13: 87ad5d1a6eaf49f2908a4457ef3f97b8f34db481a24bbc121d2e924559b19183
A14: W3-S10 | B14: Aire de montures | C14: Structures de guerre | D14: 15 | E14: C15, D15, E15, F15, G15, H15, I15, J15, K15 | F14: OUVERT | H14: Identifier et déplacer les montures existantes, leurs gardiens et leur capacité ; ne pas créer une monture depuis un compteur. | I14: 87ad5d1a6eaf49f2908a4457ef3f97b8f34db481a24bbc121d2e924559b19183
A15: W3-S11 | B15: Poste de soin | C15: Structures de guerre | D15: 16 | E15: C16, D16, E16, F16, G16, H16, I16, J16, K16 | F15: INTEGRE_LIBRE | G15: medical | H15: Définition acceptée par le runtime libre actuel ; raccord campagne et certification globale non déduits. | I15: 87ad5d1a6eaf49f2908a4457ef3f97b8f34db481a24bbc121d2e924559b19183
A16: W3-S12 | B16: Relais de signaux | C16: Structures de guerre | D16: 17 | E16: C17, D17, E17, F17, G17, H17, I17, J17, K17 | F16: INTEGRE_LIBRE | G16: relay | H16: Définition acceptée par le runtime libre actuel ; raccord campagne et certification globale non déduits. | I16: 87ad5d1a6eaf49f2908a4457ef3f97b8f34db481a24bbc121d2e924559b19183
A17: W3-S13 | B17: Écran de confinement | C17: Structures de guerre | D17: 18 | E17: C18, D18, E18, F18, G18, H18, I18, J18, K18 | F17: OUVERT | H17: Raccorder l'alimentation et le coût réel de confinement ; aucun effet gratuit déduit de la description. | I17: 87ad5d1a6eaf49f2908a4457ef3f97b8f34db481a24bbc121d2e924559b19183
A18: W3-S14 | B18: Emplacement de duel | C18: Structures de guerre | D18: 19 | E18: C19, D19, E19, F19, G19, H19, I19, J19, K19 | F18: OUVERT | H18: Raccorder un duel accepté par ses participants et son résultat réel ; pas de victoire automatique. | I18: 87ad5d1a6eaf49f2908a4457ef3f97b8f34db481a24bbc121d2e924559b19183
A19: W3-S15 | B19: Station d’écoute | C19: Structures de guerre | D19: 20 | E19: C20, D20, E20, F20, G20, H20, I20, J20, K20 | F19: OUVERT | H19: Raccorder des sons enregistrés et situés, leur portée et leur occultation ; une direction de voix écrite n'est pas un son. | I19: 87ad5d1a6eaf49f2908a4457ef3f97b8f34db481a24bbc121d2e924559b19183
A20: W3-S16 | B20: Dépôt de retour | C20: Structures de guerre | D20: 21 | E20: C21, D21, E21, F21, G21, H21, I21, J21, K21 | F20: INTEGRE_LIBRE | G20: extraction | H20: Définition acceptée par le runtime libre actuel ; raccord campagne et certification globale non déduits. | I20: 87ad5d1a6eaf49f2908a4457ef3f97b8f34db481a24bbc121d2e924559b19183
A21: W3-S17 | B21: Anneau de treuils | C21: Structures de guerre | D21: 22 | E21: C22, D22, E22, F22, G22, H22, I22, J22, K22 | F21: INTEGRE_LIBRE | G21: hoist | H21: Définition acceptée par le runtime libre actuel ; raccord campagne et certification globale non déduits. | I21: 87ad5d1a6eaf49f2908a4457ef3f97b8f34db481a24bbc121d2e924559b19183
A22: W3-S18 | B22: Plateforme d’escale | C22: Structures de guerre | D22: 23 | E22: C23, D23, E23, F23, G23, H23, I23, J23, K23 | F22: OUVERT | H22: Raccorder un navire acquis et une route orbitale effective ; l'inspection documentaire ne donne ni navire ni voyage. | I22: 87ad5d1a6eaf49f2908a4457ef3f97b8f34db481a24bbc121d2e924559b19183

Sheet PitOuvertV100
A1: Six dossiers Pit historiques encore ouverts
A2: Les animations Feral/Scar ne ferment aucun de ces dossiers V63 ; cellules historiques conservées.
A3: Synthèse : SyntheseV100 · filtres ligne 4 · en-têtes figés
A4: ID source | B4: Dossier | C4: Cellules source | D4: Feuille des manques | E4: État historique | F4: Reste ouvert | G4: SHA source V54
